Workbook

Sheet 店舗コード
A2: 店舗名称
A3: FJALLRAVEN by 3NITY 札幌ステラプレイス | B3: 99 XXX
A4: FJALLRAVEN STORE OSAKA ALBi | B4: 99 XXX
A5: FJALLRAVEN STORE 新宿小田急ハルク | B5: 99 XXX
A6: フェールラーベンストア名古屋ファッションワン | B6: 04 名古屋
A7: FJALLRAVEN by 3NITY ｱﾐｭﾌﾟﾗｻﾞ博多 | B7: 99 XXX
A8: FJALLRAVEN by 3NITY TOKYO | B8: 07 TOKYO
A9: FJALLRAVEN STORE 石井山専新宿東口ビックロ | B9: 99 XXX
A10: FJALLRAVEN by 3NITY 新宿小田急ハルク | B10: 99 XXX
A11: FJALLRAVEN by 3NITY 博多阪急イングス | B11: 99 XXX
A12: FJALLERAVEN by 3NITYルクア大阪 | B12: 08 ルクア大阪
A13: ハルク売上 | B13: 99 XXX
A14: FJALLRAVEN by 3NITY ルクア大阪 | B14: 08 ルクア大阪
... A22: FJALLRAVEN by 3NITY 心斎橋パルコ | B22: 99 XXX
A23: 6142 | B23: 16 6142
A24: FJALLRAVEN by 3NITY玉川高島屋S・C | B24: 17 玉川高島屋
A25: FJALLRAVEN POP-UP | B25: 99 XXX
A26: FJALLRAVEN by 3NITY POPUP | B26: 19 NODE
A27: FJALLRAVEN by 3NITY 大丸心斎橋 | B27: 15 大丸心斎橋
A28: FJALLRAVEN POPUP NARITA | B28: 20 NARITA
A29: FJALLRAVEN by 3NITY TOKYO NODE | B29: 19 NODE

Sheet 営業日付別売上分析 貼り付け
A1: 店舗名称 | B1: 3rd Item No. | C1: 表記部門名1 | D1: StyleNo | E1: 商品名 | F1: ColorNo | G1: ColorName | H1: Size | I1: 数量 | J1: 店舗
A2: FJALLRAVEN STORE 名古屋ファッションワン | B2: 77292633S/M | C2: FJALLRAVEN | D2: 77292 | E2: Singi Gaiters | F2: 633 | G2: Dark Olive | H2: S/M | I2: 1 | J2: =VLOOKUP(A2,店舗コード!A:B,2,FALSE) -> 04 名古屋
A3: FJALLRAVEN by 3NITY 大丸心斎橋 | B3: 23225550X | C3: FJALLRAVEN | D3: 23225 | E3: High Coast Totepack | F3: 550 | G3: Black | H3: X | I3: 1 | J3: =VLOOKUP(A3,店舗コード!A:B,2,FALSE) -> 15 大丸心斎橋
A4: FJALLRAVEN by 3NITY 大丸心斎橋 | B4: 23225550X | C4: FJALLRAVEN | D4: 23225 | E4: High Coast Totepack | F4: 550 | G4: Black | H4: X | I4: -1 | J4: =VLOOKUP(A4,店舗コード!A:B,2,FALSE) -> 15 大丸心斎橋
A5: FJALLRAVEN by 3NITY 大丸心斎橋 | B5: 23225550X | C5: FJALLRAVEN | D5: 23225 | E5: High Coast Totepack | F5: 550 | G5: Black | H5: X | I5: 1 | J5: =VLOOKUP(A5,店舗コード!A:B,2,FALSE) -> 15 大丸心斎橋
A6: FJALLRAVEN by 3NITY SAPPORO HUTTE | B6: 77357520L/XL | C6: FJALLRAVEN | D6: 77357 | E6: Vidda Cap | F6: 520 | G6: Uncle Blue | H6: L/XL | I6: 1 | J6: =VLOOKUP(A6,店舗コード!A:B,2,FALSE) -> 10 ヒュッテ
A7: FJALLRAVEN by 3NITY SAPPORO HUTTE | B7: 77357520L/XL | C7: FJALLRAVEN | D7: 77357 | E7: Vidda Cap | F7: 520 | G7: Uncle Blue | H7: L/XL | I7: -1 | J7: =VLOOKUP(A7,店舗コード!A:B,2,FALSE) -> 10 ヒュッテ
A8: FJALLRAVEN POPUP NARITA | B8: 23225424X | C8: FJALLRAVEN | D8: 23225 | E8: High Coast Totepack | F8: 424 | G8: Blackberry | H8: X | I8: 1 | J8: =VLOOKUP(A8,店舗コード!A:B,2,FALSE) -> 20 NARITA
A9: FJALLRAVEN POPUP NARITA | B9: 23226424X | C9: FJALLRAVEN | D9: 23226 | E9: High Coast Pocket | F9: 424 | G9: Blackberry | H9: X | I9: 1 | J9: =VLOOKUP(A9,店舗コード!A:B,2,FALSE) -> 20 NARITA
A10: FJALLRAVEN by 3NITY SAPPORO HUTTE | B10: 77357520L/XL | C10: FJALLRAVEN | D10: 77357 | E10: Vidda Cap | F10: 520 | G10: Uncle Blue | H10: L/XL | I10: 1 | J10: =VLOOKUP(A10,店舗コード!A:B,2,FALSE) -> 10 ヒュッテ
A11: FJALLRAVEN by 3NITY SAPPORO HUTTE | B11: 79030X | C11: FJALLRAVEN | D11: 79030 | E11: Greenland Wax travel pack | H11: X | I11: 1 | J11: =VLOOKUP(A11,店舗コード!A:B,2,FALSE) -> 10 ヒュッテ
A12: FJALLRAVEN by 3NITY玉川高島屋S・C | B12: 23510126X | C12: FJALLRAVEN | D12: 23510 | E12: Kanken | F12: 126 | G12: Corn | H12: X | I12: 1 | J12: =VLOOKUP(A12,店舗コード!A:B,2,FALSE) -> 17 玉川高島屋
A13: FJALLRAVEN POPUP NARITA | B13: 23561126X | C13: FJALLRAVEN | D13: 23561 | E13: Kanken Mini | F13: 126 | G13: Corn | H13: X | I13: 1 | J13: =VLOOKUP(A13,店舗コード!A:B,2,FALSE) -> 20 NARITA
A14: FJALLRAVEN POPUP NARITA | B14: 23561457X | C14: FJALLRAVEN | D14: 23561 | E14: Kanken Mini | F14: 457 | G14: Pastel Lavender | H14: X | I14: 1 | J14: =VLOOKUP(A14,店舗コード!A:B,2,FALSE) -> 20 NARITA
A15: FJALLRAVEN STORE 名古屋ファッションワン | B15: 23524560X | C15: FJALLRAVEN | D15: 23524 | E15: Kanken Laptop 15 | F15: 560 | G15: Navy | H15: X | I15: 1 | J15: =VLOOKUP(A15,店舗コード!A:B,2,FALSE) -> 04 名古屋
A16: FJALLRAVEN POPUP NARITA | B16: 23803560X | C16: FJALLRAVEN | D16: 23803 | E16: Kanken no. 2 Laptop 15 | F16: 560 | G16: Navy | H16: X | I16: 1 | J16: =VLOOKUP(A16,店舗コード!A:B,2,FALSE) -> 20 NARITA
A17: FJALLRAVEN by 3NITY ルクア大阪 | B17: 24215560X | C17: FJALLRAVEN | D17: 24215 | E17: Gear Pocket | F17: 560 | G17: Navy | H17: X | I17: 1 | J17: =VLOOKUP(A17,店舗コード!A:B,2,FALSE) -> 08 ルクア大阪
A18: FJALLRAVEN STORE 名古屋ファッションワン | B18: 23349577X | C18: FJALLRAVEN | D18: 23349 | E18: Skule 20 | F18: 577 | G18: Nimbus Blue | H18: X | I18: 1 | J18: =VLOOKUP(A18,店舗コード!A:B,2,FALSE) -> 04 名古屋
A19: FJALLRAVEN STORE 名古屋ファッションワン | B19: 24213030X | C19: FJALLRAVEN | D19: 24213 | E19: Gear Bag | F19: 30 | G19: Dark Grey | H19: X | I19: 1 | J19: =VLOOKUP(A19,店舗コード!A:B,2,FALSE) -> 04 名古屋
A20: FJALLRAVEN STORE 名古屋ファッションワン | B20: 25862664X | C20: FJALLRAVEN | D20: 25862 | E20: Kanken Gear Bag | F20: 664 | G20: Frost Green | H20: X | I20: 1 | J20: =VLOOKUP(A20,店舗コード!A:B,2,FALSE) -> 04 名古屋
A21: 6142 | B21: 23200330620X | C21: FJALLRAVEN | D21: 23200330 | E21: High Coast Backpack 24 | F21: 620 | G21: Green | H21: X | I21: 1 | J21: =VLOOKUP(A21,店舗コード!A:B,2,FALSE) -> 16 6142
A22: 6142 | B22: 23226623X | C22: FJALLRAVEN | D22: 23226 | E22: High Coast Pocket | F22: 623 | G22: Mountain Green | H22: X | I22: 1 | J22: =VLOOKUP(A22,店舗コード!A:B,2,FALSE) -> 16 6142
A23: FJALLRAVEN STORE 名古屋ファッションワン | B23: 86984550S | C23: FJALLRAVEN | D23: 86984 | E23: HC Hydratic Trail Jacket M | F23: 550 | G23: Black | H23: S | I23: 1 | J23: =VLOOKUP(A23,店舗コード!A:B,2,FALSE) -> 04 名古屋
A24: FJALLRAVEN POPUP NARITA | B24: 23785620X | C24: FJALLRAVEN | D24: 23785 | E24: Kanken Keyring | F24: 620 | G24: Green | H24: X | I24: 1 | J24: =VLOOKUP(A24,店舗コード!A:B,2,FALSE) -> 20 NARITA
A25: FJALLRAVEN by 3NITY 大丸心斎橋 | B25: 23510664X | C25: FJALLRAVEN | D25: 23510 | E25: Kanken | F25: 664 | G25: Frost Green | H25: X | I25: 1 | J25: =VLOOKUP(A25,店舗コード!A:B,2,FALSE) -> 15 大丸心斎橋
A26: FJALLRAVEN by 3NITY 京王新宿 | B26: 23165550X | C26: FJALLRAVEN | D26: 23165 | E26: Ulvo Hip Pack Medium | F26: 550 | G26: Black | H26: X | I26: 1 | J26: =VLOOKUP(A26,店舗コード!A:B,2,FALSE) -> 13 京王新宿
A27: FJALLRAVEN by 3NITY TOKYO | B27: 23565633X | C27: FJALLRAVEN | D27: 23565 | E27: Kanken No.2 | F27: 633 | G27: Dark Olive | H27: X | I27: 1 | J27: =VLOOKUP(A27,店舗コード!A:B,2,FALSE) -> 07 TOKYO
A28: 6142 | B28: 23222620X | C28: FJALLRAVEN | D28: 23222 | E28: High Coast Foldsack 24 | F28: 620 | G28: Green | H28: X | I28: 1 | J28: =VLOOKUP(A28,店舗コード!A:B,2,FALSE) -> 16 6142
A29: FJALLRAVEN POPUP NARITA | B29: 23802424X | C29: FJALLRAVEN | D29: 23802 | E29: Kanken Weekender | F29: 424 | G29: Blackberry | H29: X | I29: 1 | J29: =VLOOKUP(A29,店舗コード!A:B,2,FALSE) -> 20 NARITA
A30: FJALLRAVEN by 3NITY ルクア大阪 | B30: 23796600X | C30: FJALLRAVEN | D30: 23796 | E30: Kanken Hip Pack | F30: 600 | G30: Mint Green | H30: X | I30: 1 | J30: =VLOOKUP(A30,店舗コード!A:B,2,FALSE) -> 08 ルクア大阪
A31: FJALLRAVEN POPUP NARITA | B31: 23227550X | C31: FJALLRAVEN | D31: 23227 | E31: High Coast Crossbody | F31: 550 | G31: Black | H31: X | I31: 1 | J31: =VLOOKUP(A31,店舗コード!A:B,2,FALSE) -> 20 NARITA
A32: FJALLRAVEN POPUP NARITA | B32: 77357570-050L/XL | C32: FJALLRAVEN | D32: 77357 | E32: Vidda Cap | F32: 570-050 | G32: Mountain Blue-Basalt | H32: L/XL | I32: 1 | J32: =VLOOKUP(A32,店舗コード!A:B,2,FALSE) -> 20 NARITA
A33: FJALLRAVEN by 3NITY ルクア大阪 | B33: 25863550X | C33: FJALLRAVEN | D33: 25863 | E33: Kanken Gear Pocket | F33: 550 | G33: Black | H33: X | I33: 1 | J33: =VLOOKUP(A33,店舗コード!A:B,2,FALSE) -> 08 ルクア大阪
A34: FJALLRAVEN by 3NITY ルクア大阪 | B34: 25863560X | C34: FJALLRAVEN | D34: 25863 | E34: Kanken Gear Pocket | F34: 560 | G34: Navy | H34: X | I34: 1 | J34: =VLOOKUP(A34,店舗コード!A:B,2,FALSE) -> 08 ルクア大阪
A35: 6142 | B35: 23510021-312X | C35: FJALLRAVEN | D35: 23510 | E35: Kanken | F35: 021-312 | G35: Fog-Pink | H35: X | I35: 1 | J35: =VLOOKUP(A35,店舗コード!A:B,2,FALSE) -> 16 6142
A36: FJALLRAVEN by 3NITY 大丸心斎橋 | B36: 23510501X | C36: FJALLRAVEN | D36: 23510 | E36: Kanken | F36: 501 | G36: Sky blue | H36: X | I36: 1 | J36: =VLOOKUP(A36,店舗コード!A:B,2,FALSE) -> 15 大丸心斎橋
A37: FJALLRAVEN by 3NITY 大丸心斎橋 | B37: 23346550X | C37: FJALLRAVEN | D37: 23346 | E37: Skule 28 | F37: 550 | G37: Black | H37: X | I37: 1 | J37: =VLOOKUP(A37,店舗コード!A:B,2,FALSE) -> 15 大丸心斎橋
A38: FJALLRAVEN by 3NITY ルクア大阪 | B38: 23346550X | C38: FJALLRAVEN | D38: 23346 | E38: Skule 28 | F38: 550 | G38: Black | H38: X | I38: 1 | J38: =VLOOKUP(A38,店舗コード!A:B,2,FALSE) -> 08 ルクア大阪
A39: FJALLRAVEN by 3NITY ルクア大阪 | B39: 23346577X | C39: FJALLRAVEN | D39: 23346 | E39: Skule 28 | F39: 577 | G39: Nimbus Blue | H39: X | I39: 1 | J39: =VLOOKUP(A39,店舗コード!A:B,2,FALSE) -> 08 ルクア大阪
A40: FJALLRAVEN by 3NITY ルクア大阪 | B40: 23785299X | C40: FJALLRAVEN | D40: 23785 | E40: Kanken Keyring | F40: 299 | G40: Dark Oak | H40: X | I40: 1 | J40: =VLOOKUP(A40,店舗コード!A:B,2,FALSE) -> 08 ルクア大阪
A41: FJALLRAVEN by 3NITY TOKYO | B41: 23200300354-228X | C41: FJALLRAVEN | D41: 23200300 | E41: VardagBackpack17 | F41: 354-228 | G41: Poppy Pink-Khaki Dust | H41: X | I41: 1 | J41: =VLOOKUP(A41,店舗コード!A:B,2,FALSE) -> 07 TOKYO
A42: FJALLRAVEN by 3NITY ルクア大阪 | B42: 23222016X | C42: FJALLRAVEN | D42: 23222 | E42: High Coast Foldsack 24 | F42: 16 | G42: Shark Grey | H42: X | I42: 1 | J42: =VLOOKUP(A42,店舗コード!A:B,2,FALSE) -> 08 ルクア大阪
A43: FJALLRAVEN POPUP NARITA | B43: 23803633X | C43: FJALLRAVEN | D43: 23803 | E43: Kanken no. 2 Laptop 15 | F43: 633 | G43: Dark Olive | H43: X | I43: 1 | J43: =VLOOKUP(A43,店舗コード!A:B,2,FALSE) -> 20 NARITA
A44: FJALLRAVEN by 3NITY ルクア大阪 | B44: 23525160X | C44: FJALLRAVEN | D44: 23525 | E44: Kanken Laptop 17 | F44: 160 | G44: Ochre | H44: X | I44: 1 | J44: =VLOOKUP(A44,店舗コード!A:B,2,FALSE) -> 08 ルクア大阪
A45: FJALLRAVEN POPUP NARITA | B45: 23510501-115X | C45: FJALLRAVEN | D45: 23510 | E45: Kanken | F45: 501-115 | G45: Sky Blue-Light Oak | H45: X | I45: 1 | J45: =VLOOKUP(A45,店舗コード!A:B,2,FALSE) -> 20 NARITA
A46: FJALLRAVEN by 3NITY ルクア大阪 | B46: 23710312X | C46: FJALLRAVEN | D46: 23710 | E46: Kanken Totepack | F46: 312 | G46: Pink | H46: X | I46: 1 | J46: =VLOOKUP(A46,店舗コード!A:B,2,FALSE) -> 08 ルクア大阪
A47: FJALLRAVEN by 3NITY ルクア大阪 | B47: 79060X | C47: FJALLRAVEN | D47: 79060 | E47: Greenland Wax | H47: X | I47: 1 | J47: =VLOOKUP(A47,店舗コード!A:B,2,FALSE) -> 08 ルクア大阪
A48: FJALLRAVEN by 3NITY TOKYO | B48: 23796560X | C48: FJALLRAVEN | D48: 23796 | E48: Kanken Hip Pack | F48: 560 | G48: Navy | H48: X | I48: 1 | J48: =VLOOKUP(A48,店舗コード!A:B,2,FALSE) -> 07 TOKYO
A49: FJALLRAVEN by 3NITY TOKYO | B49: 23505160X | C49: FJALLRAVEN | D49: 23505 | E49: Kanken Shoulder Pads | F49: 160 | G49: Ochre | H49: X | I49: 1 | J49: =VLOOKUP(A49,店舗コード!A:B,2,FALSE) -> 07 TOKYO
A50: FJALLRAVEN by 3NITY TOKYO | B50: 23510424X | C50: FJALLRAVEN | D50: 23510 | E50: Kanken | F50: 424 | G50: Blackberry | H50: X | I50: 1 | J50: =VLOOKUP(A50,店舗コード!A:B,2,FALSE) -> 07 TOKYO
A51: FJALLRAVEN by 3NITY TOKYO | B51: 23621550-907X | C51: FJALLRAVEN | D51: 23621 | E51: Kanken Rainbow Mini | F51: 550-907 | G51: Black-Rainbow Pattern | H51: X | I51: 1 | J51: =VLOOKUP(A51,店舗コード!A:B,2,FALSE) -> 07 TOKYO
A52: FJALLRAVEN by 3NITY TOKYO | B52: 23561312X | C52: FJALLRAVEN | D52: 23561 | E52: Kanken Mini | F52: 312 | G52: Pink | H52: X | I52: 1 | J52: =VLOOKUP(A52,店舗コード!A:B,2,FALSE) -> 07 TOKYO
A53: FJALLRAVEN by 3NITY TOKYO | B53: 23803560X | C53: FJALLRAVEN | D53: 23803 | E53: Kanken no. 2 Laptop 15 | F53: 560 | G53: Navy | H53: X | I53: 1 | J53: =VLOOKUP(A53,店舗コード!A:B,2,FALSE) -> 07 TOKYO
A54: FJALLRAVEN by 3NITY ルクア大阪 | B54: 24213633X | C54: FJALLRAVEN | D54: 24213 | E54: Gear Bag | F54: 633 | G54: Dark Olive | H54: X | I54: 1 | J54: =VLOOKUP(A54,店舗コード!A:B,2,FALSE) -> 08 ルクア大阪
A55: FJALLRAVEN by 3NITY ルクア大阪 | B55: 24216633X | C55: FJALLRAVEN | D55: 24216 | E55: Zip Wallet | F55: 633 | G55: Dark Olive | H55: X | I55: 1 | J55: =VLOOKUP(A55,店舗コード!A:B,2,FALSE) -> 08 ルクア大阪
A56: FJALLRAVEN by 3NITY 大丸心斎橋 | B56: 86977543S | C56: FJALLRAVEN | D56: 86977 | E56: Abisko Wool Logo SS M | F56: 543 | G56: Dawn Blue | H56: S | I56: 1 | J56: =VLOOKUP(A56,店舗コード!A:B,2,FALSE) -> 15 大丸心斎橋
A57: FJALLRAVEN by 3NITY 大丸心斎橋 | B57: 87153452S | C57: FJALLRAVEN | D57: 87153 | E57: FoxBoxyLogoTeeW | F57: 452 | G57: Lavender Mist | H57: S | I57: 1 | J57: =VLOOKUP(A57,店舗コード!A:B,2,FALSE) -> 15 大丸心斎橋
A58: 6142 | B58: 23227543X | C58: FJALLRAVEN | D58: 23227 | E58: High Coast Crossbody | F58: 543 | G58: Dawn Blue | H58: X | I58: 1 | J58: =VLOOKUP(A58,店舗コード!A:B,2,FALSE) -> 16 6142
A59: 6142 | B59: 23200307550X | C59: FJALLRAVEN | D59: 23200307 | E59: Abisko Softpack 16 | F59: 550 | G59: Black | H59: X | I59: 1 | J59: =VLOOKUP(A59,店舗コード!A:B,2,FALSE) -> 16 6142
A60: FJALLRAVEN by 3NITY TOKYO | B60: 23565577X | C60: FJALLRAVEN | D60: 23565 | E60: KankenNo.2 | F60: 577 | G60: Nimbus Blue | H60: X | I60: 1 | J60: =VLOOKUP(A60,店舗コード!A:B,2,FALSE) -> 07 TOKYO
A61: FJALLRAVEN by 3NITY 京王新宿 | B61: 23510501-115X | C61: FJALLRAVEN | D61: 23510 | E61: Kanken | F61: 501-115 | G61: Sky Blue-Light Oak | H61: X | I61: 1 | J61: =VLOOKUP(A61,店舗コード!A:B,2,FALSE) -> 13 京王新宿
A62: FJALLRAVEN by 3NITY TOKYO | B62: 23223550X | C62: FJALLRAVEN | D62: 23223 | E62: High Coast Hip Pack | F62: 550 | G62: Black | H62: X | I62: 1 | J62: =VLOOKUP(A62,店舗コード!A:B,2,FALSE) -> 07 TOKYO
A63: FJALLRAVEN by 3NITY TOKYO | B63: 87310550L | C63: FJALLRAVEN | D63: 87310 | E63: Fjallraven Logo T-shirt M | F63: 550 | G63: Black | H63: L | I63: 1 | J63: =VLOOKUP(A63,店舗コード!A:B,2,FALSE) -> 07 TOKYO
A64: FJALLRAVEN by 3NITY TOKYO | B64: 23200340037X | C64: FJALLRAVEN | D64: 23200340 | E64: Farden Crossbody | F64: 37 | G64: Coal Black | H64: X | I64: 1 | J64: =VLOOKUP(A64,店舗コード!A:B,2,FALSE) -> 07 TOKYO
A65: FJALLRAVEN by 3NITY TOKYO | B65: 23200408570-260X | C65: FJALLRAVEN | D65: 23200408 | E65: Samlaren Tote Pack 2A | F65: 570-260 | G65: Mountain Blue-Field Orange | H65: X | I65: 1 | J65: =VLOOKUP(A65,店舗コード!A:B,2,FALSE) -> 07 TOKYO
A66: FJALLRAVEN by 3NITY TOKYO | B66: 23227221X | C66: FJALLRAVEN | D66: 23227 | E66: High Coast Crossbody | F66: 221 | G66: Clay | H66: X | I66: 1 | J66: =VLOOKUP(A66,店舗コード!A:B,2,FALSE) -> 07 TOKYO
A67: FJALLRAVEN by 3NITY 大丸心斎橋 | B67: 23200303037X | C67: FJALLRAVEN | D67: 23200303 | E67: Farden Carry-On Pack | F67: 37 | G67: Coal Black | H67: X | I67: 1 | J67: =VLOOKUP(A67,店舗コード!A:B,2,FALSE) -> 15 大丸心斎橋
A68: FJALLRAVEN by 3NITY ルクア大阪 | B68: 23346050X | C68: FJALLRAVEN | D68: 23346 | E68: Skule 28 | F68: 50 | G68: Basalt | H68: X | I68: 1 | J68: =VLOOKUP(A68,店舗コード!A:B,2,FALSE) -> 08 ルクア大阪
A69: FJALLRAVEN by 3NITY 大丸心斎橋 | B69: 24221679X | C69: FJALLRAVEN | D69: 24221 | E69: Pocket | F69: 679 | G69: Deep Patina | H69: X | I69: 1 | J69: =VLOOKUP(A69,店舗コード!A:B,2,FALSE) -> 15 大丸心斎橋
A70: FJALLRAVEN POPUP NARITA | B70: 87313534M | C70: FJALLRAVEN | D70: 87313 | E70: 1960 Logo T-shirt M | F70: 534 | G70: Indigo Blue | H70: M | I70: 1 | J70: =VLOOKUP(A70,店舗コード!A:B,2,FALSE) -> 20 NARITA
A71: FJALLRAVEN by 3NITY TOKYO | B71: 23510501-115X | C71: FJALLRAVEN | D71: 23510 | E71: Kanken | F71: 501-115 | G71: Sky Blue-Light Oak | H71: X | I71: 1 | J71: =VLOOKUP(A71,店舗コード!A:B,2,FALSE) -> 07 TOKYO
A72: FJALLRAVEN by 3NITY TOKYO | B72: 23561221X | C72: FJALLRAVEN | D72: 23561 | E72: Kanken Mini | F72: 221 | G72: Clay | H72: X | I72: 1 | J72: =VLOOKUP(A72,店舗コード!A:B,2,FALSE) -> 07 TOKYO
A73: FJALLRAVEN STORE 名古屋ファッションワン | B73: 23510560X | C73: FJALLRAVEN | D73: 23510 | E73: Kanken | F73: 560 | G73: Navy | H73: X | I73: 1 | J73: =VLOOKUP(A73,店舗コード!A:B,2,FALSE) -> 04 名古屋
A74: FJALLRAVEN by 3NITY 大丸心斎橋 | B74: 23200335577X | C74: FJALLRAVEN | D74: 23200335 | E74: Skule 24 | F74: 577 | G74: Nimbus Blue | H74: X | I74: 1 | J74: =VLOOKUP(A74,店舗コード!A:B,2,FALSE) -> 15 大丸心斎橋
A75: 6142 | B75: 23349550X | C75: FJALLRAVEN | D75: 23349 | E75: Skule 20 | F75: 550 | G75: Black | H75: X | I75: 1 | J75: =VLOOKUP(A75,店舗コード!A:B,2,FALSE) -> 16 6142
A76: FJALLRAVEN by 3NITY TOKYO | B76: 23802424X | C76: FJALLRAVEN | D76: 23802 | E76: Kanken Weekender | F76: 424 | G76: Blackberry | H76: X | I76: 1 | J76: =VLOOKUP(A76,店舗コード!A:B,2,FALSE) -> 07 TOKYO
A77: FJALLRAVEN by 3NITY TOKYO | B77: 23510457X | C77: FJALLRAVEN | D77: 23510 | E77: Kanken | F77: 457 | G77: Pastel Lavender | H77: X | I77: 1 | J77: =VLOOKUP(A77,店舗コード!A:B,2,FALSE) -> 07 TOKYO
A78: FJALLRAVEN by 3NITY TOKYO | B78: 23510312X | C78: FJALLRAVEN | D78: 23510 | E78: Kanken | F78: 312 | G78: Pink | H78: X | I78: 1 | J78: =VLOOKUP(A78,店舗コード!A:B,2,FALSE) -> 07 TOKYO
A79: FJALLRAVEN STORE 名古屋ファッションワン | B79: 79258195M | C79: FJALLRAVEN | D79: 79258 | E79: Hatfield Hat | F79: 195 | G79: Sand Stone | H79: M | I79: 1 | J79: =VLOOKUP(A79,店舗コード!A:B,2,FALSE) -> 04 名古屋
A80: FJALLRAVEN by 3NITY玉川高島屋S・C | B80: 23565550X | C80: FJALLRAVEN | D80: 23565 | E80: Kanken No.2 | F80: 550 | G80: Black | H80: X | I80: 1 | J80: =VLOOKUP(A80,店舗コード!A:B,2,FALSE) -> 17 玉川高島屋
A81: FJALLRAVEN by 3NITY TOKYO | B81: 23791525X | C81: FJALLRAVEN | D81: 23791 | E81: Kanken Rain Cover | F81: 525 | G81: UN Blue | H81: X | I81: 1 | J81: =VLOOKUP(A81,店舗コード!A:B,2,FALSE) -> 07 TOKYO
A82: FJALLRAVEN POPUP NARITA | B82: 23803577X | C82: FJALLRAVEN | D82: 23803 | E82: Kanken no. 2 Laptop 15 | F82: 577 | G82: Nimbus Blue | H82: X | I82: 1 | J82: =VLOOKUP(A82,店舗コード!A:B,2,FALSE) -> 20 NARITA
A83: FJALLRAVEN by 3NITY TOKYO | B83: 23797424X | C83: FJALLRAVEN | D83: 23797 | E83: Kanken Sling | F83: 424 | G83: Blackberry | H83: X | I83: 1 | J83: =VLOOKUP(A83,店舗コード!A:B,2,FALSE) -> 07 TOKYO
A84: FJALLRAVEN by 3NITY ルクア大阪 | B84: 23200331560X | C84: FJALLRAVEN | D84: 23200331 | E84: High Coast Tote 30 | F84: 560 | G84: Navy | H84: X | I84: 1 | J84: =VLOOKUP(A84,店舗コード!A:B,2,FALSE) -> 08 ルクア大阪
A85: 6142 | B85: 23156550X | C85: FJALLRAVEN | D85: 23156 | E85: Greenland Pocket | F85: 550 | G85: Black | H85: X | I85: 1 | J85: =VLOOKUP(A85,店舗コード!A:B,2,FALSE) -> 16 6142
A86: 6142 | B86: 23200339620-221X | C86: FJALLRAVEN | D86: 23200339 | E86: Vardag Pocket Large | F86: 620-221 | G86: Green-Clay | H86: X | I86: 1 | J86: =VLOOKUP(A86,店舗コード!A:B,2,FALSE) -> 16 6142
A87: 6142 | B87: 77357232S/M | C87: FJALLRAVEN | D87: 77357 | E87: Vidda Cap | F87: 232 | G87: Buckwheat Brown | H87: S/M | I87: 1 | J87: =VLOOKUP(A87,店舗コード!A:B,2,FALSE) -> 16 6142
A88: 6142 | B88: 8118811848 | C88: FJALLRAVEN | D88: 81188 | E88: Ruaha Shorts M | F88: 118 | G88: Fossil | H88: 48 | I88: 1 | J88: =VLOOKUP(A88,店舗コード!A:B,2,FALSE) -> 16 6142
A89: FJALLRAVEN by 3NITY TOKYO | B89: 23797664-319X | C89: FJALLRAVEN | D89: 23797 | E89: Kanken Sling | F89: 664-319 | G89: Frost Green-Peach Pink | H89: X | I89: 1 | J89: =VLOOKUP(A89,店舗コード!A:B,2,FALSE) -> 07 TOKYO
A90: FJALLRAVEN by 3NITY ルクア大阪 | B90: 23345560X | C90: FJALLRAVEN | D90: 23345 | E90: Raven 28 | F90: 560 | G90: Navy | H90: X | I90: 1 | J90: =VLOOKUP(A90,店舗コード!A:B,2,FALSE) -> 08 ルクア大阪
A91: FJALLRAVEN by 3NITY玉川高島屋S・C | B91: 23510302X | C91: FJALLRAVEN | D91: 23510 | E91: Kanken | F91: 302 | G91: Chalk Rose | H91: X | I91: 1 | J91: =VLOOKUP(A91,店舗コード!A:B,2,FALSE) -> 17 玉川高島屋
A92: FJALLRAVEN by 3NITY 大丸心斎橋 | B92: 24221633X | C92: FJALLRAVEN | D92: 24221 | E92: Pocket | F92: 633 | G92: Dark Olive | H92: X | I92: 1 | J92: =VLOOKUP(A92,店舗コード!A:B,2,FALSE) -> 15 大丸心斎橋
A93: FJALLRAVEN by 3NITY 京王新宿 | B93: 23227614X | C93: FJALLRAVEN | D93: 23227 | E93: High Coast Crossbody | F93: 614 | G93: Patina Green | H93: X | I93: 1 | J93: =VLOOKUP(A93,店舗コード!A:B,2,FALSE) -> 13 京王新宿
A94: FJALLRAVEN POPUP NARITA | B94: 23349662X | C94: FJALLRAVEN | D94: 23349 | E94: Skule 20 | F94: 662 | G94: Deep Forest | H94: X | I94: 1 | J94: =VLOOKUP(A94,店舗コード!A:B,2,FALSE) -> 20 NARITA
A95: FJALLRAVEN POPUP NARITA | B95: 23200395550X | C95: FJALLRAVEN | D95: 23200395 | E95: Kanken Crossbody | F95: 550 | G95: Black | H95: X | I95: 1 | J95: =VLOOKUP(A95,店舗コード!A:B,2,FALSE) -> 20 NARITA
A96: FJALLRAVEN POPUP NARITA | B96: 23797664-319X | C96: FJALLRAVEN | D96: 23797 | E96: Kanken Sling | F96: 664-319 | G96: Frost Green-Peach Pink | H96: X | I96: 1 | J96: =VLOOKUP(A96,店舗コード!A:B,2,FALSE) -> 20 NARITA
A97: FJALLRAVEN POPUP NARITA | B97: 23227452X | C97: FJALLRAVEN | D97: 23227 | E97: HighCoastCrossbody | F97: 452 | G97: Lavender Mist | H97: X | I97: 1 | J97: =VLOOKUP(A97,店舗コード!A:B,2,FALSE) -> 20 NARITA
A98: FJALLRAVEN POPUP NARITA | B98: 23797664X | C98: FJALLRAVEN | D98: 23797 | E98: Kanken Sling | F98: 664 | G98: FROST GREEN | H98: X | I98: 1 | J98: =VLOOKUP(A98,店舗コード!A:B,2,FALSE) -> 20 NARITA
A99: FJALLRAVEN by 3NITY 大丸心斎橋 | B99: 79030X | C99: FJALLRAVEN | D99: 79030 | E99: Greenland Wax travel pack | H99: X | I99: 1 | J99: =VLOOKUP(A99,店舗コード!A:B,2,FALSE) -> 15 大丸心斎橋
A100: FJALLRAVEN by 3NITY ルクア大阪 | B100: 23505550X | C100: FJALLRAVEN | D100: 23505 | E100: Kanken Shoulder Pads | F100: 550 | G100: Black | H100: X | I100: 1 | J100: =VLOOKUP(A100,店舗コード!A:B,2,FALSE) -> 08 ルクア大阪
...

Sheet pivot
A4: a | B4: =TRIM(MID(B6,3,10)) -> 名古屋 | C4: =TRIM(MID(C6,3,10)) -> TOKYO | D4: =TRIM(MID(D6,3,10)) -> ルクア大阪 | E4: =TRIM(MID(E6,3,10)) -> ヒュッテ | F4: =TRIM(MID(F6,3,10)) -> 京王新宿 | G4: =TRIM(MID(G6,3,10)) -> 大丸心斎橋 | H4: =TRIM(MID(H6,3,10))*1 -> 6142 | I4: =TRIM(MID(I6,3,10)) -> 玉川高島屋 | J4: =TRIM(MID(J6,3,10)) -> NARITA | K4: =TRIM(MID(K6,3,10)) | L4: =MID(L6,3,10) | M4: =MID(M6,3,10) | N4: 1
A5: 合計 / 数量 | B5: 列ラベル
A6: 行ラベル | B6: 04 名古屋 | C6: 07 TOKYO | D6: 08 ルクア大阪 | E6: 10 ヒュッテ | F6: 13 京王新宿 | G6: 15 大丸心斎橋 | H6: 16 6142 | I6: 17 玉川高島屋 | J6: 20 NARITA
A7: 23524031X | F7: 1
A8: 23510302X | B8: 1 | C8: 8 | D8: 3 | E8: 2 | F8: 2 | G8: 1 | H8: 1 | I8: 4 | J8: 2
A9: 23620550-907X | B9: 1 | C9: 1 | D9: 1 | J9: 1
A10: 23622907X | D10: 2 | H10: 1 | J10: 1
A11: 23344050X | H11: 1
A12: 23804550X | C12: 2 | D12: 2 | E12: 1 | J12: 1
A13: 23345560X | C13: 1 | D13: 2
A14: 23510118X | C14: 1 | F14: 1
A15: 23510664X | C15: 1 | F15: 1 | G15: 1 | H15: 1
A16: 23227543X | C16: 2 | H16: 1 | J16: 1
A17: 23166550X | D17: 1 | J17: 1
A18: 23346550X | C18: 1 | D18: 1 | G18: 1 | I18: 1 | J18: 1
A19: 23223550X | C19: 2 | D19: 2
A20: 23510600X | C20: 2 | E20: 1 | F20: 1 | G20: 1 | J20: 1
A21: 23803560X | C21: 2 | J21: 1
A22: 23510021-312X | B22: 1 | E22: 1 | H22: 2 | J22: 2
A23: 23510501-115X | B23: 1 | C23: 4 | D23: 1 | E23: 3 | F23: 4 | I23: 2 | J23: 2
A24: 23561021-312X | C24: 1 | D24: 2 | G24: 1 | J24: 1
A25: 23505160X | C25: 1 | G25: 2
A26: 23797302X | C26: 1 | H26: 2
A27: 23510312X | B27: 1 | C27: 2 | D27: 3 | E27: 1 | F27: 2 | I27: 1 | J27: 3
A28: 23524560X | B28: 1 | D28: 1
A29: 23510560X | B29: 1 | C29: 1 | I29: 1
A30: 23227221X | C30: 2 | D30: 2 | F30: 1
A31: 23349550X | D31: 4 | H31: 1 | J31: 2
A32: 23623550-907X | D32: 1
A33: 23561457X | I33: 1 | J33: 1
A34: 23200339037X | B34: 1 | D34: 1
A35: 23200395550X | C35: 2 | D35: 1 | J35: 3
A36: 23523424X | I36: 1
A37: 23510540X | C37: 1 | D37: 1 | G37: 2 | I37: 1
A38: 23523501X | C38: 1
A39: 23510326X | E39: 1 | F39: 3 | G39: 3 | H39: 2
A40: 77357030S/M | D40: 2 | E40: 1 | G40: 2 | J40: 1
A41: 23510424X | C41: 2 | D41: 3 | G41: 1
A42: 87153300XS | J42: 1
A43: 23797118X | G43: 1
A44: 79060X | C44: 1 | D44: 5 | G44: 1
A45: 23561126X | J45: 1
A46: 23505664X | C46: 1 | J46: 1
A47: 23346662X | F47: 1
A48: 23797457X | C48: 2
A49: 77357570-050L/XL | J49: 1
A50: 23344560X | F50: 1
A51: 23226221X | D51: 1
A52: 23227452X | B52: 1 | J52: 1
A53: 23561228X | B53: 1
A54: 23510031X | C54: 1 | G54: 2 | I54: 1
A55: 23561326X | B55: 1 | C55: 1
A56: 23780664X | B56: 1 | C56: 1
A57: 23222560X | D57: 1
A58: 23565550X | I58: 1 | J58: 1
A59: 23505228X | C59: 1 | E59: 1
A60: 23226550X | C60: 3 | D60: 1 | G60: 2 | I60: 2 | J60: 1
A61: 23561046X | J61: 1
A62: 24221550X | C62: 1 | F62: 1
A63: 23223560X | G63: 1
A64: 23505326X | B64: 1 | C64: 2 | G64: 1
A65: 23226560X | G65: 1
A66: 23200334228-135X | C66: 1 | G66: 1
A67: 23154662X | F67: 1 | I67: 1
A68: 24216633X | D68: 1 | E68: 1 | H68: 1 | I68: 1
A69: 23510160X | B69: 1 | D69: 1 | G69: 1
A70: 23227550X | D70: 1 | J70: 1
A71: 23797664-319X | C71: 1 | F71: 1 | H71: 1 | J71: 2
A72: 77316633X | G72: 1
A73: 23345633X | D73: 1 | E73: 1 | F73: 1
A74: 23565238X | D74: 1
A75: 23796118X | D75: 1
A76: 23561501X | F76: 1
A77: 23200334031-424X | B77: 1 | I77: 1
A78: 23785299X | D78: 1 | E78: 1 | I78: 1
A79: 23344550-550X | C79: 2 | E79: 1
A80: 24221030X | B80: 1 | D80: 1
A81: 77277118L | B81: 1
A82: 23200301037X | D82: 2 | F82: 1 | J82: 1
A83: 23200338037X | F83: 1
A84: 23227424X | D84: 2 | J84: 1
A85: 23200338662X | D85: 1
A86: 23561550X | C86: 1 | J86: 1
A87: 23510126X | B87: 1 | C87: 1 | I87: 1
A88: 23510550X | C88: 1 | G88: 1
A89: 23227623X | E89: 1 | J89: 1
A90: 23223207X | D90: 1 | F90: 1
A91: 23200408570-260X | C91: 1 | I91: 1
A92: 13100237550S/M | D92: 1
A93: 23226620X | C93: 2 | D93: 1 | H93: 1 | J93: 1
A94: 23200335577X | G94: 1
A95: 23200303620X | C95: 1
A96: 24213633X | D96: 2 | F96: 1
A97: 24218030X | E97: 1
A98: 87310550L | C98: 1 | I98: 1
A99: 23524424X | C99: 2
A100: 23223424X | G100: 1
A101: 23226424X | J101: 3
A102: 23510457-916X | B102: 1
A103: 23803118X | E103: 1
...

Sheet ZOZOOIOI
A1: ZOZO | B1: 商品コード | C1: ブランド名 | D1: StyleNo | E1: 商品名 | F1: ColorNo | G1: ColorName | H1: Size | I1: 標準単価 | J1: 販売数量 | L1: 行ラベル | M1: 合計 / 販売数量 | O1: OIOI | P1: 商品コード | Q1: ブランド名 | R1: StyleNo | S1: 商品名 | T1: ColorNo | U1: ColorName | V1: Size | W1: 標準単価 | X1: 販売数量 | Z1: 行ラベル | AA1: 合計 / 販売数量
A2: =SUM(J:J) -> 44 | B2: 23561501-115X | C2: FJALLRAVEN | D2: 23561 | E2: Kanken Mini | F2: 501-115 | G2: Sky Blue-Light Oak | H2: X | I2: 12000 | J2: -1 | L2: 23344550X | M2: 2 | O2: =SUM(X:X) -> 28 | P2: 23510501X | Q2: FJALLRAVEN | R2: 23510 | S2: Kanken | T2: 501 | U2: Sky blue | V2: X | W2: 13000 | X2: -1 | Z2: 23505560X | AA2: 0
B3: 23510457X | C3: FJALLRAVEN | D3: 23510 | E3: Kanken | F3: 457 | G3: Pastel Lavender | H3: X | I3: 13000 | J3: 1 | L3: 23510312X | M3: 1 | P3: 23505560X | Q3: FJALLRAVEN | R3: 23505 | S3: Kanken Shoulder Pads | T3: 560 | U3: Navy | V3: X | W3: 3500 | X3: -1 | Z3: 23510312X | AA3: 1
B4: 23561021-312X | C4: FJALLRAVEN | D4: 23561 | E4: Kanken Mini | F4: 021-312 | G4: Fog-Pink | H4: X | I4: 12000 | J4: 1 | L4: 23510457X | M4: 1 | P4: 23346662X | Q4: FJALLRAVEN | R4: 23346 | S4: Skule 28 | T4: 662 | U4: Deep Forest | V4: X | W4: 14000 | X4: -1 | Z4: 23510501X | AA4: -1
B5: 23561326X | C5: FJALLRAVEN | D5: 23561 | E5: Kanken Mini | F5: 326 | G5: Ox Red | H5: X | I5: 12000 | J5: 1 | L5: 23510501X | M5: 1 | P5: 23525160X | Q5: FJALLRAVEN | R5: 23525 | S5: Kanken Laptop 17 | T5: 160 | U5: Ochre | V5: X | W5: 19000 | X5: 1 | Z5: 23510540X | AA5: 2
B6: 23223543X | C6: FJALLRAVEN | D6: 23223 | E6: High Coast Hip Pack | F6: 543 | G6: Dawn Blue | H6: X | I6: 6500 | J6: 1 | L6: 23510540X | M6: 1 | P6: 23510126X | Q6: FJALLRAVEN | R6: 23510 | S6: Kanken | T6: 126 | U6: Corn | V6: X | W6: 13000 | X6: 1 | Z6: 23510550X | AA6: 1
B7: 23349662X | C7: FJALLRAVEN | D7: 23349 | E7: Skule 20 | F7: 662 | G7: Deep Forest | H7: X | I7: 12000 | J7: 1 | L7: 23510600X | M7: 1 | P7: 23510312X | Q7: FJALLRAVEN | R7: 23510 | S7: Kanken | T7: 312 | U7: Pink | V7: X | W7: 13000 | X7: 1 | Z7: 23510021X | AA7: 2
B8: 23200330016X | C8: FJALLRAVEN | D8: 23200330 | E8: High Coast Backpack 24 | F8: 16 | G8: Shark Grey | H8: X | I8: 17000 | J8: 1 | L8: 23561021-312X | M8: 4 | P8: 23561046X | Q8: FJALLRAVEN | R8: 23561 | S8: Kanken Mini | T8: 46 | U8: Super grey | V8: X | W8: 12000 | X8: 1 | Z8: 23165550X | AA8: 1
B9: 23561021-312X | C9: FJALLRAVEN | D9: 23561 | E9: Kanken Mini | F9: 021-312 | G9: Fog-Pink | H9: X | I9: 12000 | J9: 1 | L9: 23561312X | M9: -1 | P9: 23510664X | Q9: FJALLRAVEN | R9: 23510 | S9: Kanken | T9: 664 | U9: Frost Green | V9: X | W9: 13000 | X9: 1 | Z9: 79030X | AA9: 1
B10: 23561326X | C10: FJALLRAVEN | D10: 23561 | E10: Kanken Mini | F10: 326 | G10: Ox Red | H10: X | I10: 12000 | J10: 1 | L10: 23620550-907X | M10: 2 | P10: 23510126X | Q10: FJALLRAVEN | R10: 23510 | S10: Kanken | T10: 126 | U10: Corn | V10: X | W10: 13000 | X10: 1 | Z10: 23561046X | AA10: 1
B11: 23223623X | C11: FJALLRAVEN | D11: 23223 | E11: High Coast Hip Pack | F11: 623 | G11: Mountain Green | H11: X | I11: 6500 | J11: 1 | L11: 23796118X | M11: 1 | P11: 23781550X | Q11: FJALLRAVEN | R11: 23781 | S11: Kanken Travel Wallet | T11: 550 | U11: Black | V11: X | W11: 9000 | X11: 1 | Z11: (空白)
B12: 23524031X | C12: FJALLRAVEN | D12: 23524 | E12: Kanken Laptop 15 | F12: 31 | G12: Graphite | H12: X | I12: 18000 | J12: 1 | L12: 24213030X | M12: 1 | P12: 23165550X | Q12: FJALLRAVEN | R12: 23165 | S12: Ulvo Hip Pack Medium | T12: 550 | U12: Black | V12: X | W12: 8000 | X12: 1 | Z12: 23510126X | AA12: 2
B13: 23344550-550X | C13: FJALLRAVEN | D13: 23344 | E13: Raven 20 | F13: 550-550 | G13: Black-Black | H13: X | I13: 16000 | J13: 1 | L13: (空白) | P13: 79030X | Q13: FJALLRAVEN | R13: 79030 | S13: Greenland Wax travel pack | V13: X | W13: 850 | X13: 1 | Z13: 23796424X | AA13: 1
B14: 23804550X | C14: FJALLRAVEN | D14: 23804 | E14: Kanken no. 2 Black Laptop 15 | F14: 550 | G14: Black | H14: X | I14: 26000 | J14: 1 | L14: 23797031X | M14: 1 | P14: 23510540X | Q14: FJALLRAVEN | R14: 23510 | S14: Kanken | T14: 540 | U14: Royal Blue | V14: X | W14: 13000 | X14: 1 | Z14: 23510501-115X | AA14: 2
B15: TNT026164L | C15: TENNEN | D15: TNT026 | E15: 天撚Tシャツ /メリノウール | F15: 164 | G15: Burgundy | H15: L | I15: 11000 | J15: 1 | L15: 23796457X | M15: 1 | P15: 23510501-115X | Q15: FJALLRAVEN | R15: 23510 | S15: Kanken | T15: 501-115 | U15: Sky Blue-Light Oak | V15: X | W15: 13000 | X15: 1 | Z15: 23525160X | AA15: 1
B16: 23510160X | C16: FJALLRAVEN | D16: 23510 | E16: Kanken | F16: 160 | G16: Ochre | H16: X | I16: 13000 | J16: 1 | L16: 23510664X | M16: 1 | P16: 23565238X | Q16: FJALLRAVEN | R16: 23565 | S16: Kanken No.2 | T16: 238 | U16: Hazel Brown | V16: X | W16: 20000 | X16: 1 | Z16: 23510424X | AA16: 1
B17: 23510664X | C17: FJALLRAVEN | D17: 23510 | E17: Kanken | F17: 664 | G17: Frost Green | H17: X | I17: 13000 | J17: 1 | L17: 23510560X | M17: 1 | P17: 23200251021X | Q17: FJALLRAVEN | R17: 23200251 | S17: Kanken Outlong | T17: 21 | U17: Fog | V17: X | W17: 19000 | X17: 1 | Z17: 23510664X | AA17: 1
B18: 23561021-312X | C18: FJALLRAVEN | D18: 23561 | E18: Kanken Mini | F18: 021-312 | G18: Fog-Pink | H18: X | I18: 12000 | J18: 1 | L18: 23346050X | M18: 1 | P18: 23510424X | Q18: FJALLRAVEN | R18: 23510 | S18: Kanken | T18: 424 | U18: Blackberry | V18: X | W18: 13000 | X18: 1 | Z18: 23346550X | AA18: 1
B19: 23524031X | C19: FJALLRAVEN | D19: 23524 | E19: Kanken Laptop 15 | F19: 31 | G19: Graphite | H19: X | I19: 18000 | J19: 1 | L19: 23561600X | M19: -1 | P19: 23510540X | Q19: FJALLRAVEN | R19: 23510 | S19: Kanken | T19: 540 | U19: Royal Blue | V19: X | W19: 13000 | X19: 1 | Z19: 23349662X | AA19: 1
B20: 23344550X | C20: FJALLRAVEN | D20: 23344 | E20: Raven 20 | F20: 550 | G20: Black | H20: X | I20: 16000 | J20: 1 | L20: 23804550X | M20: 1 | P20: 23510501-115X | Q20: FJALLRAVEN | R20: 23510 | S20: Kanken | T20: 501-115 | U20: Sky Blue-Light Oak | V20: X | W20: 13000 | X20: 1 | Z20: 23349550X | AA20: 1
B21: 23200330620X | C21: FJALLRAVEN | D21: 23200330 | E21: High Coast Backpack 24 | F21: 620 | G21: Green | H21: X | I21: 17000 | J21: 1 | L21: 23200251160X | M21: 1 | P21: 23349662X | Q21: FJALLRAVEN | R21: 23349 | S21: Skule 20 | T21: 662 | U21: Deep Forest | V21: X | W21: 12000 | X21: 1 | Z21: 23565633X | AA21: 1
B22: 23561021-312X | C22: FJALLRAVEN | D22: 23561 | E22: Kanken Mini | F22: 021-312 | G22: Fog-Pink | H22: X | I22: 12000 | J22: 1 | L22: 23510021X | M22: 1 | P22: 23349550X | Q22: FJALLRAVEN | R22: 23349 | S22: Skule 20 | T22: 550 | U22: Black | V22: X | W22: 12000 | X22: 1 | Z22: 23345550X | AA22: 1
B23: 23200251160X | C23: FJALLRAVEN | D23: 23200251 | E23: Kanken Outlong | F23: 160 | G23: Ochre | H23: X | I23: 19000 | J23: 1 | L23: 23561457-916X | M23: 1 | P23: 23510021X | Q23: FJALLRAVEN | R23: 23510 | S23: Kanken | T23: 21 | U23: Fog | V23: X | W23: 13000 | X23: 1 | Z23: 23223207X | AA23: 1
B24: 23510664X | C24: FJALLRAVEN | D24: 23510 | E24: Kanken | F24: 664 | G24: Frost Green | H24: X | I24: 13000 | J24: -1 | L24: 23561326X | M24: 3 | P24: 23565633X | Q24: FJALLRAVEN | R24: 23565 | S24: Kanken No.2 | T24: 633 | U24: Dark Olive | V24: X | W24: 20000 | X24: 1 | Z24: 23508560X | AA24: 1
B25: 23561600X | C25: FJALLRAVEN | D25: 23561 | E25: Kanken Mini | F25: 600 | G25: Mint Green | H25: X | I25: 12000 | J25: -1 | L25: 23710031X | M25: 1 | P25: 23345550X | Q25: FJALLRAVEN | R25: 23345 | S25: Raven 28 | T25: 550 | U25: Black | V25: X | W25: 19000 | X25: 1 | Z25: 23322633X | AA25: 1
B26: 23510021X | C26: FJALLRAVEN | D26: 23510 | E26: Kanken | F26: 21 | G26: Fog | H26: X | I26: 13000 | J26: 1 | L26: 23796664X | M26: 1 | P26: 23223207X | Q26: FJALLRAVEN | R26: 23223 | S26: High Coast Hip Pack | T26: 207 | U26: Sunset Orange | V26: X | W26: 6500 | X26: 1 | Z26: 23346662X | AA26: 0
B27: 23510501X | C27: FJALLRAVEN | D27: 23510 | E27: Kanken | F27: 501 | G27: Sky blue | H27: X | I27: 13000 | J27: 1 | L27: 23796221X | M27: 1 | P27: 23508560X | Q27: FJALLRAVEN | R27: 23508 | S27: Kanken Organizer | T27: 560 | U27: Navy | V27: X | W27: 5500 | X27: 1 | Z27: 23226333X | AA27: 1
B28: 23561457-916X | C28: FJALLRAVEN | D28: 23561 | E28: Kanken Mini | F28: 457-916 | G28: Pastel Lavender-Confetti Pattern | H28: X | I28: 12000 | J28: 1 | L28: 23561501X | M28: -1 | P28: 23322633X | Q28: FJALLRAVEN | R28: 23322 | S28: Singi Stubben | T28: 633 | U28: Dark Olive | V28: X | W28: 42000 | X28: 1 | Z28: 23781550X | AA28: 1
B29: 23561326X | C29: FJALLRAVEN | D29: 23561 | E29: Kanken Mini | F29: 326 | G29: Ox Red | H29: X | I29: 12000 | J29: 1 | L29: 23561501-115X | M29: 0 | P29: 23510021X | Q29: FJALLRAVEN | R29: 23510 | S29: Kanken | T29: 21 | U29: Fog | V29: X | W29: 13000 | X29: 1 | Z29: 23565238X | AA29: 1
B30: 23710031X | C30: FJALLRAVEN | D30: 23710 | E30: Kanken Totepack | F30: 31 | G30: Graphite | H30: X | I30: 15000 | J30: 1 | L30: 23796031X | M30: 1 | P30: 23510550X | Q30: FJALLRAVEN | R30: 23510 | S30: Kanken | T30: 550 | U30: Black | V30: X | W30: 13000 | X30: 1 | Z30: 23200251021X | AA30: 1
B31: 23796664X | C31: FJALLRAVEN | D31: 23796 | E31: Kanken Hip Pack | F31: 664 | G31: Frost Green | H31: X | I31: 8000 | J31: 1 | L31: 23561457X | M31: 2 | P31: 23346662X | Q31: FJALLRAVEN | R31: 23346 | S31: Skule 28 | T31: 662 | U31: Deep Forest | V31: X | W31: 14000 | X31: 1 | Z31: 総計 | AA31: 28
B32: 23796221X | C32: FJALLRAVEN | D32: 23796 | E32: Kanken Hip Pack | F32: 221 | G32: Clay | H32: X | I32: 8000 | J32: 1 | L32: 23524160X | M32: 1 | P32: 23346550X | Q32: FJALLRAVEN | R32: 23346 | S32: Skule 28 | T32: 550 | U32: Black | V32: X | W32: 14000 | X32: 1
B33: 23346050X | C33: FJALLRAVEN | D33: 23346 | E33: Skule 28 | F33: 50 | G33: Basalt | H33: X | I33: 14000 | J33: 1 | L33: 23796560X | M33: 1 | P33: 23226333X | Q33: FJALLRAVEN | R33: 23226 | S33: High Coast Pocket | T33: 333 | U33: Rowan Red | V33: X | W33: 5000 | X33: 1
B34: 23561501X | C34: FJALLRAVEN | D34: 23561 | E34: Kanken Mini | F34: 501 | G34: Sky blue | H34: X | I34: 12000 | J34: -1 | L34: 23345550-550X | M34: 1 | P34: 23505560X | Q34: FJALLRAVEN | R34: 23505 | S34: Kanken Shoulder Pads | T34: 560 | U34: Navy | V34: X | W34: 3500 | X34: 1
B35: 23561312X | C35: FJALLRAVEN | D35: 23561 | E35: Kanken Mini | F35: 312 | G35: Pink | H35: X | I35: 12000 | J35: -1 | L35: 23345357X | M35: 1 | P35: 23796424X | Q35: FJALLRAVEN | R35: 23796 | S35: Kanken Hip Pack | T35: 424 | U35: Blackberry | V35: X | W35: 8000 | X35: 1
B36: 23561501-115X | C36: FJALLRAVEN | D36: 23561 | E36: Kanken Mini | F36: 501-115 | G36: Sky Blue-Light Oak | H36: X | I36: 12000 | J36: 1 | L36: 23510160X | M36: 1
B37: 23797031X | C37: FJALLRAVEN | D37: 23797 | E37: Kanken Sling | F37: 31 | G37: GRAPHITE | H37: X | I37: 10500 | J37: 1 | L37: 23223543X | M37: 1
B38: 23796031X | C38: FJALLRAVEN | D38: 23796 | E38: Kanken Hip Pack | F38: 31 | G38: Graphite | H38: X | I38: 8000 | J38: 1 | L38: 23349662X | M38: 1
B39: 23344550X | C39: FJALLRAVEN | D39: 23344 | E39: Raven 20 | F39: 550 | G39: Black | H39: X | I39: 16000 | J39: 1 | L39: 23200330016X | M39: 1
B40: 23561457X | C40: FJALLRAVEN | D40: 23561 | E40: Kanken Mini | F40: 457 | G40: Pastel Lavender | H40: X | I40: 12000 | J40: 2 | L40: 23223623X | M40: 1
B41: 23620550-907X | C41: FJALLRAVEN | D41: 23620 | E41: Kanken Rainbow | F41: 550-907 | G41: Black-Rainbow Pattern | H41: X | I41: 13500 | J41: 2 | L41: 23524031X | M41: 2
B42: 23510664X | C42: FJALLRAVEN | D42: 23510 | E42: Kanken | F42: 664 | G42: Frost Green | H42: X | I42: 13000 | J42: 1 | L42: 23344550-550X | M42: 1
B43: 23796118X | C43: FJALLRAVEN | D43: 23796 | E43: Kanken Hip Pack | F43: 118 | G43: Fossil | H43: X | I43: 8000 | J43: 1 | L43: TNT026164L | M43: 1
B44: 23524160X | C44: FJALLRAVEN | D44: 23524 | E44: Kanken Laptop 15 | F44: 160 | G44: Ochre | H44: X | I44: 18000 | J44: 1 | L44: 23200330620X | M44: 1
B45: 23510540X | C45: FJALLRAVEN | D45: 23510 | E45: Kanken | F45: 540 | G45: Royal Blue | H45: X | I45: 13000 | J45: 1 | L45: 総計 | M45: 44
B46: 23510560X | C46: FJALLRAVEN | D46: 23510 | E46: Kanken | F46: 560 | G46: Navy | H46: X | I46: 13000 | J46: 1
B47: 23510312X | C47: FJALLRAVEN | D47: 23510 | E47: Kanken | F47: 312 | G47: Pink | H47: X | I47: 13000 | J47: 1
B48: 23510600X | C48: FJALLRAVEN | D48: 23510 | E48: Kanken | F48: 600 | G48: Mint Green | H48: X | I48: 13000 | J48: 1
B49: 24213030X | C49: FJALLRAVEN | D49: 24213 | E49: Gear Bag | F49: 30 | G49: Dark Grey | H49: X | I49: 4300 | J49: 1
B50: 23796457X | C50: FJALLRAVEN | D50: 23796 | E50: Kanken Hip Pack | F50: 457 | G50: Pastel Lavender | H50: X | I50: 8000 | J50: 1
B51: 23796560X | C51: FJALLRAVEN | D51: 23796 | E51: Kanken Hip Pack | F51: 560 | G51: Navy | H51: X | I51: 8000 | J51: 1
B52: 23345550-550X | C52: FJALLRAVEN | D52: 23345 | E52: Raven 28 | F52: 550-550 | G52: Black-Black | H52: X | I52: 19000 | J52: 1
B53: 23345357X | C53: FJALLRAVEN | D53: 23345 | E53: Raven 28 | F53: 357 | G53: Port | H53: X | I53: 19000 | J53: 1

Sheet EC_ORDER
A1: 日付 | B1: 注文時間 | C1: 注文番号 | D1: 決済方法(ステータス) | E1: 注文者 | F1: 注文者電話番号 | G1: 注文者電話番号 緊急時連絡先 | H1: 緊急時連絡先2 | I1: 注文者の住所 | J1: 受取人 | K1: 受取人の電話番号 | L1: 住所 | M1: 郵便番号 | N1: 商品名 | O1: 個数 | P1: 商品価格 | Q1: ポイント | R1: 商品コード | S1: 独自商品コード | T1: オプション独自コード | U1: JANコード | V1: 決済方法 | W1: 支払金額 | X1: 送料 | Y1: 代金引換決済方法 | Z1: 代金引換手数料 | AA1: 利用ポイント | AB1: 消費税 | AC1: 消費税率 | AD1: 利用GMOポイント | AE1: 優待会員特典 | AF1: 配送先ごとの金額 | AG1: 配送方法 | AH1: 配送希望日 | AI1: 出荷予定日 | AJ1: 配送希望時間帯 | AK1: 配送日 | AL1: 伝票番号 | AM1: 注文メッセージ | AN1: 配送メッセージ | AO1: メッセージ | AP1: メモ
A2: 46204 | B2: 123737 | C2: P186948209336569367 | D2: PGクレジットカード [決済完了] | E2: 松原由未子 | F2: 070-8340-6798 | G2: 7083406798 | I2: (192-0066) 東京都八王子市本町31-9 | J2: 松原由未子 | K2: 070-8340-6798 | L2: 東京都八王子市本町31-9 | M2: 192-0066 | N2: Kanken Laptop 15 | O2: 1 | P2: 19800 | Q2: 1980 | R2: 000000001143 | S2: 23524 | T2: 23524046X | V2: PGクレジットカード | W2: 20350 | X2: 550 | Z2: 0 | AA2: 0 | AB2: 0 | AC2: 10 | AD2: 0 | AE2: 0 | AG2: 佐川急便 | AM2: 伝達メッセージ : | AO2: 伝達メッセージ :
A3: 46204 | B3: 084011 | C3: P186946715506715034 | D3: Amazon Pay [決済完了] | E3: 井原裕樹 | F3: 080-6146-8353 | G3: 8061468353 | I3: (595-0805) 大阪府泉北郡忠岡町忠岡東1丁目22-13 忠岡グリーンハイツ 6-L | J3: 井原裕樹 | K3: 080-6146-8353 | L3: 大阪府泉北郡忠岡町忠岡東1丁目22-13 忠岡グリーンハイツ 6-L | M3: 595-0805 | N3: Abisko Wool Logo SS M | O3: 1 | P3: 12100 | Q3: 1210 | R3: 000000001465 | S3: 86977 | T3: 86977550M | V3: Amazon Pay | W3: 22440 | X3: 550 | Z3: 0 | AA3: 0 | AB3: 0 | AC3: 10 | AD3: 0 | AE3: 0 | AG3: 佐川急便 | AM3: 伝達メッセージ : | AO3: 伝達メッセージ :
A4: 46204 | B4: 084011 | C4: P186946715506715034 | D4: Amazon Pay [決済完了] | E4: 井原裕樹 | F4: 080-6146-8353 | G4: 8061468353 | I4: (595-0805) 大阪府泉北郡忠岡町忠岡東1丁目22-13 忠岡グリーンハイツ 6-L | J4: 井原裕樹 | K4: 080-6146-8353 | L4: 大阪府泉北郡忠岡町忠岡東1丁目22-13 忠岡グリーンハイツ 6-L | M4: 595-0805 | N4: Multicolor Logo T-shirt M | O4: 1 | P4: 9790 | Q4: 979 | R4: 000000001734 | S4: 12600268 | T4: 12600268244M | V4: Amazon Pay | W4: 22440 | X4: 550 | Z4: 0 | AA4: 0 | AB4: 0 | AC4: 10 | AD4: 0 | AE4: 0 | AG4: 佐川急便 | AM4: 伝達メッセージ : | AO4: 伝達メッセージ :
A5: 46204 | B5: 082508 | C5: P186946620811731880 | D5: PayPay [決済完了] | E5: 井亦伶 | F5: 090-8097-8515 | G5: 9080978515 | I5: (937-0816) 富山県魚津市大海寺野855-8 | J5: 井亦伶 | K5: 090-8097-8515 | L5: 富山県魚津市大海寺野855-8 | M5: 937-0816 | N5: Kanken 16L (Frost Green 664) | O5: 1 | P5: 14300 | Q5: 1430 | R5: 000000000897 | S5: 23510 | T5: 23510664X | V5: PayPay | W5: 14850 | X5: 550 | Z5: 0 | AA5: 0 | AB5: 0 | AC5: 10 | AD5: 0 | AE5: 0 | AG5: 佐川急便 | AM5: 伝達メッセージ : | AO5: 伝達メッセージ :
A6: 46204 | B6: 002517 | C6: P186943601856493114 | D6: PayPay [決済完了] | E6: Indri | F6: 070-9036-5335 | G6: 7090365335 | I6: (635-0832) 奈良県北葛城郡広陵町馬見中5丁目1番1号アーバンハイツ真美201 | J6: Indri | K6: 070-9036-5335 | L6: 奈良県北葛城郡広陵町馬見中5丁目1番1号アーバンハイツ真美201 | M6: 635-0832 | N6: Kanken Totepack | O6: 1 | P6: 16500 | Q6: 1650 | R6: 000000000594 | S6: 23710 | T6: 23710550X | V6: PayPay | W6: 17050 | X6: 550 | Z6: 0 | AA6: 0 | AB6: 0 | AC6: 10 | AD6: 0 | AE6: 0 | AG6: 佐川急便 | AM6: 伝達メッセージ : | AO6: 伝達メッセージ :
A7: 46203 | B7: 234528 | C7: P186943351358138473 | D7: PayPay [決済完了] | E7: SameerDeshmukh | F7: 070-4465-5316 | G7: 7044655316 | I7: (210-0011) 神奈川県川崎市川崎区富士見１丁目６番１５-２０９ | J7: SameerDeshmukh | K7: 070-4465-5316 | L7: 神奈川県川崎市川崎区富士見１丁目６番１５-２０９ | M7: 210-0011 | N7: High Coast Totepack | O7: 1 | P7: 14300 | Q7: 1430 | R7: 000000000802 | S7: 23225 | T7: 23225424X | V7: PayPay | W7: 14850 | X7: 550 | Z7: 0 | AA7: 0 | AB7: 0 | AC7: 10 | AD7: 0 | AE7: 0 | AG7: 佐川急便 | AM7: 伝達メッセージ : | AO7: 伝達メッセージ :
A8: 46203 | B8: 234423 | C8: P186943344623497308 | D8: Amazon Pay [要確認] | E8: SameerDeshmukh | F8: 070-4465-5316 | G8: 7044655316 | I8: (210-0011) 神奈川県川崎市川崎区富士見１丁目６番１５-２０９ | J8: デシュムクサミーア | K8: 070-4465-5316 | L8: 神奈川県川崎市川崎区富士見１丁目６番１５ コンフォーレ川崎富士見５棟 ２０９ | M8: 210-0011 | N8: High Coast Totepack | O8: 1 | P8: 14300 | Q8: 1430 | R8: 000000000802 | S8: 23225 | T8: 23225424X | V8: Amazon Pay | W8: 14850 | X8: 550 | Z8: 0 | AA8: 0 | AB8: 0 | AC8: 10 | AD8: 0 | AE8: 0 | AG8: 佐川急便 | AM8: 伝達メッセージ : | AO8: 伝達メッセージ :
A9: 46203 | B9: 222006 | C9: P186942814264413677 | D9: Amazon Pay [決済完了] | E9: 白須政人 | F9: 080-6588-6230 | G9: 8065886230 | I9: (402-0032) 山梨県都留市 鹿留１０９９－２ | J9: 白須政人 | K9: 080-6588-6230 | L9: 山梨県都留市 鹿留１０９９－２ | M9: 402-0032 | N9: Kanken 16L (Navy 560) | O9: 1 | P9: 14300 | Q9: 1430 | R9: 000000000882 | S9: 23510 | T9: 23510560X | V9: Amazon Pay | W9: 14850 | X9: 550 | Z9: 0 | AA9: 0 | AB9: 0 | AC9: 10 | AD9: 0 | AE9: 0 | AG9: 佐川急便 | AM9: 伝達メッセージ : | AO9: 伝達メッセージ :
A10: 46203 | B10: 220720 | C10: P186942733978574865 | D10: PGクレジットカード [決済完了] | E10: 中川文江 | F10: 090-9033-4798 | G10: 9090334798 | I10: (999-3716) 山形県東根市蟹沢1447-14 | J10: 中川文江 | K10: 090-9033-4798 | L10: 山形県東根市蟹沢1447-14 | M10: 999-3716 | N10: Keb Trekking Belt | O10: 1 | P10: 5280 | Q10: 528 | R10: 000000000210 | S10: 77316 | T10: 77316633X | V10: PGクレジットカード | W10: 45338 | X10: 550 | Z10: 0 | AA10: -3062 | AB10: 0 | AC10: 10 | AD10: 0 | AE10: 0 | AG10: 佐川急便 | AM10: 伝達メッセージ : | AO10: 伝達メッセージ :
A11: 46203 | B11: 220720 | C11: P186942733978574865 | D11: PGクレジットカード [決済完了] | E11: 中川文江 | F11: 090-9033-4798 | G11: 9090334798 | I11: (999-3716) 山形県東根市蟹沢1447-14 | J11: 中川文江 | K11: 090-9033-4798 | L11: 山形県東根市蟹沢1447-14 | M11: 999-3716 | N11: Marlin Mosquito Hat | O11: 1 | P11: 7370 | Q11: 737 | R11: 000000001244 | S11: 79339 | T11: 79339030M | V11: PGクレジットカード | W11: 45338 | X11: 550 | Z11: 0 | AA11: -3062 | AB11: 0 | AC11: 10 | AD11: 0 | AE11: 0 | AG11: 佐川急便 | AM11: 伝達メッセージ : | AO11: 伝達メッセージ :
A12: 46203 | B12: 220720 | C12: P186942733978574865 | D12: PGクレジットカード [決済完了] | E12: 中川文江 | F12: 090-9033-4798 | G12: 9090334798 | I12: (999-3716) 山形県東根市蟹沢1447-14 | J12: 中川文江 | K12: 090-9033-4798 | L12: 山形県東根市蟹沢1447-14 | M12: 999-3716 | N12: 【Women’s】【UPDATED】Keb Trousers W | O12: 1 | P12: 35200 | Q12: 3520 | R12: 000000001613 | S12: 86706 | T12: 86706662-62538/S | V12: PGクレジットカード | W12: 45338 | X12: 550 | Z12: 0 | AA12: -3062 | AB12: 0 | AC12: 10 | AD12: 0 | AE12: 0 | AG12: 佐川急便 | AM12: 伝達メッセージ : | AO12: 伝達メッセージ :
A13: 46203 | B13: 210659 | C13: P186942354275062894 | D13: PayPay [決済完了] | E13: 株式会社冨田工業 | F13: 090-5332-1465 | G13: 9053321465 | I13: (315-0031) 茨城県石岡市東大橋1805 | J13: 株式会社冨田工業 | K13: 090-5332-1465 | L13: 茨城県石岡市東大橋1805 | M13: 315-0031 | N13: Kanken 16L (Sky Blue 501) | O13: 1 | P13: 14300 | Q13: 1430 | R13: 000000000872 | S13: 23510 | T13: 23510501X | V13: PayPay | W13: 14850 | X13: 550 | Z13: 0 | AA13: 0 | AB13: 0 | AC13: 10 | AD13: 0 | AE13: 0 | AG13: 佐川急便 | AM13: 伝達メッセージ : | AO13: 伝達メッセージ :
... A16: 46203 | B16: 192150 | C16: P186941692737373587 | D16: Amazon Pay [決済完了] | E16: 松本健次郎 | F16: 053-485-9631 | G16: 534859631 | I16: (432-8001) 静岡県浜松市西区西山町1055-57ブライトタウン西山402 | J16: 松本健次郎 | K16: 053-485-9631 | L16: 静岡県浜松市西区西山町1055-57ブライトタウン西山402 | M16: 432-8001 | N16: Kanken 16L (Chalk Rose 302) | O16: 1 | P16: 14300 | Q16: 1430 | R16: 000000001723 | S16: 23510 | T16: 23510302X | V16: Amazon Pay | W16: 14850 | X16: 550 | Z16: 0 | AA16: 0 | AB16: 0 | AC16: 10 | AD16: 0 | AE16: 0 | AG16: 佐川急便 | AM16: 伝達メッセージ : | AO16: 伝達メッセージ :
A17: 46203 | B17: 192119 | C17: P186941775968513272 | D17: Yahoo!ショッピングPayPay残高払い [支払完了] | E17: 大内雅 | F17: 8033042628 | G17: 8033042628 | I17: (253-0105) 神奈川県高座郡寒川町岡田5-13-25メゾン・ド・フラン2 101 | J17: 大内雅 | K17: 8033042628 | L17: 神奈川県高座郡寒川町岡田5-13-25メゾン・ド・フラン2 101 | M17: 253-0105 | N17: Greenland Wax Bag | O17: 1 | P17: 3520 | Q17: 10 | R17: 000000000296 | S17: 79061 | T17: 79061X | V17: Yahoo!ショッピングPayPay残高払い | W17: 3520 | X17: 0 | Z17: 0 | AA17: 0 | AB17: 0 | AC17: 10 | AD17: 0 | AE17: 0 | AG17: 当店規定の配送方法（Yahoo!ショッピングの注文） | AM17: 伝達メッセージ : | AO17: 伝達メッセージ :
A18: 46203 | B18: 191057 | C18: P186941624301428941 | D18: Amazon Pay [決済完了] | E18: 下重智也 | F18: 090-4374-7589 | G18: 9043747589 | I18: (108-0074) 東京都港区高輪1-4-23 コスモ高輪シティーフォルム1403 | J18: 下重智也 | K18: 090-4374-7589 | L18: 東京都港区高輪1-4-23コスモ高輪シティフォルム1403 | M18: 108-0074 | N18: High Coast Wind Jacket M | O18: 1 | P18: 30250 | Q18: 3025 | R18: 000000001531 | S18: 82606 | T18: 82606232-620M | V18: Amazon Pay | W18: 24750 | X18: 550 | Z18: 0 | AA18: 0 | AB18: 0 | AC18: 10 | AD18: 0 | AE18: 0 | AG18: 佐川急便 | AM18: 伝達メッセージ : | AO18: 伝達メッセージ :
A19: 46203 | B19: 181915 | C19: P186941298978322974 | D19: Amazon Pay [決済完了] | E19: 千葉里花 | F19: 0285-84-5470 | G19: 285845470 | I19: (321-4357) 栃木県真岡市下大沼一丁目11-6 | J19: 千葉里花 | K19: 0285-84-5470 | L19: 栃木県真岡市下大沼一丁目11-6 | M19: 321-4357 | N19: Kanken 16L (Sky Blue 501) | O19: 1 | P19: 14300 | Q19: 1430 | R19: 000000000872 | S19: 23510 | T19: 23510501X | V19: Amazon Pay | W19: 14850 | X19: 550 | Z19: 0 | AA19: 0 | AB19: 0 | AC19: 10 | AD19: 0 | AE19: 0 | AG19: 佐川急便 | AM19: 伝達メッセージ : | AO19: 伝達メッセージ :
A20: 46203 | B20: 173536 | C20: P186941024353087257 | D20: PayPay [決済完了] | E20: 久野慶次 | F20: 090-1724-6514 | G20: 9017246514 | I20: (411-0041) 静岡県三島市佐野見晴台1-23-2 | J20: 久野慶次 | K20: 090-1724-6514 | L20: 静岡県三島市佐野見晴台1-23-2 | M20: 411-0041 | N20: Gift Wrapping (L) | O20: 1 | P20: 550 | Q20: 55 | R20: 000000000584 | S20: GIFT500 | T20: GIFT500 | V20: PayPay | W20: 15400 | X20: 550 | Z20: 0 | AA20: 0 | AB20: 0 | AC20: 10 | AD20: 0 | AE20: 0 | AG20: 佐川急便 | AM20: 伝達メッセージ : | AO20: 伝達メッセージ :
A21: 46203 | B21: 173536 | C21: P186941024353087257 | D21: PayPay [決済完了] | E21: 久野慶次 | F21: 090-1724-6514 | G21: 9017246514 | I21: (411-0041) 静岡県三島市佐野見晴台1-23-2 | J21: 久野慶次 | K21: 090-1724-6514 | L21: 静岡県三島市佐野見晴台1-23-2 | M21: 411-0041 | N21: Kanken 16L (Graphite 031) | O21: 1 | P21: 14300 | Q21: 1430 | R21: 000000000851 | S21: 23510 | T21: 23510031X | V21: PayPay | W21: 15400 | X21: 550 | Z21: 0 | AA21: 0 | AB21: 0 | AC21: 10 | AD21: 0 | AE21: 0 | AG21: 佐川急便 | AM21: 伝達メッセージ : | AO21: 伝達メッセージ :
A22: 46203 | B22: 173320 | C22: P186941010112151775 | D22: PayPay [要確認] | E22: 久野慶次 | F22: 090-1724-6514 | G22: 9017246514 | I22: (411-0041) 静岡県三島市佐野見晴台1-23-2 | J22: 久野慶次 | K22: 090-1724-6514 | L22: 静岡県三島市佐野見晴台1-23-2 | M22: 411-0041 | N22: Gift Wrapping (L) | O22: 1 | P22: 550 | Q22: 55 | R22: 000000000584 | S22: GIFT500 | T22: GIFT500 | V22: PayPay | W22: 15400 | X22: 550 | Z22: 0 | AA22: 0 | AB22: 0 | AC22: 10 | AD22: 0 | AE22: 0 | AG22: 佐川急便 | AM22: 伝達メッセージ : | AO22: 伝達メッセージ :
A23: 46203 | B23: 173320 | C23: P186941010112151775 | D23: PayPay [要確認] | E23: 久野慶次 | F23: 090-1724-6514 | G23: 9017246514 | I23: (411-0041) 静岡県三島市佐野見晴台1-23-2 | J23: 久野慶次 | K23: 090-1724-6514 | L23: 静岡県三島市佐野見晴台1-23-2 | M23: 411-0041 | N23: Kanken 16L (Graphite 031) | O23: 1 | P23: 14300 | Q23: 1430 | R23: 000000000851 | S23: 23510 | T23: 23510031X | V23: PayPay | W23: 15400 | X23: 550 | Z23: 0 | AA23: 0 | AB23: 0 | AC23: 10 | AD23: 0 | AE23: 0 | AG23: 佐川急便 | AM23: 伝達メッセージ : | AO23: 伝達メッセージ :
A24: 46203 | B24: 165300 | C24: P186940756332847537 | D24: 代金引換 [未入金] | E24: viarputrirahayu | F24: 070-5360-6276 | G24: 7053606276 | I24: (889-4314) 宮崎県えびの市大河平ichigokan life suport 4327-27 ebino-shi miyazaki ken | J24: viarputrirahayu | K24: 070-5360-6276 | L24: 宮崎県えびの市大河平ichigokan life suport 4327-27 ebino-shi miyazaki ken | M24: 889-4314 | N24: Kanken Laptop 15 | O24: 1 | P24: 19800 | Q24: 1980 | R24: 000000001143 | S24: 23524 | T24: 23524560X | V24: 代金引換 | W24: 20790 | X24: 550 | Z24: 440 | AA24: 0 | AB24: 0 | AC24: 10 | AD24: 0 | AE24: 0 | AG24: 佐川急便 | AM24: 伝達メッセージ : | AO24: 伝達メッセージ :
A25: 46203 | B25: 162703 | C25: P186940593147033594 | D25: PGクレジットカード [決済完了] | E25: 中島華子 | F25: 090-4275-1379 | G25: 9042751379 | I25: (652-0058) 兵庫県神戸市兵庫区菊水町6丁目1-20-807 | J25: 中島華子 | K25: 090-4275-1379 | L25: 兵庫県神戸市兵庫区菊水町6丁目1-20-807 | M25: 652-0058 | N25: Gift Wrapping (L) | O25: 1 | P25: 550 | Q25: 55 | R25: 000000000584 | S25: GIFT500 | T25: GIFT500 | V25: PGクレジットカード | W25: 15400 | X25: 550 | Z25: 0 | AA25: 0 | AB25: 0 | AC25: 10 | AD25: 0 | AE25: 0 | AG25: 佐川急便 | AM25: 伝達メッセージ : | AO25: 伝達メッセージ :
A26: 46203 | B26: 162703 | C26: P186940593147033594 | D26: PGクレジットカード [決済完了] | E26: 中島華子 | F26: 090-4275-1379 | G26: 9042751379 | I26: (652-0058) 兵庫県神戸市兵庫区菊水町6丁目1-20-807 | J26: 中島華子 | K26: 090-4275-1379 | L26: 兵庫県神戸市兵庫区菊水町6丁目1-20-807 | M26: 652-0058 | N26: Kanken 16L (Blackberry 424) | O26: 1 | P26: 14300 | Q26: 1430 | R26: 000000001481 | S26: 23510 | T26: 23510424X | V26: PGクレジットカード | W26: 15400 | X26: 550 | Z26: 0 | AA26: 0 | AB26: 0 | AC26: 10 | AD26: 0 | AE26: 0 | AG26: 佐川急便 | AM26: 伝達メッセージ : | AO26: 伝達メッセージ :
A27: 46203 | B27: 160142 | C27: P186940517637469789 | D27: Yahoo!ショッピングPayPay残高払い [支払完了] | E27: 伊藤雅章 | F27: 9069688928 | G27: 9069688928 | I27: (550-0013) 大阪府大阪市西区新町２丁目１０－１２ー403 | J27: 伊藤雅章 | K27: 9069688928 | L27: 大阪府大阪市西区新町２丁目１０－１２ー403 | M27: 550-0013 | N27: Kanken 16L (Chalk Rose 302) | O27: 1 | P27: 14300 | Q27: 10 | R27: 000000001723 | S27: 23510 | T27: 23510302X | V27: Yahoo!ショッピングPayPay残高払い | W27: 14300 | X27: 0 | Z27: 0 | AA27: 0 | AB27: 0 | AC27: 10 | AD27: 0 | AE27: 0 | AG27: 当店規定の配送方法（Yahoo!ショッピングの注文） | AM27: 伝達メッセージ : 電話させていただきました。 よろしくお願いいたします。 | AO27: 伝達メッセージ : 電話させていただきました。 よろしくお願いいたします。
A28: 46203 | B28: 153030 | C28: P186940237333588905 | D28: Amazon Pay [決済完了] | E28: 袖山桂子 | F28: 026-222-5427 | G28: 262225427 | I28: (381-0022) 長野県長野市大豆島745-12 | J28: 袖山治嗣 | K28: 090-4399-0246 | L28: 北海道札幌市中央区北五条西2-5 JRタワーホテル日航札幌気付 袖山 | M28: 060-0005 | N28: Gift Wrapping (L) | O28: 1 | P28: 550 | Q28: 55 | R28: 000000000584 | S28: GIFT500 | T28: GIFT500 | V28: Amazon Pay | W28: 15400 | X28: 550 | Z28: 0 | AA28: 0 | AB28: 0 | AC28: 10 | AD28: 0 | AE28: 0 | AG28: 佐川急便 | AM28: 伝達メッセージ : | AO28: 伝達メッセージ :
A29: 46203 | B29: 153030 | C29: P186940237333588905 | D29: Amazon Pay [決済完了] | E29: 袖山桂子 | F29: 026-222-5427 | G29: 262225427 | I29: (381-0022) 長野県長野市大豆島745-12 | J29: 袖山治嗣 | K29: 090-4399-0246 | L29: 北海道札幌市中央区北五条西2-5 JRタワーホテル日航札幌気付 袖山 | M29: 060-0005 | N29: Kanken 16L (Black 550) | O29: 1 | P29: 14300 | Q29: 1430 | R29: 000000000881 | S29: 23510 | T29: 23510550X | V29: Amazon Pay | W29: 15400 | X29: 550 | Z29: 0 | AA29: 0 | AB29: 0 | AC29: 10 | AD29: 0 | AE29: 0 | AG29: 佐川急便 | AM29: 伝達メッセージ : | AO29: 伝達メッセージ :
A30: 46203 | B30: 152329 | C30: P186940193233028634 | D30: Amazon Pay [決済完了] | E30: 田宮昌子 | F30: 0166-53-5104 | G30: 166535104 | I30: (070-0875) 北海道旭川市春光５条２丁目2-22 | J30: 田宮優衣 | K30: 090-6982-5183 | L30: 京都府京都市東山区妙法院前側町メゾンジョスラン 412 | M30: 605-0932 | N30: Kanken 16L (Navy 560) | O30: 1 | P30: 14300 | Q30: 1430 | R30: 000000000882 | S30: 23510 | T30: 23510560X | V30: Amazon Pay | W30: 14850 | X30: 550 | Z30: 0 | AA30: 0 | AB30: 0 | AC30: 10 | AD30: 0 | AE30: 0 | AG30: 佐川急便 | AM30: 伝達メッセージ : | AO30: 伝達メッセージ :
A31: 46203 | B31: 143752 | C31: P186939906199401290 | D31: PayPay [決済完了] | E31: 野田彩乃 | F31: 080-3963-1451 | G31: 8039631451 | I31: (880-0841) 宮崎県宮崎市吉村町西田甲656-5 | J31: 野田彩乃 | K31: 080-3963-1451 | L31: 宮崎県宮崎市吉村町西田甲656-5 | M31: 880-0841 | N31: Kanken Hip Pack | O31: 1 | P31: 8800 | Q31: 880 | R31: 000000000596 | S31: 23796 | T31: 23796115X | V31: PayPay | W31: 9790 | X31: 550 | Z31: 0 | AA31: 0 | AB31: 0 | AC31: 10 | AD31: 0 | AE31: 0 | AG31: 佐川急便 | AM31: 伝達メッセージ : | AO31: 伝達メッセージ :
A32: 46203 | B32: 143752 | C32: P186939906199401290 | D32: PayPay [決済完了] | E32: 野田彩乃 | F32: 080-3963-1451 | G32: 8039631451 | I32: (880-0841) 宮崎県宮崎市吉村町西田甲656-5 | J32: 野田彩乃 | K32: 080-3963-1451 | L32: 宮崎県宮崎市吉村町西田甲656-5 | M32: 880-0841 | N32: 【NEW】Gift Wrapping (M) | O32: 1 | P32: 440 | Q32: 44 | R32: 000000001472 | S32: GIFT400 | T32: GIFT400 | V32: PayPay | W32: 9790 | X32: 550 | Z32: 0 | AA32: 0 | AB32: 0 | AC32: 10 | AD32: 0 | AE32: 0 | AG32: 佐川急便 | AM32: 伝達メッセージ : | AO32: 伝達メッセージ :
A33: 46203 | B33: 133952 | C33: P186939541319158992 | D33: PGクレジットカード [決済完了] | E33: 木村世瑠奈 | F33: 080-7986-9082 | G33: 8079869082 | I33: (860-0035) 熊本県熊本市中央区呉服町2-5-6-701 | J33: 中川美啓 | K33: 090-8405-0506 | L33: 熊本県熊本市中央区坪井1-3-6-206 | M33: 860-0863 | N33: 【ミニ】Kanken Mini (Green 620) | O33: 1 | P33: 13200 | Q33: 1320 | R33: 000000001740 | S33: 23561 | T33: 23561620X | V33: PGクレジットカード | W33: 13750 | X33: 550 | Z33: 0 | AA33: 0 | AB33: 0 | AC33: 10 | AD33: 0 | AE33: 0 | AG33: 佐川急便 | AM33: 伝達メッセージ : | AO33: 伝達メッセージ :
A34: 46203 | B34: 113427 | C34: P186938752241301512 | D34: PGクレジットカード [決済完了] | E34: 平井俊介 | F34: 090-7278-0377 | G34: 9072780377 | I34: (252-1124) 神奈川県綾瀬市吉岡1968-10 | J34: 田村心 | K34: 080-9441-1125 | L34: 神奈川県横浜市旭区若葉台3-2-1320 | M34: 241-0801 | N34: Kanken 16L (Chalk Rose 302) | O34: 1 | P34: 14300 | Q34: 1430 | R34: 000000001723 | S34: 23510 | T34: 23510302X | V34: PGクレジットカード | W34: 14850 | X34: 550 | Z34: 0 | AA34: 0 | AB34: 0 | AC34: 10 | AD34: 0 | AE34: 0 | AG34: 佐川急便 | AM34: 伝達メッセージ : | AO34: 伝達メッセージ :
A35: 46203 | B35: 081414 | C35: P186937492531212070 | D35: Amazon Pay [決済完了] | E35: 井之上寿子 | F35: 042-708-9170 | G35: 427089170 | I35: (195-0073) 東京都町田市薬師台2-19-3 | J35: 井之上寿子 | K35: 042-708-9170 | L35: 東京都町田市薬師台2-19-3 | M35: 195-0073 | N35: Kanken 16L (Chalk Rose 302) | O35: 1 | P35: 14300 | Q35: 1430 | R35: 000000001723 | S35: 23510 | T35: 23510302X | V35: Amazon Pay | W35: 14850 | X35: 550 | Z35: 0 | AA35: 0 | AB35: 0 | AC35: 10 | AD35: 0 | AE35: 0 | AG35: 佐川急便 | AM35: 伝達メッセージ : | AO35: 伝達メッセージ :
A36: 46203 | B36: 065310 | C36: P186936982589581854 | D36: Amazon Pay [決済完了] | E36: 永嶋美華子 | F36: 080-3330-4037 | G36: 8033304037 | I36: (990-2423) 山形県山形市東青田2-1-7 | J36: 永嶋美華子 | K36: 080-3330-4037 | L36: 山形県山形市東青田2-1-7 | M36: 990-2423 | N36: Vardag Backpack 17 | O36: 1 | P36: 17050 | Q36: 1705 | R36: 000000001624 | S36: 23200300 | T36: 23200300354-228X | V36: Amazon Pay | W36: 17600 | X36: 550 | Z36: 0 | AA36: 0 | AB36: 0 | AC36: 10 | AD36: 0 | AE36: 0 | AG36: 佐川急便 | AM36: 伝達メッセージ : | AO36: 伝達メッセージ :
A37: 46203 | B37: 005827 | C37: P186934750900161998 | D37: PGクレジットカード [決済完了] | E37: 下山和子 | F37: 090-4754-7355 | G37: 9047547355 | I37: (371-0012) 群馬県前橋市東片貝町482 | J37: 下山和子 | K37: 090-4754-7355 | L37: 群馬県前橋市東片貝町482 | M37: 371-0012 | N37: Kanken 16L (Frost Green 664) | O37: 1 | P37: 14300 | Q37: 1430 | R37: 000000000897 | S37: 23510 | T37: 23510664X | V37: PGクレジットカード | W37: 14850 | X37: 550 | Z37: 0 | AA37: 0 | AB37: 0 | AC37: 10 | AD37: 0 | AE37: 0 | AG37: 佐川急便 | AM37: 伝達メッセージ : | AO37: 伝達メッセージ :
A38: 46202 | B38: 235918 | C38: P186934378738521684 | D38: 代金引換 [未入金] | E38: 本田美鳥 | F38: 090-3904-2870 | G38: 9039042870 | I38: (151-0072) 東京都渋谷区幡ヶ谷1-23-17-302 | J38: 本田美鳥 | K38: 090-3904-2870 | L38: 東京都渋谷区幡ヶ谷1-23-17-302 | M38: 151-0072 | N38: 【Women’s】Vardag Shorts W | O38: 1 | P38: 19800 | Q38: 1980 | R38: 000000001662 | S38: 87105 | T38: 8710503036 | V38: 代金引換 | W38: 20000 | X38: 550 | Z38: 440 | AA38: -790 | AB38: 0 | AC38: 10 | AD38: 0 | AE38: 0 | AG38: 佐川急便 | AM38: 伝達メッセージ : 木曜か土曜の18時-20時の時間指定での受け取りをお願いできればと思います | AO38: 伝達メッセージ : 木曜か土曜の18時-20時の時間指定での受け取りをお願いできればと思います
A39: 46202 | B39: 235435 | C39: P186934349043842164 | D39: PGクレジットカード [決済完了] | E39: 福田桃香 | F39: 080-5347-5352 | G39: 8053475352 | I39: (582-0029) 大阪府柏原市石川町7-24メゾンドール玉手山406号室 | J39: 福田桃香 | K39: 080-5347-5352 | L39: 大阪府柏原市石川町7-24メゾンドール玉手山406号室 | M39: 582-0029 | N39: Kanken Hip Pack | O39: 1 | P39: 8800 | Q39: 880 | R39: 000000000596 | S39: 23796 | T39: 23796312X | V39: PGクレジットカード | W39: 9350 | X39: 550 | Z39: 0 | AA39: 0 | AB39: 0 | AC39: 10 | AD39: 0 | AE39: 0 | AG39: 佐川急便 | AM39: 伝達メッセージ : | AO39: 伝達メッセージ :
A40: 46202 | B40: 234924 | C40: P186934316412265114 | D40: Amazon Pay [決済完了] | E40: 星野亜衣子 | F40: 080-6776-1140 | G40: 8067761140 | I40: (208-0032) 東京都武蔵村山市三ツ木1-25-27 | J40: 星野亜衣子 | K40: 080-6776-1140 | L40: 東京都武蔵村山市三ツ木1-25-27 | M40: 208-0032 | N40: Kanken 16L (Sky Blue 501) | O40: 1 | P40: 14300 | Q40: 1430 | R40: 000000000872 | S40: 23510 | T40: 23510501X | V40: Amazon Pay | W40: 14850 | X40: 550 | Z40: 0 | AA40: 0 | AB40: 0 | AC40: 10 | AD40: 0 | AE40: 0 | AG40: 佐川急便 | AM40: 伝達メッセージ : | AO40: 伝達メッセージ :
A41: 46202 | B41: 232651 | C41: P186934174609888011 | D41: Amazon Pay [決済完了] | E41: 辻本雄紀 | F41: 080-3783-8861 | G41: 8037838861 | I41: (158-0081) 東京都世田谷区深沢5-24-23 ルナコート等々力503号室 | J41: 辻本雄紀 | K41: 080-3783-8861 | L41: 東京都世田谷区深沢5-24-23 ルナコート等々力503号室 | M41: 158-0081 | N41: Kanken 16L (Chalk Rose 302) | O41: 1 | P41: 14300 | Q41: 1430 | R41: 000000001723 | S41: 23510 | T41: 23510302X | V41: Amazon Pay | W41: 14850 | X41: 550 | Z41: 0 | AA41: 0 | AB41: 0 | AC41: 10 | AD41: 0 | AE41: 0 | AG41: 佐川急便 | AM41: 伝達メッセージ : | AO41: 伝達メッセージ :
A42: 46202 | B42: 231110 | C42: P186934075917743692 | D42: Amazon Pay [決済完了] | E42: 後藤貴也 | F42: 042-810-0890 | G42: 428100890 | I42: (252-0104) 神奈川県相模原市緑区向原2-6-49 | J42: 後藤貴也 | K42: 042-810-0890 | L42: 神奈川県相模原市緑区向原2-6-49 | M42: 252-0104 | N42: Kanken 16L (Chalk Rose 302) | O42: 1 | P42: 14300 | Q42: 1430 | R42: 000000001723 | S42: 23510 | T42: 23510302X | V42: Amazon Pay | W42: 14850 | X42: 550 | Z42: 0 | AA42: 0 | AB42: 0 | AC42: 10 | AD42: 0 | AE42: 0 | AG42: 佐川急便 | AM42: 伝達メッセージ : | AO42: 伝達メッセージ :
A43: 46202 | B43: 230458 | C43: P186934036943334756 | D43: PGクレジットカード [決済完了] | E43: 山本昌之 | F43: 080-4027-8350 | G43: 8040278350 | I43: (615-8142) 京都府京都市西京区樫原畔ノ海道10-45 | J43: 山本昌之 | K43: 080-4027-8350 | L43: 京都府京都市西京区樫原畔ノ海道10-45 | M43: 615-8142 | N43: Kanken Organizer | O43: 1 | P43: 6050 | Q43: 605 | R43: 000000000712 | S43: 23508 | T43: 23508021X | V43: PGクレジットカード | W43: 27500 | X43: 550 | Z43: 0 | AA43: 0 | AB43: 0 | AC43: 10 | AD43: 0 | AE43: 0 | AG43: 佐川急便 | AM43: 伝達メッセージ : | AO43: 伝達メッセージ :
A44: 46202 | B44: 230458 | C44: P186934036943334756 | D44: PGクレジットカード [決済完了] | E44: 山本昌之 | F44: 080-4027-8350 | G44: 8040278350 | I44: (615-8142) 京都府京都市西京区樫原畔ノ海道10-45 | J44: 山本昌之 | K44: 080-4027-8350 | L44: 京都府京都市西京区樫原畔ノ海道10-45 | M44: 615-8142 | N44: Kanken Outlong | O44: 1 | P44: 20900 | Q44: 2090 | R44: 000000001495 | S44: 23200251 | T44: 23200251021X | V44: PGクレジットカード | W44: 27500 | X44: 550 | Z44: 0 | AA44: 0 | AB44: 0 | AC44: 10 | AD44: 0 | AE44: 0 | AG44: 佐川急便 | AM44: 伝達メッセージ : | AO44: 伝達メッセージ :
A45: 46202 | B45: 230151 | C45: P186934017264149576 | D45: 代金引換 [未入金] | E45: 佐藤真菜 | F45: 090-3408-2245 | G45: 9034082245 | I45: (366-0007) 埼玉県深谷市南阿賀野273 | J45: 佐藤真菜 | K45: 090-3408-2245 | L45: 埼玉県深谷市南阿賀野273 | M45: 366-0007 | N45: Kanken 16L (Chalk Rose 302) | O45: 1 | P45: 14300 | Q45: 1430 | R45: 000000001723 | S45: 23510 | T45: 23510302X | V45: 代金引換 | W45: 15290 | X45: 550 | Z45: 440 | AA45: 0 | AB45: 0 | AC45: 10 | AD45: 0 | AE45: 0 | AG45: 佐川急便 | AM45: 伝達メッセージ : | AO45: 伝達メッセージ :
A46: 46202 | B46: 222849 | C46: P186933809460448813 | D46: 代金引換 [未入金] | E46: 直井愛心 | F46: 080-9576-3755 | G46: 8095763755 | I46: (300-3264) 茨城県つくば市篠崎2120-30 | J46: 直井愛心 | K46: 080-9576-3755 | L46: 茨城県つくば市篠崎2120-30 | M46: 300-3264 | N46: Kanken 16L (Pastel Lavender 457) | O46: 1 | P46: 14300 | Q46: 1430 | R46: 000000000870 | S46: 23510 | T46: 23510457X | V46: 代金引換 | W46: 15290 | X46: 550 | Z46: 440 | AA46: 0 | AB46: 0 | AC46: 10 | AD46: 0 | AE46: 0 | AG46: 佐川急便 | AM46: 伝達メッセージ : | AO46: 伝達メッセージ :
A47: 46202 | B47: 222456 | C47: P186933785012667092 | D47: PayPay [決済完了] | E47: 渡邉斗夢 | F47: 090-1258-8716 | G47: 9012588716 | I47: (340-0002) 埼玉県草加市青柳5-5-20 コンフォート201 | J47: 渡邉斗夢 | K47: 090-1258-8716 | L47: 埼玉県草加市青柳5-5-20 コンフォート201 | M47: 340-0002 | N47: Kanken Hip Pack | O47: 1 | P47: 8800 | Q47: 880 | R47: 000000000596 | S47: 23796 | T47: 23796550X | V47: PayPay | W47: 9790 | X47: 550 | Z47: 0 | AA47: 0 | AB47: 0 | AC47: 10 | AD47: 0 | AE47: 0 | AG47: 佐川急便 | AM47: 伝達メッセージ : | AO47: 伝達メッセージ :
A48: 46202 | B48: 222456 | C48: P186933785012667092 | D48: PayPay [決済完了] | E48: 渡邉斗夢 | F48: 090-1258-8716 | G48: 9012588716 | I48: (340-0002) 埼玉県草加市青柳5-5-20 コンフォート201 | J48: 渡邉斗夢 | K48: 090-1258-8716 | L48: 埼玉県草加市青柳5-5-20 コンフォート201 | M48: 340-0002 | N48: 【NEW】Gift Wrapping (M) | O48: 1 | P48: 440 | Q48: 44 | R48: 000000001472 | S48: GIFT400 | T48: GIFT400 | V48: PayPay | W48: 9790 | X48: 550 | Z48: 0 | AA48: 0 | AB48: 0 | AC48: 10 | AD48: 0 | AE48: 0 | AG48: 佐川急便 | AM48: 伝達メッセージ : | AO48: 伝達メッセージ :
A49: 46202 | B49: 214601 | C49: P186933540189044259 | D49: Amazon Pay [要確認] | E49: 田中真央 | F49: 080-2461-0874 | G49: 8024610874 | I49: (606-8231) 京都府京都市左京区田中上古川町34-34 メゾン高野 508号室 | J49: 田中真央 | K49: 080-2461-0874 | L49: 京都府京都市左京区田中上古川町34-34 メゾン高野 508号室 | M49: 606-8231 | N49: Kanken 16L (Green 620) | O49: 1 | P49: 14300 | Q49: 1430 | R49: 000000001739 | S49: 23510 | T49: 23510620X | V49: Amazon Pay | W49: 14850 | X49: 550 | Z49: 0 | AA49: 0 | AB49: 0 | AC49: 10 | AD49: 0 | AE49: 0 | AG49: 佐川急便 | AM49: 伝達メッセージ : | AO49: 伝達メッセージ : | AP49: 要確認 Amazon Pay → (6/30) info.より再注文依頼済。こちらはキャンセルします。
A50: 46202 | B50: 195643 | C50: P186932852527452561 | D50: PGクレジットカード [決済完了] | E50: 吉川亜希子 | F50: 080-5063-0624 | G50: 8050630624 | I50: (368-0045) 埼玉県秩父市道生町23-9 | J50: 吉川亜希子 | K50: 080-5063-0624 | L50: 埼玉県秩父市道生町23-9 | M50: 368-0045 | N50: Kanken Hip Pack | O50: 1 | P50: 8800 | Q50: 880 | R50: 000000000596 | S50: 23796 | T50: 23796560X | V50: PGクレジットカード | W50: 9350 | X50: 550 | Z50: 0 | AA50: 0 | AB50: 0 | AC50: 10 | AD50: 0 | AE50: 0 | AG50: 佐川急便 | AM50: 伝達メッセージ : | AO50: 伝達メッセージ :
A51: 46202 | B51: 195429 | C51: P186932838466944351 | D51: PGクレジットカード [決済完了] | E51: 吉川亜希子 | F51: 080-5063-0624 | G51: 8050630624 | I51: (368-0045) 埼玉県秩父市道生町23-9 | J51: 吉川亜希子 | K51: 080-5063-0624 | L51: 埼玉県秩父市道生町23-9 | M51: 368-0045 | N51: Kanken Hip Pack | O51: 1 | P51: 8800 | Q51: 880 | R51: 000000000596 | S51: 23796 | T51: 23796620X | V51: PGクレジットカード | W51: 9350 | X51: 550 | Z51: 0 | AA51: 0 | AB51: 0 | AC51: 10 | AD51: 0 | AE51: 0 | AG51: 佐川急便 | AM51: 伝達メッセージ : | AO51: 伝達メッセージ :
A52: 46202 | B52: 194725 | C52: P186932794010842690 | D52: 代金引換 [未入金] | E52: 鈴木希実 | F52: 080-2136-8300 | G52: 8021368300 | I52: (940-0829) 新潟県長岡市長倉3丁目660番地 | J52: 鈴木希実 | K52: 080-2136-8300 | L52: 新潟県長岡市長倉3丁目660番地 | M52: 940-0829 | N52: Kanken 16L (Sky Blue 501) | O52: 1 | P52: 14300 | Q52: 1430 | R52: 000000000872 | S52: 23510 | T52: 23510501X | V52: 代金引換 | W52: 15290 | X52: 550 | Z52: 440 | AA52: 0 | AB52: 0 | AC52: 10 | AD52: 0 | AE52: 0 | AG52: 佐川急便 | AM52: 伝達メッセージ : | AO52: 伝達メッセージ :
A53: 46202 | B53: 191528 | C53: P186932592981204757 | D53: 代金引換 [未入金] | E53: 日野朱 | F53: 090-1068-0733 | G53: 9010680733 | I53: (981-3132) 宮城県仙台市泉区将監12-16-3 | J53: 日野朱 | K53: 090-1068-0733 | L53: 宮城県仙台市泉区将監12-16-3 | M53: 981-3132 | N53: Kanken Laptop 15 | O53: 1 | P53: 19800 | Q53: 1980 | R53: 000000001143 | S53: 23524 | T53: 23524326X | V53: 代金引換 | W53: 20790 | X53: 550 | Z53: 440 | AA53: 0 | AB53: 0 | AC53: 10 | AD53: 0 | AE53: 0 | AG53: 佐川急便 | AM53: 伝達メッセージ : | AO53: 伝達メッセージ :
A54: 46202 | B54: 183317 | C54: P186932327585742354 | D54: PGクレジットカード [決済完了] | E54: 中根里菜 | F54: 070-8460-3818 | G54: 7084603818 | I54: (135-0007) 東京都江東区新大橋2-10-5 OAKLANCE森下2 503 | J54: 中根里菜 | K54: 070-8460-3818 | L54: 東京都江東区新大橋2-10-5 OAKLANCE森下2 503 | M54: 135-0007 | N54: 【NEW】Gift Wrapping (M) | O54: 1 | P54: 440 | Q54: 44 | R54: 000000001472 | S54: GIFT400 | T54: GIFT400 | V54: PGクレジットカード | W54: 8140 | X54: 550 | Z54: 0 | AA54: 0 | AB54: 0 | AC54: 10 | AD54: 0 | AE54: 0 | AG54: 佐川急便 | AM54: 伝達メッセージ : | AO54: 伝達メッセージ :
A55: 46202 | B55: 183317 | C55: P186932327585742354 | D55: PGクレジットカード [決済完了] | E55: 中根里菜 | F55: 070-8460-3818 | G55: 7084603818 | I55: (135-0007) 東京都江東区新大橋2-10-5 OAKLANCE森下2 503 | J55: 中根里菜 | K55: 070-8460-3818 | L55: 東京都江東区新大橋2-10-5 OAKLANCE森下2 503 | M55: 135-0007 | N55: Walk With Nature T-Shirt M | O55: 1 | P55: 7150 | Q55: 715 | R55: 000000001503 | S55: 12600216 | T55: 12600216555L | V55: PGクレジットカード | W55: 8140 | X55: 550 | Z55: 0 | AA55: 0 | AB55: 0 | AC55: 10 | AD55: 0 | AE55: 0 | AG55: 佐川急便 | AM55: 伝達メッセージ : | AO55: 伝達メッセージ :
A56: 46202 | B56: 174210 | C56: P186932005994144493 | D56: 代金引換 [未入金] | E56: Fista | F56: 080-5294-5778 | G56: 8052945778 | I56: (279-0002) 千葉県Urayasu-shi北栄4－4－7レオパレスラトナ205 | J56: Fista | K56: 080-5294-5778 | L56: 千葉県Urayasu-shi北栄4－4－7レオパレスラトナ205 | M56: 279-0002 | N56: Kanken 16L (Pastel Lavender 457) | O56: 1 | P56: 14300 | Q56: 1430 | R56: 000000000870 | S56: 23510 | T56: 23510457X | V56: 代金引換 | W56: 15290 | X56: 550 | Z56: 440 | AA56: 0 | AB56: 0 | AC56: 10 | AD56: 0 | AE56: 0 | AG56: 佐川急便 | AM56: 伝達メッセージ : | AO56: 伝達メッセージ :
A57: 46202 | B57: 171614 | C57: P186931842807814928 | D57: 代金引換 [未入金] | E57: 下村千悠 | F57: 080-8728-0759 | G57: 8087280759 | I57: (332-0011) 埼玉県川口市元郷1-1-30 ビーサイト701号室 | J57: 下村千悠 | K57: 080-8728-0759 | L57: 埼玉県川口市元郷1-1-30 ビーサイト701号室 | M57: 332-0011 | N57: Kanken 16L (Blackberry 424) | O57: 1 | P57: 14300 | Q57: 1430 | R57: 000000001481 | S57: 23510 | T57: 23510424X | V57: 代金引換 | W57: 15290 | X57: 550 | Z57: 440 | AA57: 0 | AB57: 0 | AC57: 10 | AD57: 0 | AE57: 0 | AG57: 佐川急便 | AM57: 伝達メッセージ : | AO57: 伝達メッセージ :
A58: 46202 | B58: 170753 | C58: P186931790326699898 | D58: 代金引換 [未入金] | E58: AdistyHildaKamalia | F58: 070-1430-0677 | G58: 7014300677 | I58: (023-0026) 岩手県奥州市水沢里鎗Mizusawa Residence, Satouyari, 3 Banchi, Building 2, Room 306, Oshu-shi, Iwate | J58: AdistyHildaKamalia | K58: 070-1430-0677 | L58: 岩手県奥州市水沢里鎗Mizusawa Residence, Satouyari, 3 Banchi, Building 2, Room 306, Oshu-shi, Iwate | M58: 023-0026 | N58: Kanken 16L (Frost Green 664) | O58: 1 | P58: 14300 | Q58: 1430 | R58: 000000000897 | S58: 23510 | T58: 23510664X | V58: 代金引換 | W58: 15290 | X58: 550 | Z58: 440 | AA58: 0 | AB58: 0 | AC58: 10 | AD58: 0 | AE58: 0 | AG58: 佐川急便 | AM58: 伝達メッセージ : | AO58: 伝達メッセージ :
A59: 46202 | B59: 165553 | C59: P186931714800738802 | D59: 代金引換 [未入金] | E59: 加藤由紀子 | F59: 090-2244-9742 | G59: 9022449742 | I59: (212-0052) 神奈川県川崎市幸区古市場2-96-16 | J59: 加藤由紀子 | K59: 090-2244-9742 | L59: 神奈川県川崎市幸区古市場2-96-16 | M59: 212-0052 | N59: Kanken 16L (Pastel Lavender-Confetti Pattern) | O59: 1 | P59: 14300 | Q59: 1430 | R59: 000000001550 | S59: 23510 | T59: 23510457-916X | V59: 代金引換 | W59: 15290 | X59: 550 | Z59: 440 | AA59: 0 | AB59: 0 | AC59: 10 | AD59: 0 | AE59: 0 | AG59: 佐川急便 | AM59: 伝達メッセージ : | AO59: 伝達メッセージ :
A60: 46202 | B60: 163246 | C60: P186931569404221136 | D60: Amazon Pay [決済完了] | E60: 田中惠美子 | F60: 0586-43-3221 | G60: 586433221 | I60: (491-0914) 愛知県一宮市花池3-13-15 | J60: 田中江史子 | K60: 0586-43-3221 | L60: 愛知県一宮市花池3－13－15 life | M60: 491-0914 | N60: Kanken Totepack Mini | O60: 1 | P60: 15400 | Q60: 1540 | R60: 000000000595 | S60: 23711 | T60: 23711350X | V60: Amazon Pay | W60: 15950 | X60: 550 | Z60: 0 | AA60: 0 | AB60: 0 | AC60: 10 | AD60: 0 | AE60: 0 | AG60: 佐川急便 | AM60: 伝達メッセージ : | AO60: 伝達メッセージ :
A61: 46202 | B61: 150743 | C61: P186931034332195800 | D61: Amazon Pay [決済完了] | E61: 久多良木亮 | F61: 090-9075-2283 | G61: 9090752283 | I61: (224-0037) 神奈川県横浜市都筑区茅ケ崎南5丁目26－10－202 | J61: 久多良木亮 | K61: 090-9075-2283 | L61: 神奈川県横浜市都筑区茅ケ崎南5丁目26－10－202 | M61: 224-0037 | N61: Kanken 16L (Chalk Rose 302) | O61: 1 | P61: 14300 | Q61: 1430 | R61: 000000001723 | S61: 23510 | T61: 23510302X | V61: Amazon Pay | W61: 14850 | X61: 550 | Z61: 0 | AA61: 0 | AB61: 0 | AC61: 10 | AD61: 0 | AE61: 0 | AG61: 佐川急便 | AM61: 伝達メッセージ : | AO61: 伝達メッセージ :
... A63: 46202 | B63: 150413 | C63: P186931012299454347 | D63: Amazon Pay [決済完了] | E63: 岩本摩美 | F63: 090-9232-1163 | G63: 9092321163 | I63: (336-0042) 埼玉県さいたま市南区大谷口1257-15メゾングレイス 403 | J63: 手嶋礼子 | K63: 090-9232-1163 | L63: 東京都板橋区大山金井町20-5 | M63: 173-0024 | N63: 【ミニ】Kanken Mini (Green 620) | O63: 1 | P63: 13200 | Q63: 1320 | R63: 000000001740 | S63: 23561 | T63: 23561620X | V63: Amazon Pay | W63: 14190 | X63: 550 | Z63: 0 | AA63: 0 | AB63: 0 | AC63: 10 | AD63: 0 | AE63: 0 | AG63: 佐川急便 | AM63: 伝達メッセージ : | AO63: 伝達メッセージ :
A64: 46202 | B64: 135601 | C64: P186930583218107119 | D64: Amazon Pay [決済完了] | E64: 内山尊弘 | F64: 090-9318-1310 | G64: 9093181310 | I64: (107-0052) 東京都港区赤坂7-5-16-207 | J64: 林田潤子 | K64: 090-6291-1568 | L64: 東京都港区赤坂7-5-16 オープンレジデンス赤坂テラス 207 | M64: 107-0052 | N64: Pocket | O64: 1 | P64: 6600 | Q64: 660 | R64: 000000000170 | S64: 24221 | T64: 24221030X | V64: Amazon Pay | W64: 5968 | X64: 550 | Z64: 0 | AA64: -1182 | AB64: 0 | AC64: 10 | AD64: 0 | AE64: 0 | AG64: 佐川急便 | AI64: 46203 | AK64: 20260630175033 | AL64: 518875580974 | AM64: 伝達メッセージ : | AO64: 伝達メッセージ :
A65: 46202 | B65: 130900 | C65: P186930287384244999 | D65: PGクレジットカード [決済完了] | E65: 大川彩花 | F65: 080-5695-1993 | G65: 8056951993 | I65: (191-0022) 東京都日野市新井1-6-17 | J65: 大川彩花 | K65: 080-5695-1993 | L65: 東京都日野市新井1-6-17 | M65: 191-0022 | N65: Kanken Totepack | O65: 1 | P65: 16500 | Q65: 1650 | R65: 000000000594 | S65: 23710 | T65: 23710501X | V65: PGクレジットカード | W65: 16335 | X65: 550 | Z65: 0 | AA65: -715 | AB65: 0 | AC65: 10 | AD65: 0 | AE65: 0 | AG65: 佐川急便 | AI65: 46203 | AK65: 20260630170511 | AL65: 518875580414 | AM65: 伝達メッセージ : | AO65: 伝達メッセージ :
A66: 46202 | B66: 130343 | C66: P186930254148699933 | D66: PGクレジットカード [決済完了] | E66: 郡司聖子 | F66: 080-9995-0721 | G66: 8099950721 | I66: (363-0007) 埼玉県桶川市小針領家646 | J66: 郡司聖子 | K66: 080-9995-0721 | L66: 埼玉県桶川市小針領家646 | M66: 363-0007 | N66: Greenland Shoulder Bag | O66: 1 | P66: 22000 | Q66: 2200 | R66: 000000000292 | S66: 23154 | T66: 23154042X | V66: PGクレジットカード | W66: 32230 | X66: 550 | Z66: 0 | AA66: -6820 | AB66: 0 | AC66: 10 | AD66: 0 | AE66: 0 | AG66: 佐川急便 | AI66: 46203 | AK66: 20260630174826 | AL66: 518875580941 | AM66: 伝達メッセージ : | AO66: 伝達メッセージ :
A67: 46202 | B67: 130343 | C67: P186930254148699933 | D67: PGクレジットカード [決済完了] | E67: 郡司聖子 | F67: 080-9995-0721 | G67: 8099950721 | I67: (363-0007) 埼玉県桶川市小針領家646 | J67: 郡司聖子 | K67: 080-9995-0721 | L67: 埼玉県桶川市小針領家646 | M67: 363-0007 | N67: 【Women’s】Abisko Hike Shirt W | O67: 1 | P67: 16500 | Q67: 1650 | R67: 000000001649 | S67: 14600167 | T67: 14600167560XS | V67: PGクレジットカード | W67: 32230 | X67: 550 | Z67: 0 | AA67: -6820 | AB67: 0 | AC67: 10 | AD67: 0 | AE67: 0 | AG67: 佐川急便 | AI67: 46203 | AK67: 20260630174826 | AL67: 518875580941 | AM67: 伝達メッセージ : | AO67: 伝達メッセージ :
A68: 46202 | B68: 095227 | C68: P186929050836914449 | D68: PayPay [決済完了] | E68: 小林悠太 | F68: 080-4299-7225 | G68: 8042997225 | I68: (273-0103) 千葉県鎌ケ谷市丸山3-10-7 ウッドベル2 201号 | J68: 小林悠太 | K68: 080-4299-7225 | L68: 千葉県鎌ケ谷市丸山3-10-7 ウッドベル2 201号 | M68: 273-0103 | N68: Bergtagen Cap | O68: 1 | P68: 8250 | Q68: 825 | R68: 000000001242 | S68: 77404 | T68: 77404550X | V68: PayPay | W68: 8800 | X68: 550 | Z68: 0 | AA68: 0 | AB68: 0 | AC68: 10 | AD68: 0 | AE68: 0 | AG68: 佐川急便 | AI68: 46203 | AK68: 20260630181336 | AL68: 518875581151 | AM68: 伝達メッセージ : | AO68: 伝達メッセージ :
A69: 46202 | B69: 094130 | C69: P186928981873692771 | D69: PayPay [決済完了] | E69: 小林悠太 | F69: 080-4299-7225 | G69: 8042997225 | I69: (273-0103) 千葉県鎌ケ谷市丸山3-10-7 ウッドベル2 201号 | J69: 小林悠太 | K69: 080-4299-7225 | L69: 千葉県鎌ケ谷市丸山3-10-7 ウッドベル2 201号 | M69: 273-0103 | N69: Leather Passport Cover | O69: 1 | P69: 12100 | Q69: 1210 | R69: 000000000355 | S69: 77363 | T69: 77363550X | V69: PayPay | W69: 12650 | X69: 550 | Z69: 0 | AA69: 0 | AB69: 0 | AC69: 10 | AD69: 0 | AE69: 0 | AG69: 佐川急便 | AI69: 46203 | AK69: 20260630181523 | AL69: 518875581184 | AM69: 伝達メッセージ : | AO69: 伝達メッセージ :
A70: 46202 | B70: 092418 | C70: P186928873721071276 | D70: PayPay [決済完了] | E70: 小林悠太 | F70: 080-4299-7225 | G70: 8042997225 | I70: (273-0103) 千葉県鎌ケ谷市丸山3-10-7 ウッドベル2 201号 | J70: 小林悠太 | K70: 080-4299-7225 | L70: 千葉県鎌ケ谷市丸山3-10-7 ウッドベル2 201号 | M70: 273-0103 | N70: Kanken Gear Pocket | O70: 1 | P70: 4400 | Q70: 440 | R70: 000000000723 | S70: 25863 | T70: 25863550X | V70: PayPay | W70: 4950 | X70: 550 | Z70: 0 | AA70: 0 | AB70: 0 | AC70: 10 | AD70: 0 | AE70: 0 | AG70: 佐川急便 | AI70: 46203 | AK70: 20260630181429 | AL70: 518875581173 | AM70: 伝達メッセージ : | AO70: 伝達メッセージ :
A71: 46202 | B71: 091409 | C71: P186928809801655891 | D71: PayPay [決済完了] | E71: 小林悠太 | F71: 080-4299-7225 | G71: 8042997225 | I71: (273-0103) 千葉県鎌ケ谷市丸山3-10-7 ウッドベル2 201号 | J71: 小林悠太 | K71: 080-4299-7225 | L71: 千葉県鎌ケ谷市丸山3-10-7 ウッドベル2 201号 | M71: 273-0103 | N71: Kanken Gear Bag | O71: 1 | P71: 6050 | Q71: 605 | R71: 000000000943 | S71: 25862 | T71: 25862550X | V71: PayPay | W71: 6600 | X71: 550 | Z71: 0 | AA71: 0 | AB71: 0 | AC71: 10 | AD71: 0 | AE71: 0 | AG71: 佐川急便 | AI71: 46203 | AK71: 20260630181835 | AL71: 518875581243 | AM71: 伝達メッセージ : | AO71: 伝達メッセージ :
A72: 46202 | B72: 030246 | C72: P186926473277653027 | D72: PayPay [決済完了] | E72: 小林悠太 | F72: 080-4299-7225 | G72: 8042997225 | I72: (272-0132) 千葉県市川市湊新田6-11 サニーハイツ202 | J72: 小林悠太 | K72: 080-4299-7225 | L72: 千葉県市川市湊新田6-11 サニーハイツ202 | M72: 272-0132 | N72: Kanken Key Ring | O72: 1 | P72: 1650 | Q72: 165 | R72: 000000000290 | S72: 23785 | T72: 23785550X | V72: PayPay | W72: 2200 | X72: 550 | Z72: 0 | AA72: 0 | AB72: 0 | AC72: 10 | AD72: 0 | AE72: 0 | AG72: 佐川急便 | AI72: 46203 | AK72: 20260630181734 | AL72: 518875581232 | AM72: 伝達メッセージ : | AO72: 伝達メッセージ :
A73: 46202 | B73: 025651 | C73: P186926436065463509 | D73: PayPay [決済完了] | E73: 小林悠太 | F73: 080-4299-7225 | G73: 8042997225 | I73: (272-0132) 千葉県市川市湊新田6-11 サニーハイツ202 | J73: 小林悠太 | K73: 080-4299-7225 | L73: 千葉県市川市湊新田6-11 サニーハイツ202 | M73: 272-0132 | N73: Ovik Card Holder | O73: 1 | P73: 4400 | Q73: 440 | R73: 000000000298 | S73: 77308 | T73: 77308550X | V73: PayPay | W73: 4950 | X73: 550 | Z73: 0 | AA73: 0 | AB73: 0 | AC73: 10 | AD73: 0 | AE73: 0 | AG73: 佐川急便 | AI73: 46203 | AK73: 20260630181634 | AL73: 518875581206 | AM73: 伝達メッセージ : | AO73: 伝達メッセージ :
A74: 46202 | B74: 011353 | C74: P186925788271782569 | D74: PGクレジットカード [決済完了] | E74: 織田俊明 | F74: 055-253-7591 | G74: 552537591 | I74: (400-0027) 山梨県甲府市 富士見1-16-13 | J74: 織田俊明 | K74: 055-253-7591 | L74: 山梨県甲府市 富士見1-16-13 | M74: 400-0027 | N74: Gear Bag | O74: 1 | P74: 4730 | Q74: 473 | R74: 000000000051 | S74: 24213 | T74: 24213030X | V74: PGクレジットカード | W74: 11660 | X74: 550 | Z74: 0 | AA74: 0 | AB74: 0 | AC74: 10 | AD74: 0 | AE74: 0 | AG74: 佐川急便 | AI74: 46203 | AK74: 20260630180113 | AL74: 518875581125 | AM74: 伝達メッセージ : | AO74: 伝達メッセージ :
A75: 46202 | B75: 011353 | C75: P186925788271782569 | D75: PGクレジットカード [決済完了] | E75: 織田俊明 | F75: 055-253-7591 | G75: 552537591 | I75: (400-0027) 山梨県甲府市 富士見1-16-13 | J75: 織田俊明 | K75: 055-253-7591 | L75: 山梨県甲府市 富士見1-16-13 | M75: 400-0027 | N75: Gear Bag Large | O75: 1 | P75: 6380 | Q75: 638 | R75: 000000000089 | S75: 24214 | T75: 24214633X | V75: PGクレジットカード | W75: 11660 | X75: 550 | Z75: 0 | AA75: 0 | AB75: 0 | AC75: 10 | AD75: 0 | AE75: 0 | AG75: 佐川急便 | AI75: 46203 | AK75: 20260630180113 | AL75: 518875581125 | AM75: 伝達メッセージ : | AO75: 伝達メッセージ :
... A85: 46201 | B85: 222301 | C85: P186924713310468051 | D85: Amazon Pay [決済完了] | E85: 井田かなえ | F85: 090-6140-2461 | G85: 9061402461 | I85: (332-0034) 埼玉県川口市並木2-16-14 グランカーサ川口並木 603 | J85: 井田かなえ | K85: 090-6140-2461 | L85: 埼玉県川口市並木2-16-14 グランカーサ川口並木 603 | M85: 332-0034 | N85: Kanken No. 2 | O85: 1 | P85: 22000 | Q85: 2200 | R85: 000000000068 | S85: 23565 | T85: 23565560X | V85: Amazon Pay | W85: 22550 | X85: 550 | Z85: 0 | AA85: 0 | AB85: 0 | AC85: 10 | AD85: 0 | AE85: 0 | AG85: 佐川急便 | AI85: 46203 | AK85: 20260630173909 | AL85: 518875580801 | AM85: 伝達メッセージ : | AO85: 伝達メッセージ :
A86: 46201 | B86: 222043 | C86: P186924789093668061 | D86: Yahoo!ショッピングPayPay残高払い [決済完了] | E86: 菊川寛生 | F86: 9028724636 | G86: 9028724636 | I86: (061-1277) 北海道北広島市大曲光4-1-8 | J86: 菊川寛生 | K86: 9028724636 | L86: 北海道北広島市大曲光4-1-8 | M86: 061-1277 | N86: Sormland Reversible Beanie | O86: 1 | P86: 9900 | Q86: 10 | R86: 000000001608 | S86: 13100179 | T86: 13100179633X | V86: Yahoo!ショッピングPayPay残高払い | W86: 9900 | X86: 0 | Z86: 0 | AA86: 0 | AB86: 0 | AC86: 10 | AD86: 0 | AE86: 0 | AG86: 当店規定の配送方法（Yahoo!ショッピングの注文） | AI86: 46203 | AK86: 20260630180403 | AL86: 518875581210 | AM86: 伝達メッセージ : | AO86: 伝達メッセージ :
A87: 46201 | B87: 215750 | C87: P186924554802907806 | D87: Amazon Pay [決済完了] | E87: 藤崎文江 | F87: 090-7877-3273 | G87: 9078773273 | I87: (285-0855) 千葉県佐倉市井野1579-9 | J87: 藤崎文江 | K87: 090-7877-3273 | L87: 千葉県佐倉市井野1579-9 | M87: 285-0855 | N87: Kanken 16L (Royal Blue 540) | O87: 1 | P87: 14300 | Q87: 1430 | R87: 000000000880 | S87: 23510 | T87: 23510540X | V87: Amazon Pay | W87: 14850 | X87: 550 | Z87: 0 | AA87: 0 | AB87: 0 | AC87: 10 | AD87: 0 | AE87: 0 | AG87: 佐川急便 | AI87: 46203 | AK87: 20260630171636 | AL87: 518875580510 | AM87: 伝達メッセージ : | AO87: 伝達メッセージ :
A88: 46201 | B88: 215619 | C88: P186924545325392393 | D88: PGクレジットカード [決済完了] | E88: 栗原月 | F88: 090-4134-5012 | G88: 9041345012 | I88: (347-0068) 埼玉県加須市大門町20-64 花椿Ⅰ 205号室 | J88: 栗原月 | K88: 090-4134-5012 | L88: 埼玉県加須市大門町20-64 花椿Ⅰ 205号室 | M88: 347-0068 | N88: Kanken 16L (Sky Blue 501) | O88: 1 | P88: 14300 | Q88: 1430 | R88: 000000000872 | S88: 23510 | T88: 23510501X | V88: PGクレジットカード | W88: 14850 | X88: 550 | Z88: 0 | AA88: 0 | AB88: 0 | AC88: 10 | AD88: 0 | AE88: 0 | AG88: 佐川急便 | AI88: 46203 | AK88: 20260630172747 | AL88: 518875580646 | AM88: 伝達メッセージ : | AO88: 伝達メッセージ :
A89: 46201 | B89: 214113 | C89: P186924450259454974 | D89: PGクレジットカード [決済完了] | E89: 前田祐吾 | F89: 090-9559-6210 | G89: 9095596210 | I89: (781-5233) 高知県香南市野市町大谷309-5 | J89: 前田祐吾 | K89: 090-9559-6210 | L89: 高知県香南市野市町大谷309-5 | M89: 781-5233 | N89: Kanken 16L (Fossil 118) | O89: 1 | P89: 14300 | Q89: 1430 | R89: 000000001619 | S89: 23510 | T89: 23510118X | V89: PGクレジットカード | W89: 14850 | X89: 550 | Z89: 0 | AA89: 0 | AB89: 0 | AC89: 10 | AD89: 0 | AE89: 0 | AG89: 佐川急便 | AI89: 46203 | AK89: 20260630170415 | AL89: 518875580403 | AM89: 伝達メッセージ : | AO89: 伝達メッセージ :
A90: 46201 | B90: 212035 | C90: P186924320474226697 | D90: Amazon Pay [決済完了] | E90: 谷口哲雄 | F90: 0748-42-7437 | G90: 748427437 | I90: (521-1202) 滋賀県東近江市阿弥陀堂町437 | J90: 谷口哲雄 | K90: 0748-42-7437 | L90: 滋賀県東近江市阿弥陀堂町437 | M90: 521-1202 | N90: High Coast Crossbody | O90: 1 | P90: 11000 | Q90: 1100 | R90: 000000001383 | S90: 23227 | T90: 23227452X | V90: Amazon Pay | W90: 11990 | X90: 550 | Z90: 0 | AA90: 0 | AB90: 0 | AC90: 10 | AD90: 0 | AE90: 0 | AG90: 佐川急便 | AI90: 46203 | AK90: 20260630174622 | AL90: 518875580915 | AM90: 伝達メッセージ : | AO90: 伝達メッセージ :
A91: 46201 | B91: 212035 | C91: P186924320474226697 | D91: Amazon Pay [決済完了] | E91: 谷口哲雄 | F91: 0748-42-7437 | G91: 748427437 | I91: (521-1202) 滋賀県東近江市阿弥陀堂町437 | J91: 谷口哲雄 | K91: 0748-42-7437 | L91: 滋賀県東近江市阿弥陀堂町437 | M91: 521-1202 | N91: 【NEW】Gift Wrapping (M) | O91: 1 | P91: 440 | Q91: 44 | R91: 000000001472 | S91: GIFT400 | T91: GIFT400 | V91: Amazon Pay | W91: 11990 | X91: 550 | Z91: 0 | AA91: 0 | AB91: 0 | AC91: 10 | AD91: 0 | AE91: 0 | AG91: 佐川急便 | AI91: 46203 | AK91: 20260630174622 | AL91: 518875580915 | AM91: 伝達メッセージ : | AO91: 伝達メッセージ :
A92: 46201 | B92: 205901 | C92: P186924184791623839 | D92: Amazon Pay [決済完了] | E92: 岩崎亜由美 | F92: 04-7123-4557 | G92: 471234557 | I92: (278-0057) 千葉県野田市光葉町3-32-12 | J92: 岩崎亜由美 | K92: 04-7123-4557 | L92: 千葉県野田市光葉町3-32-12 | M92: 278-0057 | N92: Kanken 16L (Pastel Lavender 457) | O92: 1 | P92: 14300 | Q92: 1430 | R92: 000000000870 | S92: 23510 | T92: 23510457X | V92: Amazon Pay | W92: 14850 | X92: 550 | Z92: 0 | AA92: 0 | AB92: 0 | AC92: 10 | AD92: 0 | AE92: 0 | AG92: 佐川急便 | AI92: 46203 | AK92: 20260630172425 | AL92: 518875580602 | AM92: 伝達メッセージ : | AO92: 伝達メッセージ :
A93: 46201 | B93: 204213 | C93: P186924079091322426 | D93: Amazon Pay [決済完了] | E93: 北恵仁司 | F93: 090-9975-4706 | G93: 9099754706 | I93: (277-0005) 千葉県柏市柏1ー7ー1ー1811 | J93: 北恵仁司 | K93: 090-9975-4706 | L93: 千葉県柏市柏1ー7ー1ー1811 | M93: 277-0005 | N93: Greenland Wax travel pack | O93: 1 | P93: 935 | Q93: 93 | R93: 000000000031 | S93: 79030 | T93: 79030X | V93: Amazon Pay | W93: 37620 | X93: 550 | Z93: 0 | AA93: -2365 | AB93: 0 | AC93: 10 | AD93: 0 | AE93: 0 | AG93: 佐川急便 | AI93: 46203 | AK93: 20260630174337 | AL93: 518875580871 | AM93: 伝達メッセージ : | AO93: 伝達メッセージ :
A94: 46201 | B94: 204213 | C94: P186924079091322426 | D94: Amazon Pay [決済完了] | E94: 北恵仁司 | F94: 090-9975-4706 | G94: 9099754706 | I94: (277-0005) 千葉県柏市柏1ー7ー1ー1811 | J94: 北恵仁司 | K94: 090-9975-4706 | L94: 千葉県柏市柏1ー7ー1ー1811 | M94: 277-0005 | N94: High Coast Crossbody | O94: 1 | P94: 11000 | Q94: 1100 | R94: 000000001383 | S94: 23227 | T94: 23227543X | V94: Amazon Pay | W94: 37620 | X94: 550 | Z94: 0 | AA94: -2365 | AB94: 0 | AC94: 10 | AD94: 0 | AE94: 0 | AG94: 佐川急便 | AI94: 46203 | AK94: 20260630174337 | AL94: 518875580871 | AM94: 伝達メッセージ : | AO94: 伝達メッセージ :
A95: 46201 | B95: 204213 | C95: P186924079091322426 | D95: Amazon Pay [決済完了] | E95: 北恵仁司 | F95: 090-9975-4706 | G95: 9099754706 | I95: (277-0005) 千葉県柏市柏1ー7ー1ー1811 | J95: 北恵仁司 | K95: 090-9975-4706 | L95: 千葉県柏市柏1ー7ー1ー1811 | M95: 277-0005 | N95: Vardag Splitpack 45 | O95: 1 | P95: 27500 | Q95: 2750 | R95: 000000001622 | S95: 23200302 | T95: 23200302525-620X | V95: Amazon Pay | W95: 37620 | X95: 550 | Z95: 0 | AA95: -2365 | AB95: 0 | AC95: 10 | AD95: 0 | AE95: 0 | AG95: 佐川急便 | AI95: 46203 | AK95: 20260630174337 | AL95: 518875580871 | AM95: 伝達メッセージ : | AO95: 伝達メッセージ :
A96: 46201 | B96: 203203 | C96: P186924015174616993 | D96: Amazon Pay [決済完了] | E96: 伊藤悠子 | F96: 090-2234-5627 | G96: 9022345627 | I96: (371-0015) 群馬県高崎市沖町486－467 | J96: 伊藤悠子 | K96: 090-2234-5627 | L96: 群馬県高崎市沖町486－467 | M96: 370-0086 | N96: Greenland Wax travel pack | O96: 1 | P96: 935 | Q96: 93 | R96: 000000000031 | S96: 79030 | T96: 79030X | V96: Amazon Pay | W96: 8635 | X96: 550 | Z96: 0 | AA96: 0 | AB96: 0 | AC96: 10 | AD96: 0 | AE96: 0 | AG96: 佐川急便 | AI96: 46203 | AK96: 20260630180618 | AL96: 518875581265 | AM96: 伝達メッセージ : | AO96: 伝達メッセージ :
A97: 46201 | B97: 203203 | C97: P186924015174616993 | D97: Amazon Pay [決済完了] | E97: 伊藤悠子 | F97: 090-2234-5627 | G97: 9022345627 | I97: (371-0015) 群馬県高崎市沖町486－467 | J97: 伊藤悠子 | K97: 090-2234-5627 | L97: 群馬県高崎市沖町486－467 | M97: 370-0086 | N97: Vardag Pocket Small | O97: 1 | P97: 7150 | Q97: 715 | R97: 000000001746 | S97: 23200338 | T97: 23200338662X | V97: Amazon Pay | W97: 8635 | X97: 550 | Z97: 0 | AA97: 0 | AB97: 0 | AC97: 10 | AD97: 0 | AE97: 0 | AG97: 佐川急便 | AI97: 46203 | AK97: 20260630180618 | AL97: 518875581265 | AM97: 伝達メッセージ : | AO97: 伝達メッセージ :
A98: 46201 | B98: 202305 | C98: P186923958708586217 | D98: Amazon Pay [決済完了] | E98: 福田弦 | F98: 090-7813-7343 | G98: 9078137343 | I98: (290-0026) 千葉県市原市諏訪1-7-15-202 | J98: 福田弦 | K98: 090-7813-7343 | L98: 千葉県市原市諏訪1-7-15-202 | M98: 290-0026 | N98: Raven 28 | O98: 1 | P98: 20900 | Q98: 2090 | R98: 000000001133 | S98: 23345 | T98: 23345050X | V98: Amazon Pay | W98: 21450 | X98: 550 | Z98: 0 | AA98: 0 | AB98: 0 | AC98: 10 | AD98: 0 | AE98: 0 | AG98: 佐川急便 | AI98: 46203 | AK98: 20260630174036 | AL98: 518875580823 | AM98: 伝達メッセージ : | AO98: 伝達メッセージ : | AP98: (6/30 info.) Amazon Pay 経由にて発送についてお問い合わせあり。
A99: 46201 | B99: 201922 | C99: P186923935381344941 | D99: PGクレジットカード [決済完了] | E99: 石井真 | F99: 080-3498-8963 | G99: 8034988963 | I99: (192-0363) 東京都八王子市別所1-54-3-111 | J99: 石井真 | K99: 080-3498-8963 | L99: 東京都八王子市別所1-54-3-111 | M99: 192-0363 | N99: 【Women’s】Abisko Sun-hoodie W | O99: 1 | P99: 14850 | Q99: 1485 | R99: 000000001132 | S99: 84108 | T99: 84108614S | V99: PGクレジットカード | W99: 11413 | X99: 550 | Z99: 0 | AA99: -1760 | AB99: 0 | AC99: 10 | AD99: 0 | AE99: 0 | AG99: 佐川急便 | AI99: 46203 | AK99: 20260630175534 | AL99: 518875581044 | AM99: 伝達メッセージ : | AO99: 伝達メッセージ :
A100: 46201 | B100: 201402 | C100: P186923901783402522 | D100: PayPay [決済完了] | E100: 西河愛美 | F100: 090-5326-3365 | G100: 9053263365 | I100: (343-0845) 埼玉県越谷市南越谷5-17-2-104 | J100: 西河愛美 | K100: 090-5326-3365 | L100: 埼玉県越谷市南越谷5-17-2-104 | M100: 343-0845 | N100: Kanken 16L (Sky Blue 501) | O100: 1 | P100: 14300 | Q100: 1430 | R100: 000000000872 | S100: 23510 | T100: 23510501X | V100: PayPay | W100: 14850 | X100: 550 | Z100: 0 | AA100: 0 | AB100: 0 | AC100: 10 | AD100: 0 | AE100: 0 | AG100: 佐川急便 | AI100: 46203 | AK100: 20260630173041 | AL100: 518875580683 | AM100: 伝達メッセージ : | AO100: 伝達メッセージ :
A101: 46201 | B101: 201358 | C101: P186923901342233727 | D101: PGクレジットカード [決済完了] | E101: 渡邉保子 | F101: 090-5616-7525 | G101: 9056167525 | I101: (410-0816) 静岡県沼津市住吉町2-27 | J101: 渡邉保子 | K101: 090-5616-7525 | L101: 静岡県沼津市住吉町2-27 | M101: 410-0816 | N101: Kanken 16L (Sky Blue 501) | O101: 1 | P101: 14300 | Q101: 1430 | R101: 000000000872 | S101: 23510 | T101: 23510501X | V101: PGクレジットカード | W101: 14850 | X101: 550 | Z101: 0 | AA101: 0 | AB101: 0 | AC101: 10 | AD101: 0 | AE101: 0 | AG101: 佐川急便 | AI101: 46203 | AK101: 20260630172705 | AL101: 518875580635 | AM101: 伝達メッセージ : | AO101: 伝達メッセージ :
A102: 46201 | B102: 193630 | C102: P186923665669225648 | D102: 代金引換 [未入金] | E102: 吉屋花鈴 | F102: 080-4558-9684 | G102: 8045589684 | I102: (750-0009) 山口県下関市上田中町8-18白雲台R21 307号 | J102: 吉屋花鈴 | K102: 080-4558-9684 | L102: 山口県下関市上田中町8-18白雲台R21 307号 | M102: 750-0009 | N102: Kanken 16L (Navy 560) | O102: 1 | P102: 14300 | Q102: 1430 | R102: 000000000882 | S102: 23510 | T102: 23510560X | V102: 代金引換 | W102: 15290 | X102: 550 | Z102: 440 | AA102: 0 | AB102: 0 | AC102: 10 | AD102: 0 | AE102: 0 | AG102: 佐川急便 | AI102: 46203 | AK102: 20260630174744 | AL102: 518875580930 | AM102: 伝達メッセージ : | AO102: 伝達メッセージ :
A103: 46201 | B103: 162719 | C103: P186922475397793893 | D103: PGクレジットカード [決済完了] | E103: 椎名聖 | F103: 090-2919-2726 | G103: 9029192726 | I103: (370-0332) 群馬県太田市新田中江田町824-5 | J103: 椎名聖 | K103: 090-2919-2726 | L103: 群馬県太田市新田中江田町824-5 | M103: 370-0332 | N103: Varmland Cap | O103: 1 | P103: 7370 | Q103: 737 | R103: 000000001486 | S103: 12100003 | T103: 12100003662L/XL | V103: PGクレジットカード | W103: 7920 | X103: 550 | Z103: 0 | AA103: 0 | AB103: 0 | AC103: 10 | AD103: 0 | AE103: 0 | AG103: 佐川急便 | AI103: 46203 | AK103: 20260630180238 | AL103: 518875581140 | AM103: 伝達メッセージ : | AO103: 伝達メッセージ : | AP103: メールエラーがあった模様。
A104: 46201 | B104: 143604 | C104: P186921775487494648 | D104: Amazon Pay [決済完了] | E104: 西元寺慈子 | F104: 099-269-6789 | G104: 992696789 | I104: (891-0113) 鹿児島県鹿児島市東谷山5-14-3 | J104: 西元寺慈子 | K104: 099-269-6789 | L104: 鹿児島県鹿児島市東谷山5-14-3 | M104: 891-0113 | N104: Kanken Laptop 15 | O104: 1 | P104: 19800 | Q104: 1980 | R104: 000000001143 | S104: 23524 | T104: 23524457X | V104: Amazon Pay | W104: 20350 | X104: 550 | Z104: 0 | AA104: 0 | AB104: 0 | AC104: 10 | AD104: 0 | AE104: 0 | AG104: 佐川急便 | AI104: 46203 | AK104: 20260630173830 | AL104: 518875580790 | AM104: 伝達メッセージ : | AO104: 伝達メッセージ :
A105: 46201 | B105: 141925 | C105: P186921670742585872 | D105: PayPay [決済完了] | E105: 吉留淳子 | F105: 080-2707-5559 | G105: 8027075559 | I105: (813-0031) 福岡県福岡市東区八田3-23-42 | J105: 吉留淳子 | K105: 080-2707-5559 | L105: 福岡県福岡市東区八田3-23-42 | M105: 813-0031 | N105: Kanken Key Ring | O105: 1 | P105: 1650 | Q105: 165 | R105: 000000000290 | S105: 23785 | T105: 23785199X | V105: PayPay | W105: 17600 | X105: 550 | Z105: 0 | AA105: 0 | AB105: 0 | AC105: 10 | AD105: 0 | AE105: 0 | AG105: 佐川急便 | AI105: 46203 | AK105: 20260630174115 | AL105: 518875580834 | AM105: 伝達メッセージ : | AO105: 伝達メッセージ :
A106: 46201 | B106: 141925 | C106: P186921670742585872 | D106: PayPay [決済完了] | E106: 吉留淳子 | F106: 080-2707-5559 | G106: 8027075559 | I106: (813-0031) 福岡県福岡市東区八田3-23-42 | J106: 吉留淳子 | K106: 080-2707-5559 | L106: 福岡県福岡市東区八田3-23-42 | M106: 813-0031 | N106: Skule 28 | O106: 1 | P106: 15400 | Q106: 1540 | R106: 000000001137 | S106: 23346 | T106: 23346550X | V106: PayPay | W106: 17600 | X106: 550 | Z106: 0 | AA106: 0 | AB106: 0 | AC106: 10 | AD106: 0 | AE106: 0 | AG106: 佐川急便 | AI106: 46203 | AK106: 20260630174115 | AL106: 518875580834 | AM106: 伝達メッセージ : | AO106: 伝達メッセージ :
A107: 46201 | B107: 134024 | C107: P186921425228111561 | D107: Amazon Pay [決済完了] | E107: 樫本ともこ | F107: 080-7407-9549 | G107: 8074079549 | I107: (225-0002) 神奈川県横浜市青葉区美しが丘2-28-4ディアナコート美しが丘403号 | J107: 樫本ともこ | K107: 080-7407-9549 | L107: 神奈川県横浜市青葉区美しが丘2-28-4ディアナコート美しが丘403号 | M107: 225-0002 | N107: Kanken 16L (Blackberry 424) | O107: 1 | P107: 14300 | Q107: 1430 | R107: 000000001481 | S107: 23510 | T107: 23510424X | V107: Amazon Pay | W107: 14850 | X107: 550 | Z107: 0 | AA107: 0 | AB107: 0 | AC107: 10 | AD107: 0 | AE107: 0 | AG107: 佐川急便 | AI107: 46203 | AK107: 20260630170614 | AL107: 518875580425 | AM107: 伝達メッセージ : | AO107: 伝達メッセージ :
A108: 46201 | B108: 132216 | C108: P186921311213001341 | D108: PayPay [決済完了] | E108: NABILLASHAFARA | F108: 090-3036-2802 | G108: 9030362802 | I108: (241-0826) 神奈川県横浜市旭区東希望が丘97-3アイシマ希望ヶ丘寮308 | J108: NABILLASHAFARA | K108: 090-3036-2802 | L108: 神奈川県横浜市旭区東希望が丘97-3アイシマ希望ヶ丘寮308 | M108: 241-0826 | N108: Kanken Laptop 15 | O108: 1 | P108: 19800 | Q108: 1980 | R108: 000000001143 | S108: 23524 | T108: 23524550X | V108: PayPay | W108: 20350 | X108: 550 | Z108: 0 | AA108: 0 | AB108: 0 | AC108: 10 | AD108: 0 | AE108: 0 | AG108: 佐川急便 | AI108: 46203 | AK108: 20260630173953 | AL108: 518875580812 | AM108: 伝達メッセージ : | AO108: 伝達メッセージ :
A109: 46201 | B109: 131608 | C109: P186921272537421572 | D109: Amazon Pay [決済完了] | E109: 谷亀智代 | F109: 080-5033-3486 | G109: 8050333486 | I109: (252-0335) 神奈川県相模原市南区下溝605-13 シルキーC 105 | J109: 谷亀智代 | K109: 080-5033-3486 | L109: 神奈川県相模原市南区下溝605-13 シルキーC 105 | M109: 252-0335 | N109: Kanken 16L (Ochre 160) | O109: 1 | P109: 14300 | Q109: 1430 | R109: 000000000895 | S109: 23510 | T109: 23510160X | V109: Amazon Pay | W109: 14850 | X109: 550 | Z109: 0 | AA109: 0 | AB109: 0 | AC109: 10 | AD109: 0 | AE109: 0 | AG109: 佐川急便 | AI109: 46203 | AK109: 20260630173337 | AL109: 518875580720 | AM109: 伝達メッセージ : | AO109: 伝達メッセージ :
A110: 46201 | B110: 125312 | C110: P186921128322015353 | D110: PayPay [決済完了] | E110: 市東真菜 | F110: 090-6309-9979 | G110: 9063099979 | I110: (264-0006) 千葉県千葉市若葉区小倉台3-16-1 | J110: 市東真菜 | K110: 090-6309-9979 | L110: 千葉県千葉市若葉区小倉台3-16-1 | M110: 264-0006 | N110: Kanken 16L (Super grey 046) | O110: 1 | P110: 14300 | Q110: 1430 | R110: 000000000852 | S110: 23510 | T110: 23510046X | V110: PayPay | W110: 14850 | X110: 550 | Z110: 0 | AA110: 0 | AB110: 0 | AC110: 10 | AD110: 0 | AE110: 0 | AG110: 佐川急便 | AI110: 46203 | AK110: 20260630171123 | AL110: 518875580495 | AM110: 伝達メッセージ : | AO110: 伝達メッセージ :
A111: 46201 | B111: 124223 | C111: P186921060198054623 | D111: Amazon Pay [決済完了] | E111: 黒住武秀 | F111: 090-4804-7383 | G111: 9048047383 | I111: (714-0062) 岡山県笠岡市茂平379-1 フェリーチェB 203 | J111: 黒住武秀 | K111: 090-4804-7383 | L111: 岡山県笠岡市茂平379-1 フェリーチェB 203 | M111: 714-0062 | N111: 【ミニ】Kanken Mini (Sky Blue 501) | O111: 1 | P111: 13200 | Q111: 1320 | R111: 000000000973 | S111: 23561 | T111: 23561501X | V111: Amazon Pay | W111: 13750 | X111: 550 | Z111: 0 | AA111: 0 | AB111: 0 | AC111: 10 | AD111: 0 | AE111: 0 | AG111: 佐川急便 | AI111: 46203 | AK111: 20260630172246 | AL111: 518875580580 | AM111: 伝達メッセージ : | AO111: 伝達メッセージ :
A112: 46201 | B112: 123724 | C112: P186921028846901561 | D112: PayPay [決済完了] | E112: 長野珠妃 | F112: 080-1048-3820 | G112: 8010483820 | I112: (944-0047) 新潟県妙高市白山町4-7-27 | J112: 長野珠妃 | K112: 080-1048-3820 | L112: 新潟県妙高市白山町4-7-27 | M112: 944-0047 | N112: Kanken 16L (Royal Blue 540) | O112: 1 | P112: 14300 | Q112: 1430 | R112: 000000000880 | S112: 23510 | T112: 23510540X | V112: PayPay | W112: 14850 | X112: 550 | Z112: 0 | AA112: 0 | AB112: 0 | AC112: 10 | AD112: 0 | AE112: 0 | AG112: 佐川急便 | AI112: 46203 | AK112: 20260630171249 | AL112: 518875580506 | AM112: 伝達メッセージ : | AO112: 伝達メッセージ :
...

Sheet EC_PIVOT
A1: TTL: | B1: =SUMIF(A:A,"総計",B:B) -> 284
A2: 行ラベル | B2: 合計 / 個数
A3: 23510031X | B3: 6
A4: 23510046X | B4: 4
A5: 23510160X | B5: 2
A6: 23510228X | B6: 1
A7: 23510312X | B7: 12
A8: 23510424X | B8: 4
A9: 23510457X | B9: 5
A10: 23510501-115X | B10: 5
A11: 23510501X | B11: 15
A12: 23510540X | B12: 6
A13: 23510550X | B13: 2
A14: 23510560X | B14: 3
A15: (空白)
A16: 23510126X | B16: 3
A17: 23510302X | B17: 19
A18: 23200408570-260X | B18: 1
A19: 23510600X | B19: 8
A20: 23227543X | B20: 1
A21: 23561501-115X | B21: 1
A22: 23513907X | B22: 1
A23: 23561302X | B23: 1
A24: 23323633X | B24: 1
A25: 23505228X | B25: 2
A26: 23510118X | B26: 2
A27: 23346550X | B27: 2
... A139: 23200300354-228X | B139: 1
A140: 8710503036 | B140: 1
A141: 23796312X | B141: 1
A142: 23508021X | B142: 1
A143: 23200251021X | B143: 1
A144: 23796550X | B144: 1
A145: 23510620X | B145: 1
A146: 23796560X | B146: 1
A147: 23796620X | B147: 1
A148: 23524326X | B148: 1
A149: 12600216555L | B149: 1
A150: 23711350X | B150: 1
A151: 24221030X | B151: 1
A152: 23710501X | B152: 1
... A164: 総計 | B164: 284

Sheet 計算式2026
C1: =SUBTOTAL(9,C4:C3000) -> 21102 | D1: =SUBTOTAL(9,D4:D3000) -> 4932 | E1: =SUBTOTAL(9,E4:E3000) -> 0 | F1: =SUBTOTAL(9,F4:F3000) -> 0 | G1: =SUBTOTAL(9,G4:G3000) -> 0 | H1: =SUBTOTAL(9,H4:H3000) -> 0 | I1: =SUBTOTAL(9,I4:I3000) -> 0 | J1: =SUBTOTAL(9,J4:J3000) -> 0 | K1: =SUBTOTAL(9,K4:K3000) -> 0 | R1: =SUBTOTAL(9,R4:R3000) -> 1557 | S1: =SUBTOTAL(9,S4:S3000) -> 2778 | T1: =SUBTOTAL(9,T4:T3000) -> 1572 | U1: =SUBTOTAL(9,U4:U3000) -> 1313 | V1: =SUBTOTAL(9,V4:V3000) -> 2817 | W1: =SUBTOTAL(9,W4:W3000) -> 573 | X1: =SUBTOTAL(9,X4:X3000) -> 2745 | AF1: =MATCH(AF3,pivot!4:4,0) -> 2 | AI1: =MATCH(AI3,pivot!4:4,0) -> 3 | AJ1: =MATCH(AJ3,pivot!4:4,0) -> 4 | AK1: =MATCH(AK3,pivot!4:4,0) -> 5 | AL1: =MATCH(AL3,pivot!4:4,0) -> 6 | AM1: =MATCH(AM3,pivot!4:4,0) -> 8 | AN1: =MATCH(AN3,pivot!4:4,0) -> 9 | AO1: =MATCH(AO3,pivot!4:4,0) -> #N/A | AP1: =MATCH(AP3,pivot!4:4,0) -> 7 | AQ1: =MATCH(AQ3,pivot!4:4,0) -> 10
C2: 確保 | R2: 在庫 | AE2: RETAIL
A3: 商品コード | B3: 商品名 | C3: NWA | D3: RETAIL確保 | E3: ZOZO | F3: 名古屋 | G3: 丸井web | H3: YSEC | I3: TOKYO | J3: ルクア大阪 | K3: ヒュッテ | L3: 京王新宿 | M3: 6142 | N3: 玉川高島屋 | O3: NODE | P3: 大丸心斎橋 | Q3: NARITA | R3: ZOZO | S3: 名古屋 | T3: 丸井web | U3: YSEC | V3: TOKYO | W3: ルクア大阪 | X3: ヒュッテ | Y3: 京王新宿 | Z3: 6142 | AA3: 玉川高島屋 | AB3: NODE | AC3: 大丸心斎橋 | AD3: NARITA | AE3: ZOZO | AF3: 名古屋 | AG3: 丸井web | AH3: YSEC | AI3: TOKYO | AJ3: ルクア大阪 | AK3: ヒュッテ | AL3: 京王新宿 | AM3: 6142 | AN3: 玉川高島屋 | AO3: NODE | AP3: 大丸心斎橋 | AQ3: NARITA | AR3: ZOZO | AS3: 名古屋 | AT3: 丸井web | AU3: YSEC | AV3: TOKYO | AW3: ルクア大阪 | AX3: ヒュッテ | AY3: 京王新宿 | AZ3: 6142 | BA3: 玉川高島屋 | BB3: 越一 | BC3: 大丸心斎橋 | BD3: NARITA | BE3: マイナス | BF3: R | BG3: F
A4: 02357645X | B4: Kanken Rainbow Mini | C4: 0 | D4: 0 | E4: 0 | F4: 0 | G4: 0 | H4: 0 | I4: 0 | J4: 0 | K4: 0 | R4: 0 | S4: 0 | T4: 1 | U4: 0 | V4: 0 | W4: 0 | X4: 0 | AE4: =IFERROR(VLOOKUP(A4,ZOZOOIOI!L:M,2,FALSE),0) -> 0 | AF4: =IFERROR(VLOOKUP($A4,pivot!$A:$K,計算式2026!AF$1,FALSE),0) -> 0 | AG4: =IFERROR(VLOOKUP(A4,ZOZOOIOI!Z:AA,2,FALSE),0) -> 0 | AH4: =IFERROR(VLOOKUP(A4,EC_PIVOT!A:B,2,FALSE),0) -> 0 | AI4: =IFERROR(VLOOKUP($A4,pivot!$A:$K,計算式2026!AI$1,FALSE),0) -> 0 | AJ4: =IFERROR(VLOOKUP($A4,pivot!$A:$K,計算式2026!AJ$1,FALSE),0) -> 0 | AK4: =IFERROR(VLOOKUP($A4,pivot!$A:$K,計算式2026!AK$1,FALSE),0) -> 0 | AL4: =IFERROR(VLOOKUP($A4,pivot!$A:$K,計算式2026!AL$1,FALSE),0) -> 0 | AM4: =IFERROR(VLOOKUP($A4,pivot!$A:$K,計算式2026!AM$1,FALSE),0) -> 0 | AN4: =IFERROR(VLOOKUP($A4,pivot!$A:$K,計算式2026!AN$1,FALSE),0) -> 0 | AO4: =IFERROR(VLOOKUP($A4,pivot!$A:$K,計算式2026!AO$1,FALSE),0) -> 0 | AP4: =IFERROR(VLOOKUP($A4,pivot!$A:$K,計算式2026!AP$1,FALSE),0) -> 0 | AQ4: =IFERROR(VLOOKUP($A4,pivot!$A:$K,計算式2026!AQ$1,FALSE),0) -> 0 | AR4: =E4-AE4 -> 0 | AS4: =F4-AF4 -> 0 | AT4: =G4-AG4 -> 0 | AU4: =H4-AH4 -> 0 | AV4: =I4-AI4 -> 0 | AW4: =J4-AJ4 -> 0 | AX4: =K4-AK4 -> 0 | AY4: =L4-AL4 -> 0 | ... BD4: =Q4-AQ4 -> 0 | BE4: =SUMIF(AR4:BD4,"<0",AR4:BD4) -> 0 | BF4: =IF(BE4<0,D4+BE4,D4) -> 0 | BG4: =IF(BF4<0,C4+BF4,C4) -> 0
A5: 08164205AS | B5: Ovik Organic Printed T-Shirts W | C5: 0 | D5: 0 | E5: 0 | F5: 0 | G5: 0 | H5: 0 | I5: 0 | J5: 0 | K5: 0 | R5: 0 | S5: 1 | T5: 0 | U5: 0 | V5: 0 | W5: 0 | X5: 0 | AE5: =IFERROR(VLOOKUP($A5,pivot!$A:$G,計算式2026!AE$1,FALSE),0) -> 0 | AF5: =IFERROR(VLOOKUP($A5,pivot!$A:$I,計算式2026!AF$1,FALSE),0) -> 0 | AI5: =IFERROR(VLOOKUP($A5,pivot!$A:$I,計算式2026!AI$1,FALSE),0) -> 0 | AJ5: =IFERROR(VLOOKUP($A5,pivot!$A:$I,計算式2026!AJ$1,FALSE),0) -> 0 | AK5: =IFERROR(VLOOKUP($A5,pivot!$A:$I,計算式2026!AK$1,FALSE),0) -> 0 | AL5: =IFERROR(VLOOKUP($A5,pivot!$A:$I,計算式2026!AL$1,FALSE),0) -> 0
A6: 08164509AM | B6: Ovik Organic Printed T-Shirts W | C6: 0 | D6: 0 | E6: 0 | F6: 0 | G6: 0 | H6: 0 | I6: 0 | J6: 0 | K6: 0 | R6: 0 | S6: 1 | T6: 0 | U6: 0 | V6: 1 | W6: 0 | X6: 0 | AE6: =IFERROR(VLOOKUP($A6,pivot!$A:$G,計算式2026!AE$1,FALSE),0) -> 0 | AF6: =IFERROR(VLOOKUP($A6,pivot!$A:$I,計算式2026!AF$1,FALSE),0) -> 0 | AI6: =IFERROR(VLOOKUP($A6,pivot!$A:$I,計算式2026!AI$1,FALSE),0) -> 0 | AJ6: =IFERROR(VLOOKUP($A6,pivot!$A:$I,計算式2026!AJ$1,FALSE),0) -> 0 | AK6: =IFERROR(VLOOKUP($A6,pivot!$A:$I,計算式2026!AK$1,FALSE),0) -> 0 | AL6: =IFERROR(VLOOKUP($A6,pivot!$A:$I,計算式2026!AL$1,FALSE),0) -> 0
A7: 08164509AS | B7: Ovik Organic Printed T-Shirts W | C7: 0 | D7: 0 | E7: 0 | F7: 0 | G7: 0 | H7: 0 | I7: 0 | J7: 0 | K7: 0 | R7: 0 | S7: 0 | T7: 0 | U7: 0 | V7: 0 | W7: 0 | X7: 0 | AE7: =IFERROR(VLOOKUP($A7,pivot!$A:$G,計算式2026!AE$1,FALSE),0) -> 0 | AF7: =IFERROR(VLOOKUP($A7,pivot!$A:$I,計算式2026!AF$1,FALSE),0) -> 0 | AI7: =IFERROR(VLOOKUP($A7,pivot!$A:$I,計算式2026!AI$1,FALSE),0) -> 0 | AJ7: =IFERROR(VLOOKUP($A7,pivot!$A:$I,計算式2026!AJ$1,FALSE),0) -> 0 | AK7: =IFERROR(VLOOKUP($A7,pivot!$A:$I,計算式2026!AK$1,FALSE),0) -> 0 | AL7: =IFERROR(VLOOKUP($A7,pivot!$A:$I,計算式2026!AL$1,FALSE),0) -> 0
A8: 08164509AXS | B8: Ovik Organic Printed T-Shirts W | C8: 0 | D8: 0 | E8: 0 | F8: 0 | G8: 0 | H8: 0 | I8: 0 | J8: 0 | K8: 0 | R8: 0 | S8: 1 | T8: 0 | U8: 0 | V8: 0 | W8: 0 | X8: 0 | AE8: =IFERROR(VLOOKUP($A8,pivot!$A:$G,計算式2026!AE$1,FALSE),0) -> 0 | AF8: =IFERROR(VLOOKUP($A8,pivot!$A:$I,計算式2026!AF$1,FALSE),0) -> 0 | AI8: =IFERROR(VLOOKUP($A8,pivot!$A:$I,計算式2026!AI$1,FALSE),0) -> 0 | AJ8: =IFERROR(VLOOKUP($A8,pivot!$A:$I,計算式2026!AJ$1,FALSE),0) -> 0 | AK8: =IFERROR(VLOOKUP($A8,pivot!$A:$I,計算式2026!AK$1,FALSE),0) -> 0 | AL8: =IFERROR(VLOOKUP($A8,pivot!$A:$I,計算式2026!AL$1,FALSE),0) -> 0
A9: 08180550A42 | B9: Abisko H-loft Trekking Trousers | C9: 1 | D9: 0 | E9: 0 | F9: 0 | G9: 0 | H9: 0 | I9: 0 | J9: 0 | K9: 0 | R9: 0 | S9: 0 | T9: 0 | U9: 0 | V9: 0 | W9: 0 | X9: 0 | AE9: =IFERROR(VLOOKUP($A9,pivot!$A:$G,計算式2026!AE$1,FALSE),0) -> 0 | AF9: =IFERROR(VLOOKUP($A9,pivot!$A:$I,計算式2026!AF$1,FALSE),0) -> 0 | AI9: =IFERROR(VLOOKUP($A9,pivot!$A:$I,計算式2026!AI$1,FALSE),0) -> 0 | AJ9: =IFERROR(VLOOKUP($A9,pivot!$A:$I,計算式2026!AJ$1,FALSE),0) -> 0 | AK9: =IFERROR(VLOOKUP($A9,pivot!$A:$I,計算式2026!AK$1,FALSE),0) -> 0 | AL9: =IFERROR(VLOOKUP($A9,pivot!$A:$I,計算式2026!AL$1,FALSE),0) -> 0
A10: 08180550A44 | B10: Abisko H-loft Trekking Trousers | C10: 1 | D10: 0 | E10: 0 | F10: 0 | G10: 0 | H10: 0 | I10: 0 | J10: 0 | K10: 0 | R10: 0 | S10: 0 | T10: 0 | U10: 0 | V10: 0 | W10: 0 | X10: 0 | AE10: =IFERROR(VLOOKUP($A10,pivot!$A:$G,計算式2026!AE$1,FALSE),0) -> 0 | AF10: =IFERROR(VLOOKUP($A10,pivot!$A:$I,計算式2026!AF$1,FALSE),0) -> 0 | AI10: =IFERROR(VLOOKUP($A10,pivot!$A:$I,計算式2026!AI$1,FALSE),0) -> 0 | AJ10: =IFERROR(VLOOKUP($A10,pivot!$A:$I,計算式2026!AJ$1,FALSE),0) -> 0 | AK10: =IFERROR(VLOOKUP($A10,pivot!$A:$I,計算式2026!AK$1,FALSE),0) -> 0 | AL10: =IFERROR(VLOOKUP($A10,pivot!$A:$I,計算式2026!AL$1,FALSE),0) -> 0
A11: 08186550A32 | B11: Barents Pro Stretch Trousers W | C11: 3 | D11: 0 | E11: 0 | F11: 0 | G11: 0 | H11: 0 | I11: 0 | J11: 0 | K11: 0 | R11: 0 | S11: 0 | T11: 0 | U11: 0 | V11: 0 | W11: 0 | X11: 0 | AE11: =IFERROR(VLOOKUP($A11,pivot!$A:$G,計算式2026!AE$1,FALSE),0) -> 0 | AF11: =IFERROR(VLOOKUP($A11,pivot!$A:$I,計算式2026!AF$1,FALSE),0) -> 0 | AI11: =IFERROR(VLOOKUP($A11,pivot!$A:$I,計算式2026!AI$1,FALSE),0) -> 0 | AJ11: =IFERROR(VLOOKUP($A11,pivot!$A:$I,計算式2026!AJ$1,FALSE),0) -> 0 | AK11: =IFERROR(VLOOKUP($A11,pivot!$A:$I,計算式2026!AK$1,FALSE),0) -> 0 | AL11: =IFERROR(VLOOKUP($A11,pivot!$A:$I,計算式2026!AL$1,FALSE),0) -> 0
A12: 08186550A34 | B12: Barents Pro Stretch Trousers W | C12: 1 | D12: 0 | E12: 0 | F12: 0 | G12: 0 | H12: 0 | I12: 0 | J12: 0 | K12: 0 | R12: 0 | S12: 0 | T12: 0 | U12: 0 | V12: 0 | W12: 0 | X12: 0 | AE12: =IFERROR(VLOOKUP($A12,pivot!$A:$G,計算式2026!AE$1,FALSE),0) -> 0 | AF12: =IFERROR(VLOOKUP($A12,pivot!$A:$I,計算式2026!AF$1,FALSE),0) -> 0 | AI12: =IFERROR(VLOOKUP($A12,pivot!$A:$I,計算式2026!AI$1,FALSE),0) -> 0 | AJ12: =IFERROR(VLOOKUP($A12,pivot!$A:$I,計算式2026!AJ$1,FALSE),0) -> 0 | AK12: =IFERROR(VLOOKUP($A12,pivot!$A:$I,計算式2026!AK$1,FALSE),0) -> 0 | AL12: =IFERROR(VLOOKUP($A12,pivot!$A:$I,計算式2026!AL$1,FALSE),0) -> 0
A13: 08186550A36 | B13: Barents Pro Stretch Trousers W | C13: 1 | D13: 0 | E13: 0 | F13: 0 | G13: 0 | H13: 0 | I13: 0 | J13: 0 | K13: 0 | R13: 0 | S13: 0 | T13: 0 | U13: 0 | V13: 0 | W13: 0 | X13: 0 | AE13: =IFERROR(VLOOKUP($A13,pivot!$A:$G,計算式2026!AE$1,FALSE),0) -> 0 | AF13: =IFERROR(VLOOKUP($A13,pivot!$A:$I,計算式2026!AF$1,FALSE),0) -> 0 | AI13: =IFERROR(VLOOKUP($A13,pivot!$A:$I,計算式2026!AI$1,FALSE),0) -> 0 | AJ13: =IFERROR(VLOOKUP($A13,pivot!$A:$I,計算式2026!AJ$1,FALSE),0) -> 0 | AK13: =IFERROR(VLOOKUP($A13,pivot!$A:$I,計算式2026!AK$1,FALSE),0) -> 0 | AL13: =IFERROR(VLOOKUP($A13,pivot!$A:$I,計算式2026!AL$1,FALSE),0) -> 0
A14: 21758160X | B14: Rucksack No.21 Mini | C14: 36 | D14: 0 | E14: 0 | F14: 0 | G14: 0 | H14: 0 | I14: 0 | J14: 0 | K14: 0 | R14: 0 | S14: 0 | T14: 1 | U14: 0 | V14: 0 | W14: 1 | X14: 4 | AE14: =IFERROR(VLOOKUP($A14,pivot!$A:$G,計算式2026!AE$1,FALSE),0) -> 0 | AF14: =IFERROR(VLOOKUP($A14,pivot!$A:$I,計算式2026!AF$1,FALSE),0) -> 0 | AI14: =IFERROR(VLOOKUP($A14,pivot!$A:$I,計算式2026!AI$1,FALSE),0) -> 0 | AJ14: =IFERROR(VLOOKUP($A14,pivot!$A:$I,計算式2026!AJ$1,FALSE),0) -> 0 | AK14: =IFERROR(VLOOKUP($A14,pivot!$A:$I,計算式2026!AK$1,FALSE),0) -> 0 | AL14: =IFERROR(VLOOKUP($A14,pivot!$A:$I,計算式2026!AL$1,FALSE),0) -> 0
A15: 21758320X | B15: Rucksack No.21 Mini | C15: 22 | D15: 0 | E15: 0 | F15: 0 | G15: 0 | H15: 0 | I15: 0 | J15: 0 | K15: 0 | R15: 0 | S15: 0 | T15: 1 | U15: 0 | V15: 0 | W15: 1 | X15: 3 | AE15: =IFERROR(VLOOKUP($A15,pivot!$A:$G,計算式2026!AE$1,FALSE),0) -> 0 | AF15: =IFERROR(VLOOKUP($A15,pivot!$A:$I,計算式2026!AF$1,FALSE),0) -> 0 | AI15: =IFERROR(VLOOKUP($A15,pivot!$A:$I,計算式2026!AI$1,FALSE),0) -> 0 | AJ15: =IFERROR(VLOOKUP($A15,pivot!$A:$I,計算式2026!AJ$1,FALSE),0) -> 0 | AK15: =IFERROR(VLOOKUP($A15,pivot!$A:$I,計算式2026!AK$1,FALSE),0) -> 0 | AL15: =IFERROR(VLOOKUP($A15,pivot!$A:$I,計算式2026!AL$1,FALSE),0) -> 0
A16: 21758519X | B16: Rucksack No.21 Mini | C16: 9 | D16: 0 | E16: 0 | F16: 0 | G16: 0 | H16: 0 | I16: 0 | J16: 0 | K16: 0 | R16: 0 | S16: 0 | T16: 1 | U16: 0 | V16: 0 | W16: 1 | X16: 3 | AE16: =IFERROR(VLOOKUP($A16,pivot!$A:$G,計算式2026!AE$1,FALSE),0) -> 0 | AF16: =IFERROR(VLOOKUP($A16,pivot!$A:$I,計算式2026!AF$1,FALSE),0) -> 0 | AI16: =IFERROR(VLOOKUP($A16,pivot!$A:$I,計算式2026!AI$1,FALSE),0) -> 0 | AJ16: =IFERROR(VLOOKUP($A16,pivot!$A:$I,計算式2026!AJ$1,FALSE),0) -> 0 | AK16: =IFERROR(VLOOKUP($A16,pivot!$A:$I,計算式2026!AK$1,FALSE),0) -> 0 | AL16: =IFERROR(VLOOKUP($A16,pivot!$A:$I,計算式2026!AL$1,FALSE),0) -> 0
... A967: 77279335M | B967: Singi Trekking Cap | C967: 1 | D967: 0 | E967: 0 | F967: 0 | G967: 0 | H967: 0 | I967: 0 | J967: 0 | K967: 0 | R967: 0 | S967: 0 | T967: 0 | U967: 0 | V967: 0 | W967: 0 | X967: 0 | AE967: =IFERROR(VLOOKUP($A967,pivot!$A:$G,計算式2026!AE$1,FALSE),0) -> 0 | AF967: =IFERROR(VLOOKUP($A967,pivot!$A:$I,計算式2026!AF$1,FALSE),0) -> 0 | AI967: =IFERROR(VLOOKUP($A967,pivot!$A:$I,計算式2026!AI$1,FALSE),0) -> 0 | AJ967: =IFERROR(VLOOKUP($A967,pivot!$A:$I,計算式2026!AJ$1,FALSE),0) -> 0 | AK967: =IFERROR(VLOOKUP($A967,pivot!$A:$I,計算式2026!AK$1,FALSE),0) -> 0 | AL967: =IFERROR(VLOOKUP($A967,pivot!$A:$I,計算式2026!AL$1,FALSE),0) -> 0
A968: 77280249110 | B968: Singi Belt 2.5cm | C968: 0 | D968: 0 | E968: 0 | F968: 0 | G968: 0 | H968: 0 | I968: 0 | J968: 0 | K968: 0 | R968: 0 | S968: 0 | T968: 0 | U968: 0 | V968: 1 | W968: 0 | X968: 1 | AE968: =IFERROR(VLOOKUP($A968,pivot!$A:$G,計算式2026!AE$1,FALSE),0) -> 0 | AF968: =IFERROR(VLOOKUP($A968,pivot!$A:$I,計算式2026!AF$1,FALSE),0) -> 0 | AI968: =IFERROR(VLOOKUP($A968,pivot!$A:$I,計算式2026!AI$1,FALSE),0) -> 0 | AJ968: =IFERROR(VLOOKUP($A968,pivot!$A:$I,計算式2026!AJ$1,FALSE),0) -> 0 | AK968: =IFERROR(VLOOKUP($A968,pivot!$A:$I,計算式2026!AK$1,FALSE),0) -> 0 | AL968: =IFERROR(VLOOKUP($A968,pivot!$A:$I,計算式2026!AL$1,FALSE),0) -> 0
A969: 7728024995 | B969: Singi Belt 2.5cm | C969: 1 | D969: 0 | E969: 0 | F969: 0 | G969: 0 | H969: 0 | I969: 0 | J969: 0 | K969: 0 | R969: 0 | S969: 0 | T969: 1 | U969: 0 | V969: 0 | W969: 1 | X969: 1 | AE969: =IFERROR(VLOOKUP($A969,pivot!$A:$G,計算式2026!AE$1,FALSE),0) -> 0 | AF969: =IFERROR(VLOOKUP($A969,pivot!$A:$I,計算式2026!AF$1,FALSE),0) -> 0 | AI969: =IFERROR(VLOOKUP($A969,pivot!$A:$I,計算式2026!AI$1,FALSE),0) -> 0 | AJ969: =IFERROR(VLOOKUP($A969,pivot!$A:$I,計算式2026!AJ$1,FALSE),0) -> 0 | AK969: =IFERROR(VLOOKUP($A969,pivot!$A:$I,計算式2026!AK$1,FALSE),0) -> 0 | AL969: =IFERROR(VLOOKUP($A969,pivot!$A:$I,計算式2026!AL$1,FALSE),0) -> 0
A970: 77291555X | B970: Singi Balaclava Cap | C970: 5 | D970: 0 | E970: 0 | F970: 0 | G970: 0 | H970: 0 | I970: 0 | J970: 0 | K970: 0 | R970: 0 | S970: 0 | T970: 0 | U970: 0 | V970: 0 | W970: 0 | X970: 1 | AE970: =IFERROR(VLOOKUP($A970,pivot!$A:$G,計算式2026!AE$1,FALSE),0) -> 0 | AF970: =IFERROR(VLOOKUP($A970,pivot!$A:$I,計算式2026!AF$1,FALSE),0) -> 0 | AI970: =IFERROR(VLOOKUP($A970,pivot!$A:$I,計算式2026!AI$1,FALSE),0) -> 0 | AJ970: =IFERROR(VLOOKUP($A970,pivot!$A:$I,計算式2026!AJ$1,FALSE),0) -> 0 | AK970: =IFERROR(VLOOKUP($A970,pivot!$A:$I,計算式2026!AK$1,FALSE),0) -> 0 | AL970: =IFERROR(VLOOKUP($A970,pivot!$A:$I,計算式2026!AL$1,FALSE),0) -> 0
A971: 77291633X | B971: Singi Balaclava Cap | C971: 0 | D971: 0 | E971: 0 | F971: 0 | G971: 0 | H971: 0 | I971: 0 | J971: 0 | K971: 0 | R971: 0 | S971: 0 | T971: 0 | U971: 0 | V971: 0 | W971: 0 | X971: 1 | AE971: =IFERROR(VLOOKUP($A971,pivot!$A:$G,計算式2026!AE$1,FALSE),0) -> 0 | AF971: =IFERROR(VLOOKUP($A971,pivot!$A:$I,計算式2026!AF$1,FALSE),0) -> 0 | AI971: =IFERROR(VLOOKUP($A971,pivot!$A:$I,計算式2026!AI$1,FALSE),0) -> 0 | AJ971: =IFERROR(VLOOKUP($A971,pivot!$A:$I,計算式2026!AJ$1,FALSE),0) -> 0 | AK971: =IFERROR(VLOOKUP($A971,pivot!$A:$I,計算式2026!AK$1,FALSE),0) -> 0 | AL971: =IFERROR(VLOOKUP($A971,pivot!$A:$I,計算式2026!AL$1,FALSE),0) -> 0
A972: 77294030L | B972: Singi Winter Cap | C972: 0 | D972: 0 | E972: 0 | F972: 0 | G972: 0 | H972: 0 | I972: 0 | J972: 0 | K972: 0 | R972: 0 | S972: 0 | T972: 1 | U972: 0 | V972: 0 | W972: 2 | X972: 2 | AE972: =IFERROR(VLOOKUP($A972,pivot!$A:$G,計算式2026!AE$1,FALSE),0) -> 0 | AF972: =IFERROR(VLOOKUP($A972,pivot!$A:$I,計算式2026!AF$1,FALSE),0) -> 0 | AI972: =IFERROR(VLOOKUP($A972,pivot!$A:$I,計算式2026!AI$1,FALSE),0) -> 0 | AJ972: =IFERROR(VLOOKUP($A972,pivot!$A:$I,計算式2026!AJ$1,FALSE),0) -> 0 | AK972: =IFERROR(VLOOKUP($A972,pivot!$A:$I,計算式2026!AK$1,FALSE),0) -> 0 | AL972: =IFERROR(VLOOKUP($A972,pivot!$A:$I,計算式2026!AL$1,FALSE),0) -> 0
A973: 77294030M | B973: Singi Winter Cap | C973: 0 | D973: 0 | E973: 0 | F973: 0 | G973: 0 | H973: 0 | I973: 0 | J973: 0 | K973: 0 | R973: 0 | S973: 0 | T973: 0 | U973: 0 | V973: 0 | W973: 0 | X973: 2 | AE973: =IFERROR(VLOOKUP($A973,pivot!$A:$G,計算式2026!AE$1,FALSE),0) -> 0 | AF973: =IFERROR(VLOOKUP($A973,pivot!$A:$I,計算式2026!AF$1,FALSE),0) -> 0 | AI973: =IFERROR(VLOOKUP($A973,pivot!$A:$I,計算式2026!AI$1,FALSE),0) -> 0 | AJ973: =IFERROR(VLOOKUP($A973,pivot!$A:$I,計算式2026!AJ$1,FALSE),0) -> 0 | AK973: =IFERROR(VLOOKUP($A973,pivot!$A:$I,計算式2026!AK$1,FALSE),0) -> 0 | AL973: =IFERROR(VLOOKUP($A973,pivot!$A:$I,計算式2026!AL$1,FALSE),0) -> 0
A974: 77294555L | B974: Singi Winter Cap | C974: 0 | D974: 0 | E974: 0 | F974: 0 | G974: 0 | H974: 0 | I974: 0 | J974: 0 | K974: 0 | R974: 0 | S974: 0 | T974: 1 | U974: 0 | V974: 0 | W974: 2 | X974: 1 | AE974: =IFERROR(VLOOKUP($A974,pivot!$A:$G,計算式2026!AE$1,FALSE),0) -> 0 | AF974: =IFERROR(VLOOKUP($A974,pivot!$A:$I,計算式2026!AF$1,FALSE),0) -> 0 | AI974: =IFERROR(VLOOKUP($A974,pivot!$A:$I,計算式2026!AI$1,FALSE),0) -> 0 | AJ974: =IFERROR(VLOOKUP($A974,pivot!$A:$I,計算式2026!AJ$1,FALSE),0) -> 0 | AK974: =IFERROR(VLOOKUP($A974,pivot!$A:$I,計算式2026!AK$1,FALSE),0) -> 0 | AL974: =IFERROR(VLOOKUP($A974,pivot!$A:$I,計算式2026!AL$1,FALSE),0) -> 0
A975: 77294555M | B975: Singi Winter Cap | C975: 0 | D975: 0 | E975: 0 | F975: 0 | G975: 0 | H975: 0 | I975: 0 | J975: 0 | K975: 0 | R975: 0 | S975: 0 | T975: 0 | U975: 0 | V975: 0 | W975: 0 | X975: 1 | AE975: =IFERROR(VLOOKUP($A975,pivot!$A:$G,計算式2026!AE$1,FALSE),0) -> 0 | AF975: =IFERROR(VLOOKUP($A975,pivot!$A:$I,計算式2026!AF$1,FALSE),0) -> 0 | AI975: =IFERROR(VLOOKUP($A975,pivot!$A:$I,計算式2026!AI$1,FALSE),0) -> 0 | AJ975: =IFERROR(VLOOKUP($A975,pivot!$A:$I,計算式2026!AJ$1,FALSE),0) -> 0 | AK975: =IFERROR(VLOOKUP($A975,pivot!$A:$I,計算式2026!AK$1,FALSE),0) -> 0 | AL975: =IFERROR(VLOOKUP($A975,pivot!$A:$I,計算式2026!AL$1,FALSE),0) -> 0
A976: 77295550L | B976: Singi Field Cap | C976: 0 | D976: 0 | E976: 0 | F976: 0 | G976: 0 | H976: 0 | I976: 0 | J976: 0 | K976: 0 | R976: 0 | S976: 0 | T976: 0 | U976: 0 | V976: 0 | W976: 0 | X976: 1 | AE976: =IFERROR(VLOOKUP($A976,pivot!$A:$G,計算式2026!AE$1,FALSE),0) -> 0 | AF976: =IFERROR(VLOOKUP($A976,pivot!$A:$I,計算式2026!AF$1,FALSE),0) -> 0 | AI976: =IFERROR(VLOOKUP($A976,pivot!$A:$I,計算式2026!AI$1,FALSE),0) -> 0 | AJ976: =IFERROR(VLOOKUP($A976,pivot!$A:$I,計算式2026!AJ$1,FALSE),0) -> 0 | AK976: =IFERROR(VLOOKUP($A976,pivot!$A:$I,計算式2026!AK$1,FALSE),0) -> 0 | AL976: =IFERROR(VLOOKUP($A976,pivot!$A:$I,計算式2026!AL$1,FALSE),0) -> 0
A977: 77295550M | B977: Singi Field Cap | C977: 0 | D977: 0 | E977: 0 | F977: 0 | G977: 0 | H977: 0 | I977: 0 | J977: 0 | K977: 0 | R977: 0 | S977: 0 | T977: 0 | U977: 0 | V977: 0 | W977: 0 | X977: 1 | AE977: =IFERROR(VLOOKUP($A977,pivot!$A:$G,計算式2026!AE$1,FALSE),0) -> 0 | AF977: =IFERROR(VLOOKUP($A977,pivot!$A:$I,計算式2026!AF$1,FALSE),0) -> 0 | AI977: =IFERROR(VLOOKUP($A977,pivot!$A:$I,計算式2026!AI$1,FALSE),0) -> 0 | AJ977: =IFERROR(VLOOKUP($A977,pivot!$A:$I,計算式2026!AJ$1,FALSE),0) -> 0 | AK977: =IFERROR(VLOOKUP($A977,pivot!$A:$I,計算式2026!AK$1,FALSE),0) -> 0 | AL977: =IFERROR(VLOOKUP($A977,pivot!$A:$I,計算式2026!AL$1,FALSE),0) -> 0
A978: 77295633L | B978: Singi Field Cap | C978: 0 | D978: 0 | E978: 0 | F978: 0 | G978: 0 | H978: 0 | I978: 0 | J978: 0 | K978: 0 | R978: 0 | S978: 0 | T978: 0 | U978: 0 | V978: 0 | W978: 0 | X978: 1 | AE978: =IFERROR(VLOOKUP($A978,pivot!$A:$G,計算式2026!AE$1,FALSE),0) -> 0 | AF978: =IFERROR(VLOOKUP($A978,pivot!$A:$I,計算式2026!AF$1,FALSE),0) -> 0 | AI978: =IFERROR(VLOOKUP($A978,pivot!$A:$I,計算式2026!AI$1,FALSE),0) -> 0 | AJ978: =IFERROR(VLOOKUP($A978,pivot!$A:$I,計算式2026!AJ$1,FALSE),0) -> 0 | AK978: =IFERROR(VLOOKUP($A978,pivot!$A:$I,計算式2026!AK$1,FALSE),0) -> 0 | AL978: =IFERROR(VLOOKUP($A978,pivot!$A:$I,計算式2026!AL$1,FALSE),0) -> 0
A979: 77295633M | B979: Singi Field Cap | C979: 0 | D979: 0 | E979: 0 | F979: 0 | G979: 0 | H979: 0 | I979: 0 | J979: 0 | K979: 0 | R979: 0 | S979: 0 | T979: 0 | U979: 0 | V979: 0 | W979: 0 | X979: 1 | AE979: =IFERROR(VLOOKUP($A979,pivot!$A:$G,計算式2026!AE$1,FALSE),0) -> 0 | AF979: =IFERROR(VLOOKUP($A979,pivot!$A:$I,計算式2026!AF$1,FALSE),0) -> 0 | AI979: =IFERROR(VLOOKUP($A979,pivot!$A:$I,計算式2026!AI$1,FALSE),0) -> 0 | AJ979: =IFERROR(VLOOKUP($A979,pivot!$A:$I,計算式2026!AJ$1,FALSE),0) -> 0 | AK979: =IFERROR(VLOOKUP($A979,pivot!$A:$I,計算式2026!AK$1,FALSE),0) -> 0 | AL979: =IFERROR(VLOOKUP($A979,pivot!$A:$I,計算式2026!AL$1,FALSE),0) -> 0
A980: 77297021X | B980: Canvas Brass Belt 4 cm | C980: 0 | D980: 0 | E980: 0 | F980: 0 | G980: 0 | H980: 0 | I980: 0 | J980: 0 | K980: 0 | R980: 0 | S980: 0 | T980: 0 | U980: 0 | V980: 0 | W980: 0 | X980: 0 | AE980: =IFERROR(VLOOKUP($A980,pivot!$A:$G,計算式2026!AE$1,FALSE),0) -> 0 | AF980: =IFERROR(VLOOKUP($A980,pivot!$A:$I,計算式2026!AF$1,FALSE),0) -> 0 | AI980: =IFERROR(VLOOKUP($A980,pivot!$A:$I,計算式2026!AI$1,FALSE),0) -> 0 | AJ980: =IFERROR(VLOOKUP($A980,pivot!$A:$I,計算式2026!AJ$1,FALSE),0) -> 0 | AK980: =IFERROR(VLOOKUP($A980,pivot!$A:$I,計算式2026!AK$1,FALSE),0) -> 0 | AL980: =IFERROR(VLOOKUP($A980,pivot!$A:$I,計算式2026!AL$1,FALSE),0) -> 0
A981: 77297032X | B981: Canvas Brass Belt 4 cm | C981: 34 | D981: 0 | E981: 0 | F981: 0 | G981: 0 | H981: 0 | I981: 0 | J981: 0 | K981: 0 | R981: 1 | S981: 2 | T981: 1 | U981: 0 | V981: 3 | W981: 0 | X981: 1 | AE981: =IFERROR(VLOOKUP($A981,pivot!$A:$G,計算式2026!AE$1,FALSE),0) -> 0 | AF981: =IFERROR(VLOOKUP($A981,pivot!$A:$I,計算式2026!AF$1,FALSE),0) -> 0 | AI981: =IFERROR(VLOOKUP($A981,pivot!$A:$I,計算式2026!AI$1,FALSE),0) -> 0 | AJ981: =IFERROR(VLOOKUP($A981,pivot!$A:$I,計算式2026!AJ$1,FALSE),0) -> 0 | AK981: =IFERROR(VLOOKUP($A981,pivot!$A:$I,計算式2026!AK$1,FALSE),0) -> 0 | AL981: =IFERROR(VLOOKUP($A981,pivot!$A:$I,計算式2026!AL$1,FALSE),0) -> 0
... A1132: 80522646-555146 | B1132: Kids Singi Fleece Jacket | C1132: 0 | D1132: 0 | E1132: 0 | F1132: 0 | G1132: 0 | H1132: 0 | I1132: 0 | J1132: 0 | K1132: 0 | R1132: 0 | S1132: 0 | T1132: 0 | U1132: 0 | V1132: 0 | W1132: 0 | X1132: 1 | AE1132: =IFERROR(VLOOKUP($A1132,pivot!$A:$G,計算式2026!AE$1,FALSE),0) -> 0 | AF1132: =IFERROR(VLOOKUP($A1132,pivot!$A:$I,計算式2026!AF$1,FALSE),0) -> 0 | AI1132: =IFERROR(VLOOKUP($A1132,pivot!$A:$I,計算式2026!AI$1,FALSE),0) -> 0 | AJ1132: =IFERROR(VLOOKUP($A1132,pivot!$A:$I,計算式2026!AJ$1,FALSE),0) -> 0 | AK1132: =IFERROR(VLOOKUP($A1132,pivot!$A:$I,計算式2026!AK$1,FALSE),0) -> 0 | AL1132: =IFERROR(VLOOKUP($A1132,pivot!$A:$I,計算式2026!AL$1,FALSE),0) -> 0
A1133: 80524550134 | B1133: Kids Keb Jacket | C1133: 0 | D1133: 0 | E1133: 0 | F1133: 0 | G1133: 0 | H1133: 0 | I1133: 0 | J1133: 0 | K1133: 0 | R1133: 0 | S1133: 0 | T1133: 1 | U1133: 0 | V1133: 0 | W1133: 0 | X1133: 1 | AE1133: =IFERROR(VLOOKUP($A1133,pivot!$A:$G,計算式2026!AE$1,FALSE),0) -> 0 | AF1133: =IFERROR(VLOOKUP($A1133,pivot!$A:$I,計算式2026!AF$1,FALSE),0) -> 0 | AI1133: =IFERROR(VLOOKUP($A1133,pivot!$A:$I,計算式2026!AI$1,FALSE),0) -> 0 | AJ1133: =IFERROR(VLOOKUP($A1133,pivot!$A:$I,計算式2026!AJ$1,FALSE),0) -> 0 | AK1133: =IFERROR(VLOOKUP($A1133,pivot!$A:$I,計算式2026!AK$1,FALSE),0) -> 0 | AL1133: =IFERROR(VLOOKUP($A1133,pivot!$A:$I,計算式2026!AL$1,FALSE),0) -> 0
A1134: 80524550146 | B1134: Kids Keb Jacket | C1134: 0 | D1134: 0 | E1134: 0 | F1134: 0 | G1134: 0 | H1134: 0 | I1134: 0 | J1134: 0 | K1134: 0 | R1134: 0 | S1134: 0 | T1134: 2 | U1134: 0 | V1134: 0 | W1134: 0 | X1134: 1 | AE1134: =IFERROR(VLOOKUP($A1134,pivot!$A:$G,計算式2026!AE$1,FALSE),0) -> 0 | AF1134: =IFERROR(VLOOKUP($A1134,pivot!$A:$I,計算式2026!AF$1,FALSE),0) -> 0 | AI1134: =IFERROR(VLOOKUP($A1134,pivot!$A:$I,計算式2026!AI$1,FALSE),0) -> 0 | AJ1134: =IFERROR(VLOOKUP($A1134,pivot!$A:$I,計算式2026!AJ$1,FALSE),0) -> 0 | AK1134: =IFERROR(VLOOKUP($A1134,pivot!$A:$I,計算式2026!AK$1,FALSE),0) -> 0 | AL1134: =IFERROR(VLOOKUP($A1134,pivot!$A:$I,計算式2026!AL$1,FALSE),0) -> 0
A1135: 80524646-555134 | B1135: Kids Keb Jacket | C1135: 0 | D1135: 0 | E1135: 0 | F1135: 0 | G1135: 0 | H1135: 0 | I1135: 0 | J1135: 0 | K1135: 0 | R1135: 0 | S1135: 0 | T1135: 1 | U1135: 0 | V1135: 0 | W1135: 0 | X1135: 1 | AE1135: =IFERROR(VLOOKUP($A1135,pivot!$A:$G,計算式2026!AE$1,FALSE),0) -> 0 | AF1135: =IFERROR(VLOOKUP($A1135,pivot!$A:$I,計算式2026!AF$1,FALSE),0) -> 0 | AI1135: =IFERROR(VLOOKUP($A1135,pivot!$A:$I,計算式2026!AI$1,FALSE),0) -> 0 | AJ1135: =IFERROR(VLOOKUP($A1135,pivot!$A:$I,計算式2026!AJ$1,FALSE),0) -> 0 | AK1135: =IFERROR(VLOOKUP($A1135,pivot!$A:$I,計算式2026!AK$1,FALSE),0) -> 0 | AL1135: =IFERROR(VLOOKUP($A1135,pivot!$A:$I,計算式2026!AL$1,FALSE),0) -> 0
A1136: 80524646-555146 | B1136: Kids Keb Jacket | C1136: 0 | D1136: 0 | E1136: 0 | F1136: 0 | G1136: 0 | H1136: 0 | I1136: 0 | J1136: 0 | K1136: 0 | R1136: 0 | S1136: 0 | T1136: 2 | U1136: 0 | V1136: 0 | W1136: 0 | X1136: 1 | AE1136: =IFERROR(VLOOKUP($A1136,pivot!$A:$G,計算式2026!AE$1,FALSE),0) -> 0 | AF1136: =IFERROR(VLOOKUP($A1136,pivot!$A:$I,計算式2026!AF$1,FALSE),0) -> 0 | AI1136: =IFERROR(VLOOKUP($A1136,pivot!$A:$I,計算式2026!AI$1,FALSE),0) -> 0 | AJ1136: =IFERROR(VLOOKUP($A1136,pivot!$A:$I,計算式2026!AJ$1,FALSE),0) -> 0 | AK1136: =IFERROR(VLOOKUP($A1136,pivot!$A:$I,計算式2026!AK$1,FALSE),0) -> 0 | AL1136: =IFERROR(VLOOKUP($A1136,pivot!$A:$I,計算式2026!AL$1,FALSE),0) -> 0
A1137: 80526525104 | B1137: Kids Trail T-Shirt | C1137: 4 | D1137: 0 | E1137: 0 | F1137: 0 | G1137: 0 | H1137: 0 | I1137: 0 | J1137: 0 | K1137: 0 | R1137: 0 | S1137: 0 | T1137: 0 | U1137: 0 | V1137: 0 | W1137: 0 | X1137: 1 | AE1137: =IFERROR(VLOOKUP($A1137,pivot!$A:$G,計算式2026!AE$1,FALSE),0) -> 0 | AF1137: =IFERROR(VLOOKUP($A1137,pivot!$A:$I,計算式2026!AF$1,FALSE),0) -> 0 | AI1137: =IFERROR(VLOOKUP($A1137,pivot!$A:$I,計算式2026!AI$1,FALSE),0) -> 0 | AJ1137: =IFERROR(VLOOKUP($A1137,pivot!$A:$I,計算式2026!AJ$1,FALSE),0) -> 0 | AK1137: =IFERROR(VLOOKUP($A1137,pivot!$A:$I,計算式2026!AK$1,FALSE),0) -> 0 | AL1137: =IFERROR(VLOOKUP($A1137,pivot!$A:$I,計算式2026!AL$1,FALSE),0) -> 0
A1138: 80526525110 | B1138: Kids Trail T-Shirt | C1138: 4 | D1138: 0 | E1138: 0 | F1138: 0 | G1138: 0 | H1138: 0 | I1138: 0 | J1138: 0 | K1138: 0 | R1138: 0 | S1138: 0 | T1138: 0 | U1138: 0 | V1138: 0 | W1138: 0 | X1138: 1 | AE1138: =IFERROR(VLOOKUP($A1138,pivot!$A:$G,計算式2026!AE$1,FALSE),0) -> 0 | AF1138: =IFERROR(VLOOKUP($A1138,pivot!$A:$I,計算式2026!AF$1,FALSE),0) -> 0 | AI1138: =IFERROR(VLOOKUP($A1138,pivot!$A:$I,計算式2026!AI$1,FALSE),0) -> 0 | AJ1138: =IFERROR(VLOOKUP($A1138,pivot!$A:$I,計算式2026!AJ$1,FALSE),0) -> 0 | AK1138: =IFERROR(VLOOKUP($A1138,pivot!$A:$I,計算式2026!AK$1,FALSE),0) -> 0 | AL1138: =IFERROR(VLOOKUP($A1138,pivot!$A:$I,計算式2026!AL$1,FALSE),0) -> 0
A1139: 80526525116 | B1139: Kids Trail T-Shirt | C1139: 4 | D1139: 0 | E1139: 0 | F1139: 0 | G1139: 0 | H1139: 0 | I1139: 0 | J1139: 0 | K1139: 0 | R1139: 0 | S1139: 0 | T1139: 0 | U1139: 0 | V1139: 0 | W1139: 0 | X1139: 1 | AE1139: =IFERROR(VLOOKUP($A1139,pivot!$A:$G,計算式2026!AE$1,FALSE),0) -> 0 | AF1139: =IFERROR(VLOOKUP($A1139,pivot!$A:$I,計算式2026!AF$1,FALSE),0) -> 0 | AI1139: =IFERROR(VLOOKUP($A1139,pivot!$A:$I,計算式2026!AI$1,FALSE),0) -> 0 | AJ1139: =IFERROR(VLOOKUP($A1139,pivot!$A:$I,計算式2026!AJ$1,FALSE),0) -> 0 | AK1139: =IFERROR(VLOOKUP($A1139,pivot!$A:$I,計算式2026!AK$1,FALSE),0) -> 0 | AL1139: =IFERROR(VLOOKUP($A1139,pivot!$A:$I,計算式2026!AL$1,FALSE),0) -> 0
A1140: 80526525122 | B1140: Kids Trail T-Shirt | C1140: 4 | D1140: 0 | E1140: 0 | F1140: 0 | G1140: 0 | H1140: 0 | I1140: 0 | J1140: 0 | K1140: 0 | R1140: 0 | S1140: 0 | T1140: 0 | U1140: 0 | V1140: 0 | W1140: 0 | X1140: 1 | AE1140: =IFERROR(VLOOKUP($A1140,pivot!$A:$G,計算式2026!AE$1,FALSE),0) -> 0 | AF1140: =IFERROR(VLOOKUP($A1140,pivot!$A:$I,計算式2026!AF$1,FALSE),0) -> 0 | AI1140: =IFERROR(VLOOKUP($A1140,pivot!$A:$I,計算式2026!AI$1,FALSE),0) -> 0 | AJ1140: =IFERROR(VLOOKUP($A1140,pivot!$A:$I,計算式2026!AJ$1,FALSE),0) -> 0 | AK1140: =IFERROR(VLOOKUP($A1140,pivot!$A:$I,計算式2026!AK$1,FALSE),0) -> 0 | AL1140: =IFERROR(VLOOKUP($A1140,pivot!$A:$I,計算式2026!AL$1,FALSE),0) -> 0
A1141: 80526525128 | B1141: Kids Trail T-Shirt | C1141: 3 | D1141: 0 | E1141: 0 | F1141: 0 | G1141: 0 | H1141: 0 | I1141: 0 | J1141: 0 | K1141: 0 | R1141: 0 | S1141: 0 | T1141: 0 | U1141: 0 | V1141: 0 | W1141: 0 | X1141: 1 | AE1141: =IFERROR(VLOOKUP($A1141,pivot!$A:$G,計算式2026!AE$1,FALSE),0) -> 0 | AF1141: =IFERROR(VLOOKUP($A1141,pivot!$A:$I,計算式2026!AF$1,FALSE),0) -> 0 | AI1141: =IFERROR(VLOOKUP($A1141,pivot!$A:$I,計算式2026!AI$1,FALSE),0) -> 0 | AJ1141: =IFERROR(VLOOKUP($A1141,pivot!$A:$I,計算式2026!AJ$1,FALSE),0) -> 0 | AK1141: =IFERROR(VLOOKUP($A1141,pivot!$A:$I,計算式2026!AK$1,FALSE),0) -> 0 | AL1141: =IFERROR(VLOOKUP($A1141,pivot!$A:$I,計算式2026!AL$1,FALSE),0) -> 0
A1142: 80526525134 | B1142: Kids Trail T-Shirt | C1142: 2 | D1142: 0 | E1142: 0 | F1142: 0 | G1142: 0 | H1142: 0 | I1142: 0 | J1142: 0 | K1142: 0 | R1142: 0 | S1142: 0 | T1142: 0 | U1142: 0 | V1142: 0 | W1142: 0 | X1142: 1 | AE1142: =IFERROR(VLOOKUP($A1142,pivot!$A:$G,計算式2026!AE$1,FALSE),0) -> 0 | AF1142: =IFERROR(VLOOKUP($A1142,pivot!$A:$I,計算式2026!AF$1,FALSE),0) -> 0 | AI1142: =IFERROR(VLOOKUP($A1142,pivot!$A:$I,計算式2026!AI$1,FALSE),0) -> 0 | AJ1142: =IFERROR(VLOOKUP($A1142,pivot!$A:$I,計算式2026!AJ$1,FALSE),0) -> 0 | AK1142: =IFERROR(VLOOKUP($A1142,pivot!$A:$I,計算式2026!AK$1,FALSE),0) -> 0 | AL1142: =IFERROR(VLOOKUP($A1142,pivot!$A:$I,計算式2026!AL$1,FALSE),0) -> 0
A1143: 80526610104 | B1143: Kids Trail T-Shirt | C1143: 4 | D1143: 0 | E1143: 0 | F1143: 0 | G1143: 0 | H1143: 0 | I1143: 0 | J1143: 0 | K1143: 0 | R1143: 0 | S1143: 0 | T1143: 0 | U1143: 0 | V1143: 0 | W1143: 0 | X1143: 1 | AE1143: =IFERROR(VLOOKUP($A1143,pivot!$A:$G,計算式2026!AE$1,FALSE),0) -> 0 | AF1143: =IFERROR(VLOOKUP($A1143,pivot!$A:$I,計算式2026!AF$1,FALSE),0) -> 0 | AI1143: =IFERROR(VLOOKUP($A1143,pivot!$A:$I,計算式2026!AI$1,FALSE),0) -> 0 | AJ1143: =IFERROR(VLOOKUP($A1143,pivot!$A:$I,計算式2026!AJ$1,FALSE),0) -> 0 | AK1143: =IFERROR(VLOOKUP($A1143,pivot!$A:$I,計算式2026!AK$1,FALSE),0) -> 0 | AL1143: =IFERROR(VLOOKUP($A1143,pivot!$A:$I,計算式2026!AL$1,FALSE),0) -> 0
A1144: 80526610110 | B1144: Kids Trail T-Shirt | C1144: 4 | D1144: 0 | E1144: 0 | F1144: 0 | G1144: 0 | H1144: 0 | I1144: 0 | J1144: 0 | K1144: 0 | R1144: 0 | S1144: 0 | T1144: 0 | U1144: 0 | V1144: 0 | W1144: 0 | X1144: 1 | AE1144: =IFERROR(VLOOKUP($A1144,pivot!$A:$G,計算式2026!AE$1,FALSE),0) -> 0 | AF1144: =IFERROR(VLOOKUP($A1144,pivot!$A:$I,計算式2026!AF$1,FALSE),0) -> 0 | AI1144: =IFERROR(VLOOKUP($A1144,pivot!$A:$I,計算式2026!AI$1,FALSE),0) -> 0 | AJ1144: =IFERROR(VLOOKUP($A1144,pivot!$A:$I,計算式2026!AJ$1,FALSE),0) -> 0 | AK1144: =IFERROR(VLOOKUP($A1144,pivot!$A:$I,計算式2026!AK$1,FALSE),0) -> 0 | AL1144: =IFERROR(VLOOKUP($A1144,pivot!$A:$I,計算式2026!AL$1,FALSE),0) -> 0
A1145: 80526610116 | B1145: Kids Trail T-Shirt | C1145: 4 | D1145: 0 | E1145: 0 | F1145: 0 | G1145: 0 | H1145: 0 | I1145: 0 | J1145: 0 | K1145: 0 | R1145: 0 | S1145: 0 | T1145: 0 | U1145: 0 | V1145: 0 | W1145: 0 | X1145: 1 | AE1145: =IFERROR(VLOOKUP($A1145,pivot!$A:$G,計算式2026!AE$1,FALSE),0) -> 0 | AF1145: =IFERROR(VLOOKUP($A1145,pivot!$A:$I,計算式2026!AF$1,FALSE),0) -> 0 | AI1145: =IFERROR(VLOOKUP($A1145,pivot!$A:$I,計算式2026!AI$1,FALSE),0) -> 0 | AJ1145: =IFERROR(VLOOKUP($A1145,pivot!$A:$I,計算式2026!AJ$1,FALSE),0) -> 0 | AK1145: =IFERROR(VLOOKUP($A1145,pivot!$A:$I,計算式2026!AK$1,FALSE),0) -> 0 | AL1145: =IFERROR(VLOOKUP($A1145,pivot!$A:$I,計算式2026!AL$1,FALSE),0) -> 0
A1146: 80526610122 | B1146: Kids Trail T-Shirt | C1146: 4 | D1146: 0 | E1146: 0 | F1146: 0 | G1146: 0 | H1146: 0 | I1146: 0 | J1146: 0 | K1146: 0 | R1146: 0 | S1146: 0 | T1146: 0 | U1146: 0 | V1146: 0 | W1146: 0 | X1146: 1 | AE1146: =IFERROR(VLOOKUP($A1146,pivot!$A:$G,計算式2026!AE$1,FALSE),0) -> 0 | AF1146: =IFERROR(VLOOKUP($A1146,pivot!$A:$I,計算式2026!AF$1,FALSE),0) -> 0 | AI1146: =IFERROR(VLOOKUP($A1146,pivot!$A:$I,計算式2026!AI$1,FALSE),0) -> 0 | AJ1146: =IFERROR(VLOOKUP($A1146,pivot!$A:$I,計算式2026!AJ$1,FALSE),0) -> 0 | AK1146: =IFERROR(VLOOKUP($A1146,pivot!$A:$I,計算式2026!AK$1,FALSE),0) -> 0 | AL1146: =IFERROR(VLOOKUP($A1146,pivot!$A:$I,計算式2026!AL$1,FALSE),0) -> 0
A1147: 80526610128 | B1147: Kids Trail T-Shirt | C1147: 2 | D1147: 0 | E1147: 0 | F1147: 0 | G1147: 0 | H1147: 0 | I1147: 0 | J1147: 0 | K1147: 0 | R1147: 0 | S1147: 0 | T1147: 0 | U1147: 0 | V1147: 0 | W1147: 0 | X1147: 1 | AE1147: =IFERROR(VLOOKUP($A1147,pivot!$A:$G,計算式2026!AE$1,FALSE),0) -> 0 | AF1147: =IFERROR(VLOOKUP($A1147,pivot!$A:$I,計算式2026!AF$1,FALSE),0) -> 0 | AI1147: =IFERROR(VLOOKUP($A1147,pivot!$A:$I,計算式2026!AI$1,FALSE),0) -> 0 | AJ1147: =IFERROR(VLOOKUP($A1147,pivot!$A:$I,計算式2026!AJ$1,FALSE),0) -> 0 | AK1147: =IFERROR(VLOOKUP($A1147,pivot!$A:$I,計算式2026!AK$1,FALSE),0) -> 0 | AL1147: =IFERROR(VLOOKUP($A1147,pivot!$A:$I,計算式2026!AL$1,FALSE),0) -> 0
A1148: 80526610134 | B1148: Kids Trail T-Shirt | C1148: 1 | D1148: 0 | E1148: 0 | F1148: 0 | G1148: 0 | H1148: 0 | I1148: 0 | J1148: 0 | K1148: 0 | R1148: 0 | S1148: 0 | T1148: 0 | U1148: 0 | V1148: 0 | W1148: 0 | X1148: 1 | AE1148: =IFERROR(VLOOKUP($A1148,pivot!$A:$G,計算式2026!AE$1,FALSE),0) -> 0 | AF1148: =IFERROR(VLOOKUP($A1148,pivot!$A:$I,計算式2026!AF$1,FALSE),0) -> 0 | AI1148: =IFERROR(VLOOKUP($A1148,pivot!$A:$I,計算式2026!AI$1,FALSE),0) -> 0 | AJ1148: =IFERROR(VLOOKUP($A1148,pivot!$A:$I,計算式2026!AJ$1,FALSE),0) -> 0 | AK1148: =IFERROR(VLOOKUP($A1148,pivot!$A:$I,計算式2026!AK$1,FALSE),0) -> 0 | AL1148: =IFERROR(VLOOKUP($A1148,pivot!$A:$I,計算式2026!AL$1,FALSE),0) -> 0
... A1153: 80528124128 | B1153: Kids Trek Logo T-Shirt | C1153: 3 | D1153: 0 | E1153: 0 | F1153: 0 | G1153: 0 | H1153: 0 | I1153: 0 | J1153: 0 | K1153: 0 | R1153: 0 | S1153: 0 | T1153: 0 | U1153: 0 | V1153: 0 | W1153: 0 | X1153: 0 | AE1153: =IFERROR(VLOOKUP($A1153,pivot!$A:$G,計算式2026!AE$1,FALSE),0) -> 0 | AF1153: =IFERROR(VLOOKUP($A1153,pivot!$A:$I,計算式2026!AF$1,FALSE),0) -> 0 | AI1153: =IFERROR(VLOOKUP($A1153,pivot!$A:$I,計算式2026!AI$1,FALSE),0) -> 0 | AJ1153: =IFERROR(VLOOKUP($A1153,pivot!$A:$I,計算式2026!AJ$1,FALSE),0) -> 0 | AK1153: =IFERROR(VLOOKUP($A1153,pivot!$A:$I,計算式2026!AK$1,FALSE),0) -> 0 | AL1153: =IFERROR(VLOOKUP($A1153,pivot!$A:$I,計算式2026!AL$1,FALSE),0) -> 0
A1154: 80634510L | B1154: Fjallraven Polar Parka M | C1154: 0 | D1154: 2 | E1154: 0 | F1154: 0 | G1154: 0 | H1154: 0 | I1154: 0 | J1154: 0 | K1154: 0 | R1154: 0 | S1154: 0 | T1154: 0 | U1154: 0 | V1154: 0 | W1154: 0 | X1154: 0 | AE1154: =IFERROR(VLOOKUP($A1154,pivot!$A:$G,計算式2026!AE$1,FALSE),0) -> 0 | AF1154: =IFERROR(VLOOKUP($A1154,pivot!$A:$I,計算式2026!AF$1,FALSE),0) -> 0 | AI1154: =IFERROR(VLOOKUP($A1154,pivot!$A:$I,計算式2026!AI$1,FALSE),0) -> 0 | AJ1154: =IFERROR(VLOOKUP($A1154,pivot!$A:$I,計算式2026!AJ$1,FALSE),0) -> 0 | AK1154: =IFERROR(VLOOKUP($A1154,pivot!$A:$I,計算式2026!AK$1,FALSE),0) -> 0 | AL1154: =IFERROR(VLOOKUP($A1154,pivot!$A:$I,計算式2026!AL$1,FALSE),0) -> 0
A1155: 80634510M | B1155: Fjallraven Polar Parka M | C1155: 0 | D1155: 1 | E1155: 0 | F1155: 0 | G1155: 0 | H1155: 0 | I1155: 0 | J1155: 0 | K1155: 0 | R1155: 1 | S1155: 1 | T1155: 0 | U1155: 0 | V1155: 0 | W1155: 0 | X1155: 1 | AE1155: =IFERROR(VLOOKUP($A1155,pivot!$A:$G,計算式2026!AE$1,FALSE),0) -> 0 | AF1155: =IFERROR(VLOOKUP($A1155,pivot!$A:$I,計算式2026!AF$1,FALSE),0) -> 0 | AI1155: =IFERROR(VLOOKUP($A1155,pivot!$A:$I,計算式2026!AI$1,FALSE),0) -> 0 | AJ1155: =IFERROR(VLOOKUP($A1155,pivot!$A:$I,計算式2026!AJ$1,FALSE),0) -> 0 | AK1155: =IFERROR(VLOOKUP($A1155,pivot!$A:$I,計算式2026!AK$1,FALSE),0) -> 0 | AL1155: =IFERROR(VLOOKUP($A1155,pivot!$A:$I,計算式2026!AL$1,FALSE),0) -> 0
A1156: 80634510S | B1156: Fjallraven Polar Parka M | C1156: 0 | D1156: 2 | E1156: 0 | F1156: 0 | G1156: 0 | H1156: 0 | I1156: 0 | J1156: 0 | K1156: 0 | R1156: 0 | S1156: 1 | T1156: 0 | U1156: 0 | V1156: 1 | W1156: 0 | X1156: 1 | AE1156: =IFERROR(VLOOKUP($A1156,pivot!$A:$G,計算式2026!AE$1,FALSE),0) -> 0 | AF1156: =IFERROR(VLOOKUP($A1156,pivot!$A:$I,計算式2026!AF$1,FALSE),0) -> 0 | AI1156: =IFERROR(VLOOKUP($A1156,pivot!$A:$I,計算式2026!AI$1,FALSE),0) -> 0 | AJ1156: =IFERROR(VLOOKUP($A1156,pivot!$A:$I,計算式2026!AJ$1,FALSE),0) -> 0 | AK1156: =IFERROR(VLOOKUP($A1156,pivot!$A:$I,計算式2026!AK$1,FALSE),0) -> 0 | AL1156: =IFERROR(VLOOKUP($A1156,pivot!$A:$I,計算式2026!AL$1,FALSE),0) -> 0
A1157: 80634510XS | B1157: Fjallraven Polar Parka M | C1157: 0 | D1157: 0 | E1157: 0 | F1157: 0 | G1157: 0 | H1157: 0 | I1157: 0 | J1157: 0 | K1157: 0 | R1157: 0 | S1157: 0 | T1157: 0 | U1157: 0 | V1157: 1 | W1157: 0 | X1157: 1 | AE1157: =IFERROR(VLOOKUP($A1157,pivot!$A:$G,計算式2026!AE$1,FALSE),0) -> 0 | AF1157: =IFERROR(VLOOKUP($A1157,pivot!$A:$I,計算式2026!AF$1,FALSE),0) -> 0 | AI1157: =IFERROR(VLOOKUP($A1157,pivot!$A:$I,計算式2026!AI$1,FALSE),0) -> 0 | AJ1157: =IFERROR(VLOOKUP($A1157,pivot!$A:$I,計算式2026!AJ$1,FALSE),0) -> 0 | AK1157: =IFERROR(VLOOKUP($A1157,pivot!$A:$I,計算式2026!AK$1,FALSE),0) -> 0 | AL1157: =IFERROR(VLOOKUP($A1157,pivot!$A:$I,計算式2026!AL$1,FALSE),0) -> 0
A1158: 80637633S | B1158: Luhkka | C1158: 0 | D1158: 0 | E1158: 0 | F1158: 0 | G1158: 0 | H1158: 0 | I1158: 0 | J1158: 0 | K1158: 0 | R1158: 0 | S1158: 0 | T1158: 0 | U1158: 0 | V1158: 1 | W1158: 0 | X1158: 0 | AE1158: =IFERROR(VLOOKUP($A1158,pivot!$A:$G,計算式2026!AE$1,FALSE),0) -> 0 | AF1158: =IFERROR(VLOOKUP($A1158,pivot!$A:$I,計算式2026!AF$1,FALSE),0) -> 0 | AI1158: =IFERROR(VLOOKUP($A1158,pivot!$A:$I,計算式2026!AI$1,FALSE),0) -> 0 | AJ1158: =IFERROR(VLOOKUP($A1158,pivot!$A:$I,計算式2026!AJ$1,FALSE),0) -> 0 | AK1158: =IFERROR(VLOOKUP($A1158,pivot!$A:$I,計算式2026!AK$1,FALSE),0) -> 0 | AL1158: =IFERROR(VLOOKUP($A1158,pivot!$A:$I,計算式2026!AL$1,FALSE),0) -> 0
A1159: 80724031X | B1159: Poncho | C1159: 0 | D1159: 0 | E1159: 0 | F1159: 0 | G1159: 0 | H1159: 0 | I1159: 0 | J1159: 0 | K1159: 0 | R1159: 0 | S1159: 1 | T1159: 1 | U1159: 0 | V1159: 1 | W1159: 0 | X1159: 0 | AE1159: =IFERROR(VLOOKUP($A1159,pivot!$A:$G,計算式2026!AE$1,FALSE),0) -> 0 | AF1159: =IFERROR(VLOOKUP($A1159,pivot!$A:$I,計算式2026!AF$1,FALSE),0) -> 0 | AI1159: =IFERROR(VLOOKUP($A1159,pivot!$A:$I,計算式2026!AI$1,FALSE),0) -> 0 | AJ1159: =IFERROR(VLOOKUP($A1159,pivot!$A:$I,計算式2026!AJ$1,FALSE),0) -> 0 | AK1159: =IFERROR(VLOOKUP($A1159,pivot!$A:$I,計算式2026!AK$1,FALSE),0) -> 0 | AL1159: =IFERROR(VLOOKUP($A1159,pivot!$A:$I,計算式2026!AL$1,FALSE),0) -> 0
A1160: 80724210X | B1160: Poncho | C1160: 0 | D1160: 1 | E1160: 0 | F1160: 0 | G1160: 0 | H1160: 0 | I1160: 0 | J1160: 0 | K1160: 0 | R1160: 0 | S1160: 2 | T1160: 0 | U1160: 0 | V1160: 1 | W1160: 0 | X1160: 1 | AE1160: =IFERROR(VLOOKUP($A1160,pivot!$A:$G,計算式2026!AE$1,FALSE),0) -> 0 | AF1160: =IFERROR(VLOOKUP($A1160,pivot!$A:$I,計算式2026!AF$1,FALSE),0) -> 0 | AI1160: =IFERROR(VLOOKUP($A1160,pivot!$A:$I,計算式2026!AI$1,FALSE),0) -> 0 | AJ1160: =IFERROR(VLOOKUP($A1160,pivot!$A:$I,計算式2026!AJ$1,FALSE),0) -> 0 | AK1160: =IFERROR(VLOOKUP($A1160,pivot!$A:$I,計算式2026!AK$1,FALSE),0) -> 0 | AL1160: =IFERROR(VLOOKUP($A1160,pivot!$A:$I,計算式2026!AL$1,FALSE),0) -> 0
A1161: 80724525X | B1161: Poncho | C1161: 0 | D1161: 0 | E1161: 0 | F1161: 0 | G1161: 0 | H1161: 0 | I1161: 0 | J1161: 0 | K1161: 0 | R1161: 0 | S1161: 1 | T1161: 1 | U1161: 0 | V1161: 1 | W1161: 0 | X1161: 1 | AE1161: =IFERROR(VLOOKUP($A1161,pivot!$A:$G,計算式2026!AE$1,FALSE),0) -> 0 | AF1161: =IFERROR(VLOOKUP($A1161,pivot!$A:$I,計算式2026!AF$1,FALSE),0) -> 0 | AI1161: =IFERROR(VLOOKUP($A1161,pivot!$A:$I,計算式2026!AI$1,FALSE),0) -> 0 | AJ1161: =IFERROR(VLOOKUP($A1161,pivot!$A:$I,計算式2026!AJ$1,FALSE),0) -> 0 | AK1161: =IFERROR(VLOOKUP($A1161,pivot!$A:$I,計算式2026!AK$1,FALSE),0) -> 0 | AL1161: =IFERROR(VLOOKUP($A1161,pivot!$A:$I,計算式2026!AL$1,FALSE),0) -> 0
A1162: 80724633X | B1162: Poncho | C1162: 0 | D1162: 0 | E1162: 0 | F1162: 0 | G1162: 0 | H1162: 0 | I1162: 0 | J1162: 0 | K1162: 0 | R1162: 0 | S1162: 0 | T1162: 1 | U1162: 0 | V1162: 2 | W1162: 0 | X1162: 0 | AE1162: =IFERROR(VLOOKUP($A1162,pivot!$A:$G,計算式2026!AE$1,FALSE),0) -> 0 | AF1162: =IFERROR(VLOOKUP($A1162,pivot!$A:$I,計算式2026!AF$1,FALSE),0) -> 0 | AI1162: =IFERROR(VLOOKUP($A1162,pivot!$A:$I,計算式2026!AI$1,FALSE),0) -> 0 | AJ1162: =IFERROR(VLOOKUP($A1162,pivot!$A:$I,計算式2026!AJ$1,FALSE),0) -> 0 | AK1162: =IFERROR(VLOOKUP($A1162,pivot!$A:$I,計算式2026!AK$1,FALSE),0) -> 0 | AL1162: =IFERROR(VLOOKUP($A1162,pivot!$A:$I,計算式2026!AL$1,FALSE),0) -> 0
A1163: 80766550S | B1163: Snow Flake Parka | C1163: 3 | D1163: 0 | E1163: 0 | F1163: 0 | G1163: 0 | H1163: 0 | I1163: 0 | J1163: 0 | K1163: 0 | R1163: 0 | S1163: 0 | T1163: 0 | U1163: 0 | V1163: 0 | W1163: 0 | X1163: 1 | AE1163: =IFERROR(VLOOKUP($A1163,pivot!$A:$G,計算式2026!AE$1,FALSE),0) -> 0 | AF1163: =IFERROR(VLOOKUP($A1163,pivot!$A:$I,計算式2026!AF$1,FALSE),0) -> 0 | AI1163: =IFERROR(VLOOKUP($A1163,pivot!$A:$I,計算式2026!AI$1,FALSE),0) -> 0 | AJ1163: =IFERROR(VLOOKUP($A1163,pivot!$A:$I,計算式2026!AJ$1,FALSE),0) -> 0 | AK1163: =IFERROR(VLOOKUP($A1163,pivot!$A:$I,計算式2026!AK$1,FALSE),0) -> 0 | AL1163: =IFERROR(VLOOKUP($A1163,pivot!$A:$I,計算式2026!AL$1,FALSE),0) -> 0
A1164: 80766550XS | B1164: Snow Flake Parka | C1164: 3 | D1164: 0 | E1164: 0 | F1164: 0 | G1164: 0 | H1164: 0 | I1164: 0 | J1164: 0 | K1164: 0 | R1164: 0 | S1164: 0 | T1164: 0 | U1164: 0 | V1164: 0 | W1164: 0 | X1164: 1 | AE1164: =IFERROR(VLOOKUP($A1164,pivot!$A:$G,計算式2026!AE$1,FALSE),0) -> 0 | AF1164: =IFERROR(VLOOKUP($A1164,pivot!$A:$I,計算式2026!AF$1,FALSE),0) -> 0 | AI1164: =IFERROR(VLOOKUP($A1164,pivot!$A:$I,計算式2026!AI$1,FALSE),0) -> 0 | AJ1164: =IFERROR(VLOOKUP($A1164,pivot!$A:$I,計算式2026!AJ$1,FALSE),0) -> 0 | AK1164: =IFERROR(VLOOKUP($A1164,pivot!$A:$I,計算式2026!AK$1,FALSE),0) -> 0 | AL1164: =IFERROR(VLOOKUP($A1164,pivot!$A:$I,計算式2026!AL$1,FALSE),0) -> 0
A1165: 80766555S | B1165: Snow Flake Parka | C1165: 1 | D1165: 0 | E1165: 0 | F1165: 0 | G1165: 0 | H1165: 0 | I1165: 0 | J1165: 0 | K1165: 0 | R1165: 0 | S1165: 0 | T1165: 0 | U1165: 0 | V1165: 0 | W1165: 0 | X1165: 2 | AE1165: =IFERROR(VLOOKUP($A1165,pivot!$A:$G,計算式2026!AE$1,FALSE),0) -> 0 | AF1165: =IFERROR(VLOOKUP($A1165,pivot!$A:$I,計算式2026!AF$1,FALSE),0) -> 0 | AI1165: =IFERROR(VLOOKUP($A1165,pivot!$A:$I,計算式2026!AI$1,FALSE),0) -> 0 | AJ1165: =IFERROR(VLOOKUP($A1165,pivot!$A:$I,計算式2026!AJ$1,FALSE),0) -> 0 | AK1165: =IFERROR(VLOOKUP($A1165,pivot!$A:$I,計算式2026!AK$1,FALSE),0) -> 0 | AL1165: =IFERROR(VLOOKUP($A1165,pivot!$A:$I,計算式2026!AL$1,FALSE),0) -> 0
... A1204: 81434620XS | B1204: Greenland Winter Jacket | C1204: 0 | D1204: 0 | E1204: 0 | F1204: 0 | G1204: 0 | H1204: 0 | I1204: 0 | J1204: 0 | K1204: 0 | R1204: 0 | S1204: 0 | T1204: 0 | U1204: 0 | V1204: 0 | W1204: 0 | X1204: 1 | AE1204: =IFERROR(VLOOKUP($A1204,pivot!$A:$G,計算式2026!AE$1,FALSE),0) -> 0 | AF1204: =IFERROR(VLOOKUP($A1204,pivot!$A:$I,計算式2026!AF$1,FALSE),0) -> 0 | AI1204: =IFERROR(VLOOKUP($A1204,pivot!$A:$I,計算式2026!AI$1,FALSE),0) -> 0 | AJ1204: =IFERROR(VLOOKUP($A1204,pivot!$A:$I,計算式2026!AJ$1,FALSE),0) -> 0 | AK1204: =IFERROR(VLOOKUP($A1204,pivot!$A:$I,計算式2026!AK$1,FALSE),0) -> 0 | AL1204: =IFERROR(VLOOKUP($A1204,pivot!$A:$I,計算式2026!AL$1,FALSE),0) -> 0
A1205: 8146155546 | B1205: Barents Pro Jeans | C1205: 0 | D1205: 0 | E1205: 0 | F1205: 0 | G1205: 0 | H1205: 0 | I1205: 0 | J1205: 0 | K1205: 0 | R1205: 0 | S1205: 0 | T1205: 0 | U1205: 0 | V1205: 0 | W1205: 0 | X1205: 1 | AE1205: =IFERROR(VLOOKUP($A1205,pivot!$A:$G,計算式2026!AE$1,FALSE),0) -> 0 | AF1205: =IFERROR(VLOOKUP($A1205,pivot!$A:$I,計算式2026!AF$1,FALSE),0) -> 0 | AI1205: =IFERROR(VLOOKUP($A1205,pivot!$A:$I,計算式2026!AI$1,FALSE),0) -> 0 | AJ1205: =IFERROR(VLOOKUP($A1205,pivot!$A:$I,計算式2026!AJ$1,FALSE),0) -> 0 | AK1205: =IFERROR(VLOOKUP($A1205,pivot!$A:$I,計算式2026!AK$1,FALSE),0) -> 0 | AL1205: =IFERROR(VLOOKUP($A1205,pivot!$A:$I,計算式2026!AL$1,FALSE),0) -> 0
A1206: 8146155548 | B1206: Barents Pro Jeans | C1206: 0 | D1206: 0 | E1206: 0 | F1206: 0 | G1206: 0 | H1206: 0 | I1206: 0 | J1206: 0 | K1206: 0 | R1206: 0 | S1206: 0 | T1206: 0 | U1206: 0 | V1206: 0 | W1206: 0 | X1206: 1 | AE1206: =IFERROR(VLOOKUP($A1206,pivot!$A:$G,計算式2026!AE$1,FALSE),0) -> 0 | AF1206: =IFERROR(VLOOKUP($A1206,pivot!$A:$I,計算式2026!AF$1,FALSE),0) -> 0 | AI1206: =IFERROR(VLOOKUP($A1206,pivot!$A:$I,計算式2026!AI$1,FALSE),0) -> 0 | AJ1206: =IFERROR(VLOOKUP($A1206,pivot!$A:$I,計算式2026!AJ$1,FALSE),0) -> 0 | AK1206: =IFERROR(VLOOKUP($A1206,pivot!$A:$I,計算式2026!AK$1,FALSE),0) -> 0 | AL1206: =IFERROR(VLOOKUP($A1206,pivot!$A:$I,計算式2026!AL$1,FALSE),0) -> 0
A1207: 8146155550 | B1207: Barents Pro Jeans | C1207: 0 | D1207: 0 | E1207: 0 | F1207: 0 | G1207: 0 | H1207: 0 | I1207: 0 | J1207: 0 | K1207: 0 | R1207: 0 | S1207: 0 | T1207: 0 | U1207: 0 | V1207: 0 | W1207: 0 | X1207: 2 | AE1207: =IFERROR(VLOOKUP($A1207,pivot!$A:$G,計算式2026!AE$1,FALSE),0) -> 0 | AF1207: =IFERROR(VLOOKUP($A1207,pivot!$A:$I,計算式2026!AF$1,FALSE),0) -> 0 | AI1207: =IFERROR(VLOOKUP($A1207,pivot!$A:$I,計算式2026!AI$1,FALSE),0) -> 0 | AJ1207: =IFERROR(VLOOKUP($A1207,pivot!$A:$I,計算式2026!AJ$1,FALSE),0) -> 0 | AK1207: =IFERROR(VLOOKUP($A1207,pivot!$A:$I,計算式2026!AK$1,FALSE),0) -> 0 | AL1207: =IFERROR(VLOOKUP($A1207,pivot!$A:$I,計算式2026!AL$1,FALSE),0) -> 0
A1208: 81461633-63346 | B1208: Barents Pro Jeans | C1208: 0 | D1208: 0 | E1208: 0 | F1208: 0 | G1208: 0 | H1208: 0 | I1208: 0 | J1208: 0 | K1208: 0 | R1208: 0 | S1208: 0 | T1208: 0 | U1208: 0 | V1208: 0 | W1208: 0 | X1208: 1 | AE1208: =IFERROR(VLOOKUP($A1208,pivot!$A:$G,計算式2026!AE$1,FALSE),0) -> 0 | AF1208: =IFERROR(VLOOKUP($A1208,pivot!$A:$I,計算式2026!AF$1,FALSE),0) -> 0 | AI1208: =IFERROR(VLOOKUP($A1208,pivot!$A:$I,計算式2026!AI$1,FALSE),0) -> 0 | AJ1208: =IFERROR(VLOOKUP($A1208,pivot!$A:$I,計算式2026!AJ$1,FALSE),0) -> 0 | AK1208: =IFERROR(VLOOKUP($A1208,pivot!$A:$I,計算式2026!AK$1,FALSE),0) -> 0 | AL1208: =IFERROR(VLOOKUP($A1208,pivot!$A:$I,計算式2026!AL$1,FALSE),0) -> 0
A1209: 81461633-63348 | B1209: Barents Pro Jeans | C1209: 0 | D1209: 0 | E1209: 0 | F1209: 0 | G1209: 0 | H1209: 0 | I1209: 0 | J1209: 0 | K1209: 0 | R1209: 0 | S1209: 0 | T1209: 0 | U1209: 0 | V1209: 0 | W1209: 0 | X1209: 1 | AE1209: =IFERROR(VLOOKUP($A1209,pivot!$A:$G,計算式2026!AE$1,FALSE),0) -> 0 | AF1209: =IFERROR(VLOOKUP($A1209,pivot!$A:$I,計算式2026!AF$1,FALSE),0) -> 0 | AI1209: =IFERROR(VLOOKUP($A1209,pivot!$A:$I,計算式2026!AI$1,FALSE),0) -> 0 | AJ1209: =IFERROR(VLOOKUP($A1209,pivot!$A:$I,計算式2026!AJ$1,FALSE),0) -> 0 | AK1209: =IFERROR(VLOOKUP($A1209,pivot!$A:$I,計算式2026!AK$1,FALSE),0) -> 0 | AL1209: =IFERROR(VLOOKUP($A1209,pivot!$A:$I,計算式2026!AL$1,FALSE),0) -> 0
A1210: 81461633-63350 | B1210: Barents Pro Jeans | C1210: 0 | D1210: 0 | E1210: 0 | F1210: 0 | G1210: 0 | H1210: 0 | I1210: 0 | J1210: 0 | K1210: 0 | R1210: 0 | S1210: 0 | T1210: 0 | U1210: 0 | V1210: 0 | W1210: 0 | X1210: 2 | AE1210: =IFERROR(VLOOKUP($A1210,pivot!$A:$G,計算式2026!AE$1,FALSE),0) -> 0 | AF1210: =IFERROR(VLOOKUP($A1210,pivot!$A:$I,計算式2026!AF$1,FALSE),0) -> 0 | AI1210: =IFERROR(VLOOKUP($A1210,pivot!$A:$I,計算式2026!AI$1,FALSE),0) -> 0 | AJ1210: =IFERROR(VLOOKUP($A1210,pivot!$A:$I,計算式2026!AJ$1,FALSE),0) -> 0 | AK1210: =IFERROR(VLOOKUP($A1210,pivot!$A:$I,計算式2026!AK$1,FALSE),0) -> 0 | AL1210: =IFERROR(VLOOKUP($A1210,pivot!$A:$I,計算式2026!AL$1,FALSE),0) -> 0
A1211: 81461R030-03048 | B1211: Barents Pro Jeans | C1211: 0 | D1211: 0 | E1211: 0 | F1211: 0 | G1211: 0 | H1211: 0 | I1211: 0 | J1211: 0 | K1211: 0 | R1211: 0 | S1211: 1 | T1211: 1 | U1211: 0 | V1211: 2 | W1211: 0 | X1211: 1 | AE1211: =IFERROR(VLOOKUP($A1211,pivot!$A:$G,計算式2026!AE$1,FALSE),0) -> 0 | AF1211: =IFERROR(VLOOKUP($A1211,pivot!$A:$I,計算式2026!AF$1,FALSE),0) -> 0 | AI1211: =IFERROR(VLOOKUP($A1211,pivot!$A:$I,計算式2026!AI$1,FALSE),0) -> 0 | AJ1211: =IFERROR(VLOOKUP($A1211,pivot!$A:$I,計算式2026!AJ$1,FALSE),0) -> 0 | AK1211: =IFERROR(VLOOKUP($A1211,pivot!$A:$I,計算式2026!AK$1,FALSE),0) -> 0 | AL1211: =IFERROR(VLOOKUP($A1211,pivot!$A:$I,計算式2026!AL$1,FALSE),0) -> 0
A1212: 81461R030-03050 | B1212: Barents Pro Jeans | C1212: 0 | D1212: 0 | E1212: 0 | F1212: 0 | G1212: 0 | H1212: 0 | I1212: 0 | J1212: 0 | K1212: 0 | R1212: 0 | S1212: 1 | T1212: 1 | U1212: 0 | V1212: 1 | W1212: 0 | X1212: 1 | AE1212: =IFERROR(VLOOKUP($A1212,pivot!$A:$G,計算式2026!AE$1,FALSE),0) -> 0 | AF1212: =IFERROR(VLOOKUP($A1212,pivot!$A:$I,計算式2026!AF$1,FALSE),0) -> 0 | AI1212: =IFERROR(VLOOKUP($A1212,pivot!$A:$I,計算式2026!AI$1,FALSE),0) -> 0 | AJ1212: =IFERROR(VLOOKUP($A1212,pivot!$A:$I,計算式2026!AJ$1,FALSE),0) -> 0 | AK1212: =IFERROR(VLOOKUP($A1212,pivot!$A:$I,計算式2026!AK$1,FALSE),0) -> 0 | AL1212: =IFERROR(VLOOKUP($A1212,pivot!$A:$I,計算式2026!AL$1,FALSE),0) -> 0
A1213: 81461R03048 | B1213: Barents Pro Jeans | C1213: 0 | D1213: 0 | E1213: 0 | F1213: 0 | G1213: 0 | H1213: 0 | I1213: 0 | J1213: 0 | K1213: 0 | R1213: 0 | S1213: 0 | T1213: 0 | U1213: 0 | V1213: 1 | W1213: 0 | X1213: 1 | AE1213: =IFERROR(VLOOKUP($A1213,pivot!$A:$G,計算式2026!AE$1,FALSE),0) -> 0 | AF1213: =IFERROR(VLOOKUP($A1213,pivot!$A:$I,計算式2026!AF$1,FALSE),0) -> 0 | AI1213: =IFERROR(VLOOKUP($A1213,pivot!$A:$I,計算式2026!AI$1,FALSE),0) -> 0 | AJ1213: =IFERROR(VLOOKUP($A1213,pivot!$A:$I,計算式2026!AJ$1,FALSE),0) -> 0 | AK1213: =IFERROR(VLOOKUP($A1213,pivot!$A:$I,計算式2026!AK$1,FALSE),0) -> 0 | AL1213: =IFERROR(VLOOKUP($A1213,pivot!$A:$I,計算式2026!AL$1,FALSE),0) -> 0
A1214: 81461R03050 | B1214: Barents Pro Jeans | C1214: 0 | D1214: 0 | E1214: 0 | F1214: 0 | G1214: 0 | H1214: 0 | I1214: 0 | J1214: 0 | K1214: 0 | R1214: 0 | S1214: 1 | T1214: 0 | U1214: 0 | V1214: 0 | W1214: 0 | X1214: 0 | AE1214: =IFERROR(VLOOKUP($A1214,pivot!$A:$G,計算式2026!AE$1,FALSE),0) -> 0 | AF1214: =IFERROR(VLOOKUP($A1214,pivot!$A:$I,計算式2026!AF$1,FALSE),0) -> 0 | AI1214: =IFERROR(VLOOKUP($A1214,pivot!$A:$I,計算式2026!AI$1,FALSE),0) -> 0 | AJ1214: =IFERROR(VLOOKUP($A1214,pivot!$A:$I,計算式2026!AJ$1,FALSE),0) -> 0 | AK1214: =IFERROR(VLOOKUP($A1214,pivot!$A:$I,計算式2026!AK$1,FALSE),0) -> 0 | AL1214: =IFERROR(VLOOKUP($A1214,pivot!$A:$I,計算式2026!AL$1,FALSE),0) -> 0
A1215: 81461R55548 | B1215: Barents Pro Jeans | C1215: 0 | D1215: 0 | E1215: 0 | F1215: 0 | G1215: 0 | H1215: 0 | I1215: 0 | J1215: 0 | K1215: 0 | R1215: 0 | S1215: 2 | T1215: 1 | U1215: 0 | V1215: 2 | W1215: 0 | X1215: 1 | AE1215: =IFERROR(VLOOKUP($A1215,pivot!$A:$G,計算式2026!AE$1,FALSE),0) -> 0 | AF1215: =IFERROR(VLOOKUP($A1215,pivot!$A:$I,計算式2026!AF$1,FALSE),0) -> 0 | AI1215: =IFERROR(VLOOKUP($A1215,pivot!$A:$I,計算式2026!AI$1,FALSE),0) -> 0 | AJ1215: =IFERROR(VLOOKUP($A1215,pivot!$A:$I,計算式2026!AJ$1,FALSE),0) -> 0 | AK1215: =IFERROR(VLOOKUP($A1215,pivot!$A:$I,計算式2026!AK$1,FALSE),0) -> 0 | AL1215: =IFERROR(VLOOKUP($A1215,pivot!$A:$I,計算式2026!AL$1,FALSE),0) -> 0
A1216: 81461R55550 | B1216: Barents Pro Jeans | C1216: 0 | D1216: 0 | E1216: 0 | F1216: 0 | G1216: 0 | H1216: 0 | I1216: 0 | J1216: 0 | K1216: 0 | R1216: 0 | S1216: 1 | T1216: 1 | U1216: 0 | V1216: 1 | W1216: 0 | X1216: 1 | AE1216: =IFERROR(VLOOKUP($A1216,pivot!$A:$G,計算式2026!AE$1,FALSE),0) -> 0 | AF1216: =IFERROR(VLOOKUP($A1216,pivot!$A:$I,計算式2026!AF$1,FALSE),0) -> 0 | AI1216: =IFERROR(VLOOKUP($A1216,pivot!$A:$I,計算式2026!AI$1,FALSE),0) -> 0 | AJ1216: =IFERROR(VLOOKUP($A1216,pivot!$A:$I,計算式2026!AJ$1,FALSE),0) -> 0 | AK1216: =IFERROR(VLOOKUP($A1216,pivot!$A:$I,計算式2026!AK$1,FALSE),0) -> 0 | AL1216: =IFERROR(VLOOKUP($A1216,pivot!$A:$I,計算式2026!AL$1,FALSE),0) -> 0
A1217: 8147103046 | B1217: Barents Pro Winter Jeans | C1217: 0 | D1217: 0 | E1217: 0 | F1217: 0 | G1217: 0 | H1217: 0 | I1217: 0 | J1217: 0 | K1217: 0 | R1217: 0 | S1217: 0 | T1217: 0 | U1217: 0 | V1217: 1 | W1217: 0 | X1217: 0 | AE1217: =IFERROR(VLOOKUP($A1217,pivot!$A:$G,計算式2026!AE$1,FALSE),0) -> 0 | AF1217: =IFERROR(VLOOKUP($A1217,pivot!$A:$I,計算式2026!AF$1,FALSE),0) -> 0 | AI1217: =IFERROR(VLOOKUP($A1217,pivot!$A:$I,計算式2026!AI$1,FALSE),0) -> 0 | AJ1217: =IFERROR(VLOOKUP($A1217,pivot!$A:$I,計算式2026!AJ$1,FALSE),0) -> 0 | AK1217: =IFERROR(VLOOKUP($A1217,pivot!$A:$I,計算式2026!AK$1,FALSE),0) -> 0 | AL1217: =IFERROR(VLOOKUP($A1217,pivot!$A:$I,計算式2026!AL$1,FALSE),0) -> 0
A1218: 8147103048 | B1218: Barents Pro Winter Jeans | C1218: 0 | D1218: 0 | E1218: 0 | F1218: 0 | G1218: 0 | H1218: 0 | I1218: 0 | J1218: 0 | K1218: 0 | R1218: 0 | S1218: 0 | T1218: 1 | U1218: 0 | V1218: 0 | W1218: 0 | X1218: 0 | AE1218: =IFERROR(VLOOKUP($A1218,pivot!$A:$G,計算式2026!AE$1,FALSE),0) -> 0 | AF1218: =IFERROR(VLOOKUP($A1218,pivot!$A:$I,計算式2026!AF$1,FALSE),0) -> 0 | AI1218: =IFERROR(VLOOKUP($A1218,pivot!$A:$I,計算式2026!AI$1,FALSE),0) -> 0 | AJ1218: =IFERROR(VLOOKUP($A1218,pivot!$A:$I,計算式2026!AJ$1,FALSE),0) -> 0 | AK1218: =IFERROR(VLOOKUP($A1218,pivot!$A:$I,計算式2026!AK$1,FALSE),0) -> 0 | AL1218: =IFERROR(VLOOKUP($A1218,pivot!$A:$I,計算式2026!AL$1,FALSE),0) -> 0
A1219: 8147103050 | B1219: Barents Pro Winter Jeans | C1219: 0 | D1219: 0 | E1219: 0 | F1219: 0 | G1219: 0 | H1219: 0 | I1219: 0 | J1219: 0 | K1219: 0 | R1219: 0 | S1219: 0 | T1219: 2 | U1219: 0 | V1219: 0 | W1219: 0 | X1219: 0 | AE1219: =IFERROR(VLOOKUP($A1219,pivot!$A:$G,計算式2026!AE$1,FALSE),0) -> 0 | AF1219: =IFERROR(VLOOKUP($A1219,pivot!$A:$I,計算式2026!AF$1,FALSE),0) -> 0 | AI1219: =IFERROR(VLOOKUP($A1219,pivot!$A:$I,計算式2026!AI$1,FALSE),0) -> 0 | AJ1219: =IFERROR(VLOOKUP($A1219,pivot!$A:$I,計算式2026!AJ$1,FALSE),0) -> 0 | AK1219: =IFERROR(VLOOKUP($A1219,pivot!$A:$I,計算式2026!AK$1,FALSE),0) -> 0 | AL1219: =IFERROR(VLOOKUP($A1219,pivot!$A:$I,計算式2026!AL$1,FALSE),0) -> 0
A1220: 8147163346 | B1220: Barents Pro Winter Jeans | C1220: 0 | D1220: 0 | E1220: 0 | F1220: 0 | G1220: 0 | H1220: 0 | I1220: 0 | J1220: 0 | K1220: 0 | R1220: 0 | S1220: 0 | T1220: 1 | U1220: 0 | V1220: 0 | W1220: 0 | X1220: 1 | AE1220: =IFERROR(VLOOKUP($A1220,pivot!$A:$G,計算式2026!AE$1,FALSE),0) -> 0 | AF1220: =IFERROR(VLOOKUP($A1220,pivot!$A:$I,計算式2026!AF$1,FALSE),0) -> 0 | AI1220: =IFERROR(VLOOKUP($A1220,pivot!$A:$I,計算式2026!AI$1,FALSE),0) -> 0 | AJ1220: =IFERROR(VLOOKUP($A1220,pivot!$A:$I,計算式2026!AJ$1,FALSE),0) -> 0 | AK1220: =IFERROR(VLOOKUP($A1220,pivot!$A:$I,計算式2026!AK$1,FALSE),0) -> 0 | AL1220: =IFERROR(VLOOKUP($A1220,pivot!$A:$I,計算式2026!AL$1,FALSE),0) -> 0
A1221: 8147163348 | B1221: Barents Pro Winter Jeans | C1221: 0 | D1221: 0 | E1221: 0 | F1221: 0 | G1221: 0 | H1221: 0 | I1221: 0 | J1221: 0 | K1221: 0 | R1221: 0 | S1221: 0 | T1221: 2 | U1221: 0 | V1221: 0 | W1221: 0 | X1221: 2 | AE1221: =IFERROR(VLOOKUP($A1221,pivot!$A:$G,計算式2026!AE$1,FALSE),0) -> 0 | AF1221: =IFERROR(VLOOKUP($A1221,pivot!$A:$I,計算式2026!AF$1,FALSE),0) -> 0 | AI1221: =IFERROR(VLOOKUP($A1221,pivot!$A:$I,計算式2026!AI$1,FALSE),0) -> 0 | AJ1221: =IFERROR(VLOOKUP($A1221,pivot!$A:$I,計算式2026!AJ$1,FALSE),0) -> 0 | AK1221: =IFERROR(VLOOKUP($A1221,pivot!$A:$I,計算式2026!AK$1,FALSE),0) -> 0 | AL1221: =IFERROR(VLOOKUP($A1221,pivot!$A:$I,計算式2026!AL$1,FALSE),0) -> 0
A1222: 81506550L | B1222: Abisko Trekking Tights | C1222: 0 | D1222: 0 | E1222: 0 | F1222: 0 | G1222: 0 | H1222: 0 | I1222: 0 | J1222: 0 | K1222: 0 | R1222: 0 | S1222: 0 | T1222: 0 | U1222: 0 | V1222: 0 | W1222: 0 | X1222: 0 | AE1222: =IFERROR(VLOOKUP($A1222,pivot!$A:$G,計算式2026!AE$1,FALSE),0) -> 0 | AF1222: =IFERROR(VLOOKUP($A1222,pivot!$A:$I,計算式2026!AF$1,FALSE),0) -> 0 | AI1222: =IFERROR(VLOOKUP($A1222,pivot!$A:$I,計算式2026!AI$1,FALSE),0) -> 0 | AJ1222: =IFERROR(VLOOKUP($A1222,pivot!$A:$I,計算式2026!AJ$1,FALSE),0) -> 0 | AK1222: =IFERROR(VLOOKUP($A1222,pivot!$A:$I,計算式2026!AK$1,FALSE),0) -> 0 | AL1222: =IFERROR(VLOOKUP($A1222,pivot!$A:$I,計算式2026!AL$1,FALSE),0) -> 0
A1223: 81506550M | B1223: Abisko Trekking Tights | C1223: 0 | D1223: 0 | E1223: 0 | F1223: 0 | G1223: 0 | H1223: 0 | I1223: 0 | J1223: 0 | K1223: 0 | R1223: 0 | S1223: 0 | T1223: 0 | U1223: 0 | V1223: 0 | W1223: 0 | X1223: 0 | AE1223: =IFERROR(VLOOKUP($A1223,pivot!$A:$G,計算式2026!AE$1,FALSE),0) -> 0 | AF1223: =IFERROR(VLOOKUP($A1223,pivot!$A:$I,計算式2026!AF$1,FALSE),0) -> 0 | AI1223: =IFERROR(VLOOKUP($A1223,pivot!$A:$I,計算式2026!AI$1,FALSE),0) -> 0 | AJ1223: =IFERROR(VLOOKUP($A1223,pivot!$A:$I,計算式2026!AJ$1,FALSE),0) -> 0 | AK1223: =IFERROR(VLOOKUP($A1223,pivot!$A:$I,計算式2026!AK$1,FALSE),0) -> 0 | AL1223: =IFERROR(VLOOKUP($A1223,pivot!$A:$I,計算式2026!AL$1,FALSE),0) -> 0
A1224: 81511020M | B1224: Ovik Polo Shirt M | C1224: 5 | D1224: 0 | E1224: 0 | F1224: 0 | G1224: 0 | H1224: 0 | I1224: 0 | J1224: 0 | K1224: 0 | R1224: 0 | S1224: 0 | T1224: 1 | U1224: 0 | V1224: 0 | W1224: 0 | X1224: 1 | AE1224: =IFERROR(VLOOKUP($A1224,pivot!$A:$G,計算式2026!AE$1,FALSE),0) -> 0 | AF1224: =IFERROR(VLOOKUP($A1224,pivot!$A:$I,計算式2026!AF$1,FALSE),0) -> 0 | AI1224: =IFERROR(VLOOKUP($A1224,pivot!$A:$I,計算式2026!AI$1,FALSE),0) -> 0 | AJ1224: =IFERROR(VLOOKUP($A1224,pivot!$A:$I,計算式2026!AJ$1,FALSE),0) -> 0 | AK1224: =IFERROR(VLOOKUP($A1224,pivot!$A:$I,計算式2026!AK$1,FALSE),0) -> 0 | AL1224: =IFERROR(VLOOKUP($A1224,pivot!$A:$I,計算式2026!AL$1,FALSE),0) -> 0
A1225: 81511020S | B1225: Ovik Polo Shirt M | C1225: 1 | D1225: 0 | E1225: 0 | F1225: 0 | G1225: 0 | H1225: 0 | I1225: 0 | J1225: 0 | K1225: 0 | R1225: 0 | S1225: 0 | T1225: 0 | U1225: 0 | V1225: 0 | W1225: 0 | X1225: 1 | AE1225: =IFERROR(VLOOKUP($A1225,pivot!$A:$G,計算式2026!AE$1,FALSE),0) -> 0 | AF1225: =IFERROR(VLOOKUP($A1225,pivot!$A:$I,計算式2026!AF$1,FALSE),0) -> 0 | AI1225: =IFERROR(VLOOKUP($A1225,pivot!$A:$I,計算式2026!AI$1,FALSE),0) -> 0 | AJ1225: =IFERROR(VLOOKUP($A1225,pivot!$A:$I,計算式2026!AJ$1,FALSE),0) -> 0 | AK1225: =IFERROR(VLOOKUP($A1225,pivot!$A:$I,計算式2026!AK$1,FALSE),0) -> 0 | AL1225: =IFERROR(VLOOKUP($A1225,pivot!$A:$I,計算式2026!AL$1,FALSE),0) -> 0
A1226: 81511560M | B1226: Ovik Polo Shirt M | C1226: 12 | D1226: 0 | E1226: 0 | F1226: 0 | G1226: 0 | H1226: 0 | I1226: 0 | J1226: 0 | K1226: 0 | R1226: 0 | S1226: 0 | T1226: 1 | U1226: 0 | V1226: 0 | W1226: 0 | X1226: 1 | AE1226: =IFERROR(VLOOKUP($A1226,pivot!$A:$G,計算式2026!AE$1,FALSE),0) -> 0 | AF1226: =IFERROR(VLOOKUP($A1226,pivot!$A:$I,計算式2026!AF$1,FALSE),0) -> 0 | AI1226: =IFERROR(VLOOKUP($A1226,pivot!$A:$I,計算式2026!AI$1,FALSE),0) -> 0 | AJ1226: =IFERROR(VLOOKUP($A1226,pivot!$A:$I,計算式2026!AJ$1,FALSE),0) -> 1 | AK1226: =IFERROR(VLOOKUP($A1226,pivot!$A:$I,計算式2026!AK$1,FALSE),0) -> 0 | AL1226: =IFERROR(VLOOKUP($A1226,pivot!$A:$I,計算式2026!AL$1,FALSE),0) -> 0
A1227: 81511560S | B1227: Ovik Polo Shirt M | C1227: 5 | D1227: 0 | E1227: 0 | F1227: 0 | G1227: 0 | H1227: 0 | I1227: 0 | J1227: 0 | K1227: 0 | R1227: 0 | S1227: 0 | T1227: 0 | U1227: 0 | V1227: 0 | W1227: 0 | X1227: 1 | AE1227: =IFERROR(VLOOKUP($A1227,pivot!$A:$G,計算式2026!AE$1,FALSE),0) -> 0 | AF1227: =IFERROR(VLOOKUP($A1227,pivot!$A:$I,計算式2026!AF$1,FALSE),0) -> 0 | AI1227: =IFERROR(VLOOKUP($A1227,pivot!$A:$I,計算式2026!AI$1,FALSE),0) -> 0 | AJ1227: =IFERROR(VLOOKUP($A1227,pivot!$A:$I,計算式2026!AJ$1,FALSE),0) -> 0 | AK1227: =IFERROR(VLOOKUP($A1227,pivot!$A:$I,計算式2026!AK$1,FALSE),0) -> 0 | AL1227: =IFERROR(VLOOKUP($A1227,pivot!$A:$I,計算式2026!AL$1,FALSE),0) -> 0
A1228: 81512030L | B1228: Abisko Trail T-Shirt Print | C1228: 1 | D1228: 0 | E1228: 0 | F1228: 0 | G1228: 0 | H1228: 0 | I1228: 0 | J1228: 0 | K1228: 0 | R1228: 0 | S1228: 0 | T1228: 0 | U1228: 0 | V1228: 0 | W1228: 0 | X1228: 0 | AE1228: =IFERROR(VLOOKUP($A1228,pivot!$A:$G,計算式2026!AE$1,FALSE),0) -> 0 | AF1228: =IFERROR(VLOOKUP($A1228,pivot!$A:$I,計算式2026!AF$1,FALSE),0) -> 0 | AI1228: =IFERROR(VLOOKUP($A1228,pivot!$A:$I,計算式2026!AI$1,FALSE),0) -> 0 | AJ1228: =IFERROR(VLOOKUP($A1228,pivot!$A:$I,計算式2026!AJ$1,FALSE),0) -> 0 | AK1228: =IFERROR(VLOOKUP($A1228,pivot!$A:$I,計算式2026!AK$1,FALSE),0) -> 0 | AL1228: =IFERROR(VLOOKUP($A1228,pivot!$A:$I,計算式2026!AL$1,FALSE),0) -> 0
A1229: 81512030M | B1229: Abisko Trail T-Shirt Print | C1229: 1 | D1229: 0 | E1229: 0 | F1229: 0 | G1229: 0 | H1229: 0 | I1229: 0 | J1229: 0 | K1229: 0 | R1229: 0 | S1229: 0 | T1229: 1 | U1229: 0 | V1229: 0 | W1229: 0 | X1229: 0 | AE1229: =IFERROR(VLOOKUP($A1229,pivot!$A:$G,計算式2026!AE$1,FALSE),0) -> 0 | AF1229: =IFERROR(VLOOKUP($A1229,pivot!$A:$I,計算式2026!AF$1,FALSE),0) -> 0 | AI1229: =IFERROR(VLOOKUP($A1229,pivot!$A:$I,計算式2026!AI$1,FALSE),0) -> 0 | AJ1229: =IFERROR(VLOOKUP($A1229,pivot!$A:$I,計算式2026!AJ$1,FALSE),0) -> 0 | AK1229: =IFERROR(VLOOKUP($A1229,pivot!$A:$I,計算式2026!AK$1,FALSE),0) -> 0 | AL1229: =IFERROR(VLOOKUP($A1229,pivot!$A:$I,計算式2026!AL$1,FALSE),0) -> 0
A1230: 81512030S | B1230: Abisko Trail T-Shirt Print | C1230: 1 | D1230: 0 | E1230: 0 | F1230: 0 | G1230: 0 | H1230: 0 | I1230: 0 | J1230: 0 | K1230: 0 | R1230: 0 | S1230: 0 | T1230: 1 | U1230: 0 | V1230: 0 | W1230: 0 | X1230: 0 | AE1230: =IFERROR(VLOOKUP($A1230,pivot!$A:$G,計算式2026!AE$1,FALSE),0) -> 0 | AF1230: =IFERROR(VLOOKUP($A1230,pivot!$A:$I,計算式2026!AF$1,FALSE),0) -> 0 | AI1230: =IFERROR(VLOOKUP($A1230,pivot!$A:$I,計算式2026!AI$1,FALSE),0) -> 0 | AJ1230: =IFERROR(VLOOKUP($A1230,pivot!$A:$I,計算式2026!AJ$1,FALSE),0) -> 0 | AK1230: =IFERROR(VLOOKUP($A1230,pivot!$A:$I,計算式2026!AK$1,FALSE),0) -> 0 | AL1230: =IFERROR(VLOOKUP($A1230,pivot!$A:$I,計算式2026!AL$1,FALSE),0) -> 0
A1231: 81512520M | B1231: Abisko Trail T-Shirt Print | C1231: 1 | D1231: 0 | E1231: 0 | F1231: 0 | G1231: 0 | H1231: 0 | I1231: 0 | J1231: 0 | K1231: 0 | R1231: 0 | S1231: 0 | T1231: 1 | U1231: 0 | V1231: 0 | W1231: 0 | X1231: 0 | AE1231: =IFERROR(VLOOKUP($A1231,pivot!$A:$G,計算式2026!AE$1,FALSE),0) -> 0 | AF1231: =IFERROR(VLOOKUP($A1231,pivot!$A:$I,計算式2026!AF$1,FALSE),0) -> 0 | AI1231: =IFERROR(VLOOKUP($A1231,pivot!$A:$I,計算式2026!AI$1,FALSE),0) -> 0 | AJ1231: =IFERROR(VLOOKUP($A1231,pivot!$A:$I,計算式2026!AJ$1,FALSE),0) -> 0 | AK1231: =IFERROR(VLOOKUP($A1231,pivot!$A:$I,計算式2026!AK$1,FALSE),0) -> 0 | AL1231: =IFERROR(VLOOKUP($A1231,pivot!$A:$I,計算式2026!AL$1,FALSE),0) -> 0
A1232: 81512520S | B1232: Abisko Trail T-Shirt Print | C1232: 2 | D1232: 0 | E1232: 0 | F1232: 0 | G1232: 0 | H1232: 0 | I1232: 0 | J1232: 0 | K1232: 0 | R1232: 0 | S1232: 0 | T1232: 1 | U1232: 0 | V1232: 0 | W1232: 0 | X1232: 0 | AE1232: =IFERROR(VLOOKUP($A1232,pivot!$A:$G,計算式2026!AE$1,FALSE),0) -> 0 | AF1232: =IFERROR(VLOOKUP($A1232,pivot!$A:$I,計算式2026!AF$1,FALSE),0) -> 0 | AI1232: =IFERROR(VLOOKUP($A1232,pivot!$A:$I,計算式2026!AI$1,FALSE),0) -> 0 | AJ1232: =IFERROR(VLOOKUP($A1232,pivot!$A:$I,計算式2026!AJ$1,FALSE),0) -> 0 | AK1232: =IFERROR(VLOOKUP($A1232,pivot!$A:$I,計算式2026!AK$1,FALSE),0) -> 0 | AL1232: =IFERROR(VLOOKUP($A1232,pivot!$A:$I,計算式2026!AL$1,FALSE),0) -> 0
A1233: 81517020M | B1233: Greenland Zip Hoodie | C1233: 0 | D1233: 0 | E1233: 0 | F1233: 0 | G1233: 0 | H1233: 0 | I1233: 0 | J1233: 0 | K1233: 0 | R1233: 0 | S1233: 1 | T1233: 2 | U1233: 0 | V1233: 0 | W1233: 0 | X1233: 0 | AE1233: =IFERROR(VLOOKUP($A1233,pivot!$A:$G,計算式2026!AE$1,FALSE),0) -> 0 | AF1233: =IFERROR(VLOOKUP($A1233,pivot!$A:$I,計算式2026!AF$1,FALSE),0) -> 0 | AI1233: =IFERROR(VLOOKUP($A1233,pivot!$A:$I,計算式2026!AI$1,FALSE),0) -> 0 | AJ1233: =IFERROR(VLOOKUP($A1233,pivot!$A:$I,計算式2026!AJ$1,FALSE),0) -> 0 | AK1233: =IFERROR(VLOOKUP($A1233,pivot!$A:$I,計算式2026!AK$1,FALSE),0) -> 0 | AL1233: =IFERROR(VLOOKUP($A1233,pivot!$A:$I,計算式2026!AL$1,FALSE),0) -> 0
A1234: 81517020S | B1234: Greenland Zip Hoodie | C1234: 0 | D1234: 0 | E1234: 0 | F1234: 0 | G1234: 0 | H1234: 0 | I1234: 0 | J1234: 0 | K1234: 0 | R1234: 0 | S1234: 1 | T1234: 1 | U1234: 1 | V1234: 1 | W1234: 0 | X1234: 0 | AE1234: =IFERROR(VLOOKUP($A1234,pivot!$A:$G,計算式2026!AE$1,FALSE),0) -> 0 | AF1234: =IFERROR(VLOOKUP($A1234,pivot!$A:$I,計算式2026!AF$1,FALSE),0) -> 0 | AI1234: =IFERROR(VLOOKUP($A1234,pivot!$A:$I,計算式2026!AI$1,FALSE),0) -> 0 | AJ1234: =IFERROR(VLOOKUP($A1234,pivot!$A:$I,計算式2026!AJ$1,FALSE),0) -> 0 | AK1234: =IFERROR(VLOOKUP($A1234,pivot!$A:$I,計算式2026!AK$1,FALSE),0) -> 0 | AL1234: =IFERROR(VLOOKUP($A1234,pivot!$A:$I,計算式2026!AL$1,FALSE),0) -> 0
A1235: 8152303246 | B1235: High Coast Hike Trousers | C1235: 1 | D1235: 0 | E1235: 0 | F1235: 0 | G1235: 0 | H1235: 0 | I1235: 0 | J1235: 0 | K1235: 0 | R1235: 0 | S1235: 0 | T1235: 2 | U1235: 0 | V1235: 0 | W1235: 0 | X1235: 1 | AE1235: =IFERROR(VLOOKUP($A1235,pivot!$A:$G,計算式2026!AE$1,FALSE),0) -> 0 | AF1235: =IFERROR(VLOOKUP($A1235,pivot!$A:$I,計算式2026!AF$1,FALSE),0) -> 0 | AI1235: =IFERROR(VLOOKUP($A1235,pivot!$A:$I,計算式2026!AI$1,FALSE),0) -> 0 | AJ1235: =IFERROR(VLOOKUP($A1235,pivot!$A:$I,計算式2026!AJ$1,FALSE),0) -> 0 | AK1235: =IFERROR(VLOOKUP($A1235,pivot!$A:$I,計算式2026!AK$1,FALSE),0) -> 0 | AL1235: =IFERROR(VLOOKUP($A1235,pivot!$A:$I,計算式2026!AL$1,FALSE),0) -> 0
A1236: 8152303248 | B1236: High Coast Hike Trousers | C1236: 5 | D1236: 0 | E1236: 0 | F1236: 0 | G1236: 0 | H1236: 0 | I1236: 0 | J1236: 0 | K1236: 0 | R1236: 0 | S1236: 0 | T1236: 2 | U1236: 0 | V1236: 0 | W1236: 0 | X1236: 1 | AE1236: =IFERROR(VLOOKUP($A1236,pivot!$A:$G,計算式2026!AE$1,FALSE),0) -> 0 | AF1236: =IFERROR(VLOOKUP($A1236,pivot!$A:$I,計算式2026!AF$1,FALSE),0) -> 0 | AI1236: =IFERROR(VLOOKUP($A1236,pivot!$A:$I,計算式2026!AI$1,FALSE),0) -> 0 | AJ1236: =IFERROR(VLOOKUP($A1236,pivot!$A:$I,計算式2026!AJ$1,FALSE),0) -> 0 | AK1236: =IFERROR(VLOOKUP($A1236,pivot!$A:$I,計算式2026!AK$1,FALSE),0) -> 0 | AL1236: =IFERROR(VLOOKUP($A1236,pivot!$A:$I,計算式2026!AL$1,FALSE),0) -> 0
A1237: 8152303250 | B1237: High Coast Hike Trousers | C1237: 4 | D1237: 0 | E1237: 0 | F1237: 0 | G1237: 0 | H1237: 0 | I1237: 0 | J1237: 0 | K1237: 0 | R1237: 0 | S1237: 0 | T1237: 2 | U1237: 0 | V1237: 0 | W1237: 0 | X1237: 1 | AE1237: =IFERROR(VLOOKUP($A1237,pivot!$A:$G,計算式2026!AE$1,FALSE),0) -> 0 | AF1237: =IFERROR(VLOOKUP($A1237,pivot!$A:$I,計算式2026!AF$1,FALSE),0) -> 0 | AI1237: =IFERROR(VLOOKUP($A1237,pivot!$A:$I,計算式2026!AI$1,FALSE),0) -> 0 | AJ1237: =IFERROR(VLOOKUP($A1237,pivot!$A:$I,計算式2026!AJ$1,FALSE),0) -> 0 | AK1237: =IFERROR(VLOOKUP($A1237,pivot!$A:$I,計算式2026!AK$1,FALSE),0) -> 0 | AL1237: =IFERROR(VLOOKUP($A1237,pivot!$A:$I,計算式2026!AL$1,FALSE),0) -> 0
A1238: 8152356046 | B1238: High Coast Hike Trousers | C1238: 1 | D1238: 0 | E1238: 0 | F1238: 0 | G1238: 0 | H1238: 0 | I1238: 0 | J1238: 0 | K1238: 0 | R1238: 0 | S1238: 0 | T1238: 2 | U1238: 0 | V1238: 0 | W1238: 0 | X1238: 1 | AE1238: =IFERROR(VLOOKUP($A1238,pivot!$A:$G,計算式2026!AE$1,FALSE),0) -> 0 | AF1238: =IFERROR(VLOOKUP($A1238,pivot!$A:$I,計算式2026!AF$1,FALSE),0) -> 0 | AI1238: =IFERROR(VLOOKUP($A1238,pivot!$A:$I,計算式2026!AI$1,FALSE),0) -> 0 | AJ1238: =IFERROR(VLOOKUP($A1238,pivot!$A:$I,計算式2026!AJ$1,FALSE),0) -> 0 | AK1238: =IFERROR(VLOOKUP($A1238,pivot!$A:$I,計算式2026!AK$1,FALSE),0) -> 0 | AL1238: =IFERROR(VLOOKUP($A1238,pivot!$A:$I,計算式2026!AL$1,FALSE),0) -> 0
A1239: 8152356048 | B1239: High Coast Hike Trousers | C1239: 0 | D1239: 0 | E1239: 0 | F1239: 0 | G1239: 0 | H1239: 0 | I1239: 0 | J1239: 0 | K1239: 0 | R1239: 0 | S1239: 0 | T1239: 2 | U1239: 0 | V1239: 0 | W1239: 0 | X1239: 1 | AE1239: =IFERROR(VLOOKUP($A1239,pivot!$A:$G,計算式2026!AE$1,FALSE),0) -> 0 | AF1239: =IFERROR(VLOOKUP($A1239,pivot!$A:$I,計算式2026!AF$1,FALSE),0) -> 0 | AI1239: =IFERROR(VLOOKUP($A1239,pivot!$A:$I,計算式2026!AI$1,FALSE),0) -> 0 | AJ1239: =IFERROR(VLOOKUP($A1239,pivot!$A:$I,計算式2026!AJ$1,FALSE),0) -> 0 | AK1239: =IFERROR(VLOOKUP($A1239,pivot!$A:$I,計算式2026!AK$1,FALSE),0) -> 0 | AL1239: =IFERROR(VLOOKUP($A1239,pivot!$A:$I,計算式2026!AL$1,FALSE),0) -> 0
A1240: 8152356050 | B1240: High Coast Hike Trousers | C1240: 0 | D1240: 0 | E1240: 0 | F1240: 0 | G1240: 0 | H1240: 0 | I1240: 0 | J1240: 0 | K1240: 0 | R1240: 0 | S1240: 0 | T1240: 2 | U1240: 0 | V1240: 0 | W1240: 0 | X1240: 1 | AE1240: =IFERROR(VLOOKUP($A1240,pivot!$A:$G,計算式2026!AE$1,FALSE),0) -> 0 | AF1240: =IFERROR(VLOOKUP($A1240,pivot!$A:$I,計算式2026!AF$1,FALSE),0) -> 0 | AI1240: =IFERROR(VLOOKUP($A1240,pivot!$A:$I,計算式2026!AI$1,FALSE),0) -> 0 | AJ1240: =IFERROR(VLOOKUP($A1240,pivot!$A:$I,計算式2026!AJ$1,FALSE),0) -> 0 | AK1240: =IFERROR(VLOOKUP($A1240,pivot!$A:$I,計算式2026!AK$1,FALSE),0) -> 0 | AL1240: =IFERROR(VLOOKUP($A1240,pivot!$A:$I,計算式2026!AL$1,FALSE),0) -> 0
A1241: 81523R03246 | B1241: High Coast Hike Trousers | C1241: 0 | D1241: 0 | E1241: 0 | F1241: 0 | G1241: 0 | H1241: 0 | I1241: 0 | J1241: 0 | K1241: 0 | R1241: 0 | S1241: 1 | T1241: 1 | U1241: 0 | V1241: 2 | W1241: 0 | X1241: 1 | AE1241: =IFERROR(VLOOKUP($A1241,pivot!$A:$G,計算式2026!AE$1,FALSE),0) -> 0 | AF1241: =IFERROR(VLOOKUP($A1241,pivot!$A:$I,計算式2026!AF$1,FALSE),0) -> 0 | AI1241: =IFERROR(VLOOKUP($A1241,pivot!$A:$I,計算式2026!AI$1,FALSE),0) -> 0 | AJ1241: =IFERROR(VLOOKUP($A1241,pivot!$A:$I,計算式2026!AJ$1,FALSE),0) -> 0 | AK1241: =IFERROR(VLOOKUP($A1241,pivot!$A:$I,計算式2026!AK$1,FALSE),0) -> 0 | AL1241: =IFERROR(VLOOKUP($A1241,pivot!$A:$I,計算式2026!AL$1,FALSE),0) -> 0
A1242: 81523R03248 | B1242: High Coast Hike Trousers | C1242: 0 | D1242: 0 | E1242: 0 | F1242: 0 | G1242: 0 | H1242: 0 | I1242: 0 | J1242: 0 | K1242: 0 | R1242: 0 | S1242: 0 | T1242: 1 | U1242: 0 | V1242: 0 | W1242: 0 | X1242: 0 | AE1242: =IFERROR(VLOOKUP($A1242,pivot!$A:$G,計算式2026!AE$1,FALSE),0) -> 0 | AF1242: =IFERROR(VLOOKUP($A1242,pivot!$A:$I,計算式2026!AF$1,FALSE),0) -> 0 | AI1242: =IFERROR(VLOOKUP($A1242,pivot!$A:$I,計算式2026!AI$1,FALSE),0) -> 0 | AJ1242: =IFERROR(VLOOKUP($A1242,pivot!$A:$I,計算式2026!AJ$1,FALSE),0) -> 0 | AK1242: =IFERROR(VLOOKUP($A1242,pivot!$A:$I,計算式2026!AK$1,FALSE),0) -> 0 | AL1242: =IFERROR(VLOOKUP($A1242,pivot!$A:$I,計算式2026!AL$1,FALSE),0) -> 0
...

Sheet 手順
A1: ～手順～
A2: 店舗実績
B3: 営業日付別売上分析（旧） 前週月曜以降を日付指定してＣＳＶ
B4: 「営業日付別売上分析 貼り付け」シートにＣ～Ｋ列を列ごと貼り付け
B5: 「pivot」シート更新
A6: ZOZO&OIOI実績
B7: 売上明細でZOZO拠点220で日付を指定してＣＳＶ
B8: Ｃ～Ｋ列をZOZO,OIOIそれぞれの列に貼り付け、ピボットを更新
A9: EC実績
B10: MAKE SHOPの注文一覧よりＣＳＶをＤＬ
B11: Ｄ列：「キャンセル」行を削除 E列：【店舗客注】も行で削除
B12: 「EC_ORDER」シートに貼り付け
B13: 「EC_PIVOT」のピボットを更新
A15: 「計算式2026」シートを選択 | D15: → RETAILマクロがこの状態で組まれているので必ずこのシートに！
